Workbook

Sheet INDEX
A1: node_id | B1: category | C1: bestsellers_url | D1: listed_rows
A2: 11056291 | B2: Body Washes | C2: https://www.amazon.com/Best-Sellers/zgbs/beauty/11056291 | D2: =COUNT('Body Washes'!A:A)
A3: 11060451 | B3: Skin Care | C3: https://www.amazon.com/Best-Sellers/zgbs/beauty/11060451 | D3: =COUNT('Skin Care'!A:A)
A4: 11060521 | B4: Body | C4: https://www.amazon.com/Best-Sellers/zgbs/beauty/11060521 | D4: =COUNT('Body'!A:A)
A5: 11060661 | B5: Moisturizers | C5: https://www.amazon.com/Best-Sellers/zgbs/beauty/11060661 | D5: =COUNT('Moisturizers'!A:A)
A6: 11060711 | B6: Face | C6: https://www.amazon.com/Best-Sellers/zgbs/beauty/11060711 | D6: =COUNT('Face'!A:A)
A7: 11061941 | B7: Eyes | C7: https://www.amazon.com/Best-Sellers/zgbs/beauty/11061941 | D7: =COUNT('Eyes'!A:A)
A8: 11062651 | B8: Sunscreens | C8: https://www.amazon.com/Best-Sellers/zgbs/beauty/11062651 | D8: =COUNT('Sunscreens'!A:A)
A9: 7792528011 | B9: Serums | C9: https://www.amazon.com/Best-Sellers/zgbs/beauty/7792528011 | D9: =COUNT('Serums'!A:A)
A10: de:122877031 | B10: Fragrances | C10: https://www.amazon.com/Best-Sellers/zgbs/beauty/de:122877031 | D10: =COUNT('Fragrances'!A:A)
A11: de:122878031 | B11: Skin Care | C11: https://www.amazon.com/Best-Sellers/zgbs/beauty/de:122878031 | D11: =COUNT('Skin Care'!A:A)
A12: de:122880031 | B12: Make-up | C12: https://www.amazon.com/Best-Sellers/zgbs/beauty/de:122880031 | D12: =COUNT('Make-up'!A:A)
A13: de:64272031 | B13: Bath & Body | C13: https://www.amazon.com/Best-Sellers/zgbs/beauty/de:64272031 | D13: =COUNT('Bath & Body'!A:A)
A14: de:64486031 | B14: Hair Care | C14: https://www.amazon.com/Best-Sellers/zgbs/beauty/de:64486031 | D14: =COUNT('Hair Care'!A:A)
A15: es:4347676031 | B15: Bath & Body | C15: https://www.amazon.com/Best-Sellers/zgbs/beauty/es:4347676031 | D15: =COUNT('Bath & Body'!A:A)
A16: es:4347698031 | B16: Hair Care | C16: https://www.amazon.com/Best-Sellers/zgbs/beauty/es:4347698031 | D16: =COUNT('Hair Care'!A:A)
A17: es:6397798031 | B17: Fragrances | C17: https://www.amazon.com/Best-Sellers/zgbs/beauty/es:6397798031 | D17: =COUNT('Fragrances'!A:A)
A18: es:6397823031 | B18: Make-up | C18: https://www.amazon.com/Best-Sellers/zgbs/beauty/es:6397823031 | D18: =COUNT('Make-up'!A:A)
A19: es:6397934031 | B19: Skin Care | C19: https://www.amazon.com/Best-Sellers/zgbs/beauty/es:6397934031 | D19: =COUNT('Skin Care'!A:A)
A20: fr:210965031 | B20: Fragrances | C20: https://www.amazon.com/Best-Sellers/zgbs/beauty/fr:210965031 | D20: =COUNT('Fragrances'!A:A)
A21: fr:210972031 | B21: Make up | C21: https://www.amazon.com/Best-Sellers/zgbs/beauty/fr:210972031 | D21: =COUNT('Make up'!A:A)
A22: fr:211020031 | B22: Skin Care | C22: https://www.amazon.com/Best-Sellers/zgbs/beauty/fr:211020031 | D22: =COUNT('Skin Care'!A:A)
A23: fr:211038031 | B23: Hair Care | C23: https://www.amazon.com/Best-Sellers/zgbs/beauty/fr:211038031 | D23: =COUNT('Hair Care'!A:A)
A24: fr:212073031 | B24: Bath & Body | C24: https://www.amazon.com/Best-Sellers/zgbs/beauty/fr:212073031 | D24: =COUNT('Bath & Body'!A:A)
A25: uk:118423031 | B25: Make-up | C25: https://www.amazon.com/Best-Sellers/zgbs/beauty/uk:118423031 | D25: =COUNT('Make-up'!A:A)
A26: uk:118457031 | B26: Fragrances | C26: https://www.amazon.com/Best-Sellers/zgbs/beauty/uk:118457031 | D26: =COUNT('Fragrances'!A:A)
A27: uk:118464031 | B27: Skin Care | C27: https://www.amazon.com/Best-Sellers/zgbs/beauty/uk:118464031 | D27: =COUNT('Skin Care'!A:A)
A28: uk:66469031 | B28: Hair Care | C28: https://www.amazon.com/Best-Sellers/zgbs/beauty/uk:66469031 | D28: =COUNT('Hair Care'!A:A)
A29: uk:74129031 | B29: Bath & Body | C29: https://www.amazon.com/Best-Sellers/zgbs/beauty/uk:74129031 | D29: =COUNT('Bath & Body'!A:A)

Sheet Body Washes
A1: Amazon Best Sellers — Body Washes | I1: 🔗 Best Sellers 페이지 열기
A2: rank | B2: asin | C2: title | D2: rating | E2: ratings_count | F2: price | G2: currency | H2: offers_text | I2: url
A3: 1 | B3: B0DPHQRLJC | C3: eos Cashmere Body Wash- Vanilla Cashmere, Creamy Gel with Shea Butter, 16 fl oz | D3: 4.7 | E3: 23034 | F3: 9.98 | G3: USD | I3: https://www.amazon.com/eos-Moisturizing-Nourishing-Phthalate-Sensitive/dp/B0DPHQRLJC/ref=zg_bs_g_11056291_d_sccl_1/136-1893143-0116527
A4: 2 | B4: B00MEDOY2G | C4: Dove Body Wash Body Wash Deep Moisture 30.6 oz Pump, Sulfate Free | Dove Deep Moisture Body Wash hydrates dry skin for 24 hou | D4: 4.8 | E4: 86156 | F4: 10.99 | G4: USD | I4: https://www.amazon.com/Dove-24hr-Lotion-Body-Moisture/dp/B00MEDOY2G/ref=zg_bs_g_11056291_d_sccl_2/136-1893143-0116527
A5: 3 | B5: B0B1PDDLGZ | C5: Naturium The Glow Getter Multi-Oil Body Wash, 16.9 fl oz | Nourishing Gentle Cleanser, Dissolves Impurities, Hydrating Base P | D5: 4.6 | E5: 7549 | F5: 15.18 | G5: USD | I5: https://www.amazon.com/Getter-Multi-Oil-Hydrating-Naturium-Cleanser/dp/B0B1PDDLGZ/ref=zg_bs_g_11056291_d_sccl_3/136-1893143-0116527
A6: 4 | B6: B0BT1WL6KY | C6: method Body Wash, Simply Nourish, 28 fl oz | Soothing Formula, Leaves Skin Feeling Soft & Moisturized, Made Without Parabens, | D6: 4.7 | E6: 13383 | F6: 12 | G6: USD | I6: https://www.amazon.com/Method-Simply-Nourish-Paraben-Phthalate/dp/B0BT1WL6KY/ref=zg_bs_g_11056291_d_sccl_4/136-1893143-0116527
A7: 5 | B7: B09DDD6YGJ | C7: Dove Body Wash Antibacterial For All Skin Types 30.6 oz Pump, Sulfate Free | Dove Antibacterial Body Wash eliminates 99% of b | D7: 4.8 | E7: 6609 | F7: 10.97 | G7: USD | I7: https://www.amazon.com/Dove-Body-Wash-Care-Protect/dp/B09DDD6YGJ/ref=zg_bs_g_11056291_d_sccl_5/136-1893143-0116527
A8: 6 | B8: B00SK71SAG | C8: Dove Sensitive Skin Body Wash, 24hr Lotion-Soft Skin, 30.6 oz | Dove Sensitive Skin Body Wash soothes dry, sensitive skin wit | D8: 4.8 | E8: 63650 | F8: 10.97 | G8: USD | I8: https://www.amazon.com/Dove-24hr-Lotion-Body-Sensitive/dp/B00SK71SAG/ref=zg_bs_g_11056291_d_sccl_6/136-1893143-0116527
A9: 7 | B9: B09M7SPFSJ | C9: Ivory Body Wash, Designed for the Whole Family, Gentle Formula, Free of Dyes Heavy Perfumes Parabens Phthalates & Silicones, | D9: 4.8 | E9: 20424 | F9: 6.97 | G9: USD | I9: https://www.amazon.com/Designed-Perfumes-Parabens-Phthalates-Silicones/dp/B09M7SPFSJ/ref=zg_bs_g_11056291_d_sccl_7/136-1893143-0116527
A10: 8 | B10: B0B9CHS3LR | C10: Native Clean Body Wash, Gentle & pH-balanced for Sensitive Skin, 24-Hr Freshness for Women & Men, Vegan & Cruelty-Free, Free | D10: 4.6 | E10: 2244 | F10: 15.97 | G10: USD | I10: https://www.amazon.com/Native-pH-balanced-Sensitive-Cruelty-Free-Phthalates/dp/B0B9CHS3LR/ref=zg_bs_g_11056291_d_sccl_8/136-1893143-0116527
A11: 9 | B11: B0FY7963T5 | C11: Native Clean Body Wash, Gentle & pH-balanced for Sensitive Skin, 24-Hr Freshness for Men & Women, Vegan & Cruelty-Free, Free | D11: 4.6 | E11: 7025 | F11: 9.87 | G11: USD | I11: https://www.amazon.com/Native-pH-balanced-Sensitive-Cruelty-Free-Phthalates/dp/B0FY7963T5/ref=zg_bs_g_11056291_d_sccl_9/136-1893143-0116527
A12: 10 | B12: B0BT1WN3ZD | C12: method Men’s Body Wash, Sea + Surf Scent, 28 fl oz | Soothing Formula, Leaves Skin Feeling Soft & Moisturized, Rich Lather, M | D12: 4.7 | E12: 7132 | F12: 12 | G12: USD | I12: https://www.amazon.com/method-mens-Body-Wash-Surf/dp/B0BT1WN3ZD/ref=zg_bs_g_11056291_d_sccl_10/136-1893143-0116527
A13: 11 | B13: B09GN1YRVP | C13: Irish Spring Body Wash for Men, Original Scent, 887 mL | Face and Body Wash, Men’s Body Wash, Paraben-Free, Moisturizing, Ret | D13: 4.7 | E13: 27798 | F13: 6.94 | G13: USD | I13: https://www.amazon.com/Irish-Spring-Original-Clean-Body/dp/B09GN1YRVP/ref=zg_bs_g_11056291_d_sccl_11/136-1893143-0116527
A14: 12 | B14: B09G2S1KZ2 | C14: Salt & Stone Body Wash for Women & Men, Bergamot & Hinoki 15.2 fl oz | Shower Gel, Sulfate-Free, Paraben-Free, Dye-Free, Vega | D14: 4.3 | E14: 9092 | F14: 36 | G14: USD | I14: https://www.amazon.com/Salt-Stone-Antioxidant-Rich-Body-Wash/dp/B09G2S1KZ2/ref=zg_bs_g_11056291_d_sccl_12/136-1893143-0116527
... A32: 30 | B32: B0B3FVL358 | C32: Aveeno Kids Face & Body Wash, Sensitive Skin, 18 fl. oz | Nourishing Oat Extract Washes Away Dirt and Germs Without Drying, T | D32: 4.8 | E32: 5637 | F32: 10.98 | G32: USD | I32: https://www.amazon.com/Aveeno-Sensitive-Tear-Free-Suitable-Hypoallergenic/dp/B0B3FVL358/ref=zg_bs_g_11056291_d_sccl_30/136-1893143-0116527
A33: 31 | B33: B0CGYP4GYY
A34: 32 | B34: B0DGVP5ZPK
A35: 33 | B35: B0DB6BQ798
A36: 34 | B36: B07ND4W7WR
A37: 35 | B37: B0G4X32SPX
A38: 36 | B38: B07HHHMJ6V
A39: 37 | B39: B0FX5PDSZ2
A40: 38 | B40: B0G3XRG17W
A41: 39 | B41: B07FD24RTR
A42: 40 | B42: B08BJVHYSC
A43: 41 | B43: B0CNFGXBFY
A44: 42 | B44: B0FBGWN3YH
... A52: 50 | B52: B00ZY65OSI
A53: 51 | B53: B09DDD1VS7 | C53: Dove Body Wash Body Wash Gentle Exfoliate Sea Minerals 30.6 oz Sulfate Free | Dove Gentle Exfoliating Body Wash buffs away du | D53: 4.7 | E53: 2345 | F53: 10.97 | G53: USD | I53: https://www.amazon.com/Dove-Exfoliate-Minerals-Lotion-Soft-Moisturizing/dp/B09DDD1VS7/ref=zg_bs_g_11056291_d_sccl_1/136-1893143-0116527
A54: 52 | B54: B0G4B3XLT9 | C54: Olay Body Wash for Women, Fresh Radiance, 24/7 Skin-Loving Freshness, Visibly Radiant, Plant Based Cleansers, Vitamin B3 & An | D54: 4.8 | E54: 1426 | F54: 9.09 | G54: USD | I54: https://www.amazon.com/Olay-Skin-Loving-Freshness-Antioxidant-Strawberry/dp/B0G4B3XLT9/ref=zg_bs_g_11056291_d_sccl_2/136-1893143-0116527
A55: 53 | B55: B00OQ1ZKO0 | C55: NIVEA MEN Maximum Hydration 3-in-1 Body Wash, Multipack, 3 x 16.9 FL OZ | 3-in-1 Moisturizing Body Wash, Hair and Face Wash f | D55: 4.6 | E55: 31187 | F55: 13.11 | G55: USD | I55: https://www.amazon.com/NIVEA-Men-Maximum-Hydration-Body/dp/B00OQ1ZKO0/ref=zg_bs_g_11056291_d_sccl_3/136-1893143-0116527
A56: 54 | B56: B0BVNG2MB1 | C56: Saltair Body Wash 2-Pack | Santal Bloom Moisturizing Shower Gel | 2x 17oz | Gentle easy-rinsing lather for a comfortable stra | D56: 4.3 | E56: 3346 | F56: 28 | G56: USD | I56: https://www.amazon.com/Saltair-2-Pack-Moisturizing-Cleanser-Cruelty-Free/dp/B0BVNG2MB1/ref=zg_bs_g_11056291_d_sccl_4/136-1893143-0116527
A57: 55 | B57: B0DYKBCL5G | C57: Duke Cannon Supply Co. Thick High Viscosity Body Wash - 3X Thicker, Cleansing Shower and Bath Gel, Mineral-Enriched Body Wash | D57: 4.5 | E57: 1498 | F57: 7.98 | G57: USD | I57: https://www.amazon.com/Duke-Cannon-Supply-Co-Viscosity/dp/B0DYKBCL5G/ref=zg_bs_g_11056291_d_sccl_5/136-1893143-0116527
A58: 56 | B58: B0DNGVCCZ2 | C58: The Body Wash Eucalyptus. Multi-Oil Niacinamide Shower Gel Sensitive Skin | For Women & Men. Non-Comedogenic, Hypoallergenic | D58: 4.5 | E58: 2387 | F58: 42 | G58: USD | I58: https://www.amazon.com/Fragrance-Free-Multi-Oil-Niacinamide-Shower/dp/B0DNGVCCZ2/ref=zg_bs_g_11056291_d_sccl_6/136-1893143-0116527
A59: 57 | B59: B0DT529BQK | C59: Harry's Men's Body Wash - Stone - 18 fl oz (3 Pack) | Shower Gel for Men - No Parabens, Sulfates, or Dyes | D59: 4.6 | E59: 2903 | F59: 23.91 | G59: USD | I59: https://www.amazon.com/Harrys-Mens-Body-Wash-Parabens/dp/B0DT529BQK/ref=zg_bs_g_11056291_d_sccl_7/136-1893143-0116527
A60: 58 | B60: B001G60EK8 | C60: L'OCCITANE Almond Shower Oil, Cleansing Body Wash & Shaving Base, Vegan | Purifies & smooths, non-drying, milky lather, gentl | D60: 4.4 | E60: 17668 | F60: 29 | G60: USD | I60: https://www.amazon.com/LOccitane-Cleansing-Softening-Almond-Shower/dp/B001G60EK8/ref=zg_bs_g_11056291_d_sccl_8/136-1893143-0116527
A61: 59 | B61: B0CNKZW8HL | C61: Dove Men Moisturizing Body Wash, Sandalwood + Cardamom Oil, 26oz | For dry skin, Helps nourish and refresh, With plant-based | D61: 4.6 | E61: 6518 | F61: 10.97 | G61: USD | I61: https://www.amazon.com/DOVE-MEN-Moisturizing-Dermatologist-Sandalwood/dp/B0CNKZW8HL/ref=zg_bs_g_11056291_d_sccl_9/136-1893143-0116527
A62: 60 | B62: B0FC8SRSM4 | C62: Old Spice Body Wash for Men, Fallidudes Edition, 24/7 Frightful Freshness, Long Lasting Cleanse & Refresh, Rich Lather, PumpK | D62: 4.6 | E62: 2829 | F62: 7.99 | G62: USD | I62: https://www.amazon.com/Old-Spice-Holidudes-Freshness-Stocking/dp/B0FC8SRSM4/ref=zg_bs_g_11056291_d_sccl_10/136-1893143-0116527
A63: 61 | B63: B0CGZ4FWZG | C63: Dove Serum + Acne Clear Body Wash with 1% Salicylic Acid, 18.5 oz | For acne-prone skin, Helps clear and prevent acne, With 1 | D63: 4.6 | E63: 2470 | F63: 9.97 | G63: USD | I63: https://www.amazon.com/Dove-prevent-clearing-salicylic-treatment/dp/B0CGZ4FWZG/ref=zg_bs_g_11056291_d_sccl_11/136-1893143-0116527
A64: 62 | B64: B0CNBTJ6NY | C64: Dove Ultra Sensitive Serum Body Wash Fragrance Free 10 Ingredients, 18.5 oz | For sensitive skin, Helps moisturize skin, Frag | D64: 4.6 | E64: 2397 | F64: 9.97 | G64: USD | I64: https://www.amazon.com/Dove-Fragrance-Sensitive-essential-ingredients/dp/B0CNBTJ6NY/ref=zg_bs_g_11056291_d_sccl_12/136-1893143-0116527
... A82: 80 | B82: B0F1V9QCR6 | C82: Olay Body Wash for Women, Intensely Hydrating, Pro-Hyaluronic Acid Serum Complex, Renews Moisture, Vitamin B3 Lameller Techno | D82: 4.7 | E82: 10467 | F82: 10.99 | G82: USD | I82: https://www.amazon.com/Olay-Intensely-Pro-Hyaluronic-Technology-Strawberry/dp/B0F1V9QCR6/ref=zg_bs_g_11056291_d_sccl_30/136-1893143-0116527
A83: 81 | B83: B0DNSS8NQ7
A84: 82 | B84: B0GF9QF3SK
A85: 83 | B85: B09K3T8VSJ
A86: 84 | B86: B09Q59GC1K
A87: 85 | B87: B07QTTYTTL
A88: 86 | B88: B087LYWWW4
A89: 87 | B89: B0CNZ7FZM1
A90: 88 | B90: B0DSJWVXXJ
A91: 89 | B91: B0D8K482S6
A92: 90 | B92: B07Z7X5VCV
A93: 91 | B93: B08JNRP17W
A94: 92 | B94: B0CPLJR1XP
... A102: 100 | B102: B082QC2MCX

Sheet Skin Care
A1: Amazon Best Sellers — Skin Care | I1: 🔗 Best Sellers 페이지 열기
A2: rank | B2: asin | C2: title | D2: rating | E2: ratings_count | F2: price | G2: currency | H2: offers_text | I2: url
A3: 1 | B3: B09V7Z4TJG | C3: medicube Toner Pads Zero Pore Pad 2.0 for Exfoliation and Pore Care | Dual-Textured Facial Pad with 4.5% AHA Lactic Acid, 0.4 | D3: 4.6 | E3: 30722 | F3: 15.12 | G3: USD | I3: https://www.amazon.com/Medicube-Zero-Pore-Pads-Dual-Textured/dp/B09V7Z4TJG/ref=zg_bs_g_11060451_d_sccl_1/136-1893143-0116527
A4: 2 | B4: B08KT2Z93D | C4: eos Shea Better Body Lotion- Vanilla Cashmere, 24-Hour Moisture, 16 fl oz | D4: 4.7 | E4: 74360 | F4: 9.97 | G4: USD | I4: https://www.amazon.com/eos-Cashmere-Moisture-Lightweight-Non-Greasy/dp/B08KT2Z93D/ref=zg_bs_g_11060451_d_sccl_2/136-1893143-0116527
A5: 3 | B5: B07PBXXNCY | C5: Clean Skin Club Clean Towels XL®, 100% USDA Biobased Face Towel, Disposable Face Towelette, Eczema Association Accepted, Make | D5: 4.7 | E5: 51792 | F5: 17.95 | G5: USD | I5: https://www.amazon.com/Clean-Skin-Club-Disposable-Sensitive/dp/B07PBXXNCY/ref=zg_bs_g_11060451_d_sccl_3/136-1893143-0116527
A6: 4 | B6: B00F1U0YB4 | C6: Mrs. Meyer's Clean Day, Hand Soap Refill, Lemon Verbena Scent, 33 Fl Oz | D6: 4.7 | E6: 120923 | F6: 4.98 | G6: USD | I6: https://www.amazon.com/Mrs-Meyers-Clean-Refill-Verbena/dp/B00F1U0YB4/ref=zg_bs_g_11060451_d_sccl_4/136-1893143-0116527
A7: 5 | B7: B074PVTPBW | C7: Mighty Patch Hero Cosmetics Original Nighttime Acne Pimple Patches, 36 Ct | #1 Hydrocolloid Acne Patches, Shrinking Zits & Wh | D7: 4.6 | E7: 184770 | F7: 12.99 | G7: USD | I7: https://www.amazon.com/Mighty-Patch-Hydrocolloid-Absorbing-count/dp/B074PVTPBW/ref=zg_bs_g_11060451_d_sccl_5/136-1893143-0116527
A8: 6 | B8: B00U2VQZDS | C8: Neutrogena Makeup Remover Micellar Wipes, 2 Pack of 25 Ct | Plant-Based Micellar Water Cleansing Cloths, Gently Removes Oil, | D8: 4.8 | E8: 121294 | F8: 9.97 | G8: USD | I8: https://www.amazon.com/Neutrogena-Makeup-Remover-Micellar-Wipes/dp/B00U2VQZDS/ref=zg_bs_g_11060451_d_sccl_6/136-1893143-0116527
A9: 7 | B9: B071914GGL | C9: The Ordinary Glycolic Acid 7% Exfoliating Toner, Brightening and Smoothing Daily Toner for More Even-Looking Skin Tone | D9: 4.7 | E9: 61699 | F9: 13.5 | G9: USD | I9: https://www.amazon.com/Ordinary-Exfoliating-Brightening-Smoothing-Even-Looking/dp/B071914GGL/ref=zg_bs_g_11060451_d_sccl_7/136-1893143-0116527
A10: 8 | B10: B081KL2QYJ | C10: PanOxyl 10% Benzoyl Peroxide Acne Foaming Wash, Maximum Strength, Daily Acne-Fighting Face and Body Cleanser, Face Wash to Cl | D10: 4.6 | E10: 82880 | F10: 10.19 | G10: USD | I10: https://www.amazon.com/PanOxyl-Foaming-Peroxide-Strength-Antimicrobial/dp/B081KL2QYJ/ref=zg_bs_g_11060451_d_sccl_8/136-1893143-0116527
A11: 9 | B11: B0B2RM68G2 | C11: BIODANCE Bio-Collagen Real Deep Mask, Hydrating Overnight Hydrogel Face Mask, Pore Minimizing, Elasticity, Plumping, Travel E | D11: 4.5 | E11: 46170 | F11: 19 | G11: USD | I11: https://www.amazon.com/Biodance-Bio-Collagen-Tightening-Hydrating-Molecular/dp/B0B2RM68G2/ref=zg_bs_g_11060451_d_sccl_9/136-1893143-0116527
A12: 10 | B12: B0DPHQRLJC | C12: eos Cashmere Body Wash- Vanilla Cashmere, Creamy Gel with Shea Butter, 16 fl oz | D12: 4.7 | E12: 23034 | F12: 9.98 | G12: USD | I12: https://www.amazon.com/eos-Moisturizing-Nourishing-Phthalate-Sensitive/dp/B0DPHQRLJC/ref=zg_bs_g_11060451_d_sccl_10/136-1893143-0116527
A13: 11 | B13: B0DGPSZVW3 | C13: medicube Jelly Cream with Collagen & Niacinamide, 1.69 fl.oz | Freeze-Dried Hydrolyzed Collagen for Skin Barrier Hydration, 2 | D13: 4.5 | E13: 35843 | F13: 9.9 | G13: USD | I13: https://www.amazon.com/medicube-Collagen-Niacinamide-Freeze-Dried-Hydrolyzed/dp/B0DGPSZVW3/ref=zg_bs_g_11060451_d_sccl_11/136-1893143-0116527
A14: 12 | B14: B09HHDHXWX | C14: Amazon Basics Gentle & Mild Clear Liquid Hand Soap Refill, Triclosan-Free, Dermatologist-Tested, pH Balanced, Cruelty-Free, 5 | D14: 4.6 | E14: 45731 | F14: 5.15 | G14: USD | I14: https://www.amazon.com/Amazon-Basics-Gentle-Liquid-Triclosan-free/dp/B09HHDHXWX/ref=zg_bs_g_11060451_d_sccl_12/136-1893143-0116527
... A32: 30 | B32: B0D2Z3GGCY | C32: medicube Capsule Cream with Deep Vitamin C for Radiance | Liposome Vitamin C Golden Capsule for Radiance & Firm-Looking Skin | D32: 4.6 | E32: 26361 | F32: 16.9 | G32: USD | I32: https://www.amazon.com/medicube-Liposome-Radiance-Firm-Looking-Hydrating/dp/B0D2Z3GGCY/ref=zg_bs_g_11060451_d_sccl_30/136-1893143-0116527
A33: 31 | B33: B0B1PDDLGZ
A34: 32 | B34: B00365DABC
A35: 33 | B35: B0BRMYHMS5
A36: 34 | B36: B00949CTQQ
A37: 35 | B37: B0CZF2T7CK
A38: 36 | B38: B0BT1WL6KY
A39: 37 | B39: B0DWFLY18Y
A40: 38 | B40: B0GD6R7CFJ
A41: 39 | B41: B081FFRGZB
A42: 40 | B42: B0FKGJYFC8
A43: 41 | B43: B09DDD6YGJ
A44: 42 | B44: B06WD5J8KY
... A52: 50 | B52: B0BX2TZZWG
A53: 51 | B53: B0GVQ6NYR3 | C53: medicube PDRN Collagen Gua Sha Neck Wrinkle Cream - Firming, Contour Care | Built-In Gua Sha Massager with Volufiline 5% - Fo | D53: 4.4 | E53: 509 | F53: 22.9 | G53: USD | I53: https://www.amazon.com/medicube-PDRN-Collagen-Wrinkle-Cream/dp/B0GVQ6NYR3/ref=zg_bs_g_11060451_d_sccl_1/136-1893143-0116527
A54: 52 | B54: B09M7SPFSJ | C54: Ivory Body Wash, Designed for the Whole Family, Gentle Formula, Free of Dyes Heavy Perfumes Parabens Phthalates & Silicones, | D54: 4.8 | E54: 20424 | F54: 6.97 | G54: USD | I54: https://www.amazon.com/Designed-Perfumes-Parabens-Phthalates-Silicones/dp/B09M7SPFSJ/ref=zg_bs_g_11060451_d_sccl_2/136-1893143-0116527
A55: 53 | B55: B0060OUV5Y | C55: La Roche-Posay Cicaplast Balm B5, Barrier Repair Cream for Dry Skin | Skin healing cream with centella asiatica, shea butter | D55: 4.7 | E55: 22617 | F55: 18.99 | G55: USD | I55: https://www.amazon.com/Roche-Posay-Cicaplast-Baume-Multi-Purpose-Butter/dp/B0060OUV5Y/ref=zg_bs_g_11060451_d_sccl_3/136-1893143-0116527
A56: 54 | B56: B0B9CHS3LR | C56: Native Clean Body Wash, Gentle & pH-balanced for Sensitive Skin, 24-Hr Freshness for Women & Men, Vegan & Cruelty-Free, Free | D56: 4.6 | E56: 2244 | F56: 15.97 | G56: USD | I56: https://www.amazon.com/Native-pH-balanced-Sensitive-Cruelty-Free-Phthalates/dp/B0B9CHS3LR/ref=zg_bs_g_11060451_d_sccl_4/136-1893143-0116527
A57: 55 | B57: B0G38FGSKL | C57: medicube Eye Patch PDRN Caffeine Collagen - Firming Gel Patches, | Age-Defying Care with Retinol & Collagen - Gel Patches for | D57: 4.4 | E57: 982 | F57: 16.9 | G57: USD | I57: https://www.amazon.com/medicube-Caffeine-Collagen-appearance-Age-Defying/dp/B0G38FGSKL/ref=zg_bs_g_11060451_d_sccl_5/136-1893143-0116527
A58: 56 | B58: B0BWX6NZLT | C58: NOONI Korean Lip Oil - Applepeony - pH Color-Changing Plumping Lip Gloss | 24HR Hydration, Moisturizing Lip Oil, Natural Lip | D58: 4 | E58: 25865 | F58: 9.99 | G58: USD | I58: https://www.amazon.com/NOONI-Korean-Lip-Oil-Moisturizing/dp/B0BWX6NZLT/ref=zg_bs_g_11060451_d_sccl_6/136-1893143-0116527
A59: 57 | B59: B00SNPCSUY | C59: CeraVe Night Cream, Face Moisturizer, Skin Care for Dry Skin, 1.7oz | Skin Renewing Face Moisturizer with Hyaluronic Acid & P | D59: 4.6 | E59: 56956 | F59: 15.44 | G59: USD | I59: https://www.amazon.com/CeraVe-Skin-Renewing-Night-Cream/dp/B00SNPCSUY/ref=zg_bs_g_11060451_d_sccl_7/136-1893143-0116527
A60: 58 | B60: B084ZP848Y | C60: Blue Lizard Sensitive Mineral SPF 50 Sunscreen Lotion, 100% Mineral Sunscreen, UVA/UVB Protection, Infused with organic Aloe | D60: 4.4 | E60: 21370 | F60: 15.48 | G60: USD | I60: https://www.amazon.com/Blue-Lizard-Sensitive-Mineral-Sunscreen/dp/B084ZP848Y/ref=zg_bs_g_11060451_d_sccl_8/136-1893143-0116527
A61: 59 | B61: B0054LHI5A | C61: Burt's Bees 100% Natural Moisturizing Lip Balm (Original Beeswax) | D61: 4.8 | E61: 121440 | F61: 10.48 | G61: USD | I61: https://www.amazon.com/Burts-Bees-Moisturizing-Original-Peppermint/dp/B0054LHI5A/ref=zg_bs_g_11060451_d_sccl_9/136-1893143-0116527
A62: 60 | B62: B0FY7963T5 | C62: Native Clean Body Wash, Gentle & pH-balanced for Sensitive Skin, 24-Hr Freshness for Men & Women, Vegan & Cruelty-Free, Free | D62: 4.6 | E62: 7025 | F62: 9.87 | G62: USD | I62: https://www.amazon.com/Native-pH-balanced-Sensitive-Cruelty-Free-Phthalates/dp/B0FY7963T5/ref=zg_bs_g_11060451_d_sccl_10/136-1893143-0116527
A63: 61 | B63: B006IB5T4W | C63: Aquaphor Advanced Therapy Healing Ointment Skin Protectant, 14 OZ | Clinically Proven Skin Protectant Moisturizer for Cracked | D63: 4.8 | E63: 86898 | F63: 16.49 | G63: USD | I63: https://www.amazon.com/Aquaphor-Healing-Ointment-Moisturizing-Protectant/dp/B006IB5T4W/ref=zg_bs_g_11060451_d_sccl_11/136-1893143-0116527
A64: 62 | B64: B00I69SEK0 | C64: Dove Beauty Bar Soap Original 8 Count for Soft, Smooth Skin, with 1/4 Moisturizing Cream 3.75 oz | D64: 4.8 | E64: 12327 | F64: 12.97 | G64: USD | I64: https://www.amazon.com/Dove-Beauty-Bar-White/dp/B00I69SEK0/ref=zg_bs_g_11060451_d_sccl_12/136-1893143-0116527
... A82: 80 | B82: B09Y2JCYNK | C82: Vanicream Gentle Facial Cleaner, pH-Balanced Face Wash, 2.5 Fl Oz | Formulated without Common Irritants for Sensitive Skin, R | D82: 4.7 | E82: 35148 | F82: 5.72 | G82: USD | I82: https://www.amazon.com/Vanicream-Gentle-Facial-Cleanser-Formulated/dp/B09Y2JCYNK/ref=zg_bs_g_11060451_d_sccl_30/136-1893143-0116527
A83: 81 | B83: B0FGQ3J31K
A84: 82 | B84: B0DWMSM6Y9
A85: 83 | B85: B091NJQ29P
A86: 84 | B86: B09MFMCTRK
A87: 85 | B87: B07G1VKCND
A88: 86 | B88: B092RB7LQW
A89: 87 | B89: B0CCRWC6W9
A90: 88 | B90: B0FPQGLYK9
A91: 89 | B91: B01M4NFD2N
A92: 90 | B92: B09GN1YRVP
A93: 91 | B93: B07YLKXV11
A94: 92 | B94: B09G2S1KZ2
... A102: 100 | B102: B07ZDHQQW1

Sheet Body
A1: Amazon Best Sellers — Body | I1: 🔗 Best Sellers 페이지 열기
A2: rank | B2: asin | C2: title | D2: rating | E2: ratings_count | F2: price | G2: currency | H2: offers_text | I2: url
A3: 1 | B3: B08KT2Z93D | C3: eos Shea Better Body Lotion- Vanilla Cashmere, 24-Hour Moisture, 16 fl oz | D3: 4.7 | E3: 74360 | F3: 9.97 | G3: USD | I3: https://www.amazon.com/eos-Cashmere-Moisture-Lightweight-Non-Greasy/dp/B08KT2Z93D/ref=zg_bs_g_11060521_d_sccl_1/136-1893143-0116527
A4: 2 | B4: B00F1U0YB4 | C4: Mrs. Meyer's Clean Day, Hand Soap Refill, Lemon Verbena Scent, 33 Fl Oz | D4: 4.7 | E4: 120923 | F4: 7.61 | G4: USD | I4: https://www.amazon.com/Mrs-Meyers-Clean-Refill-Verbena/dp/B00F1U0YB4/ref=zg_bs_g_11060521_d_sccl_2/136-1893143-0116527
A5: 3 | B5: B0DPHQRLJC | C5: eos Cashmere Body Wash- Vanilla Cashmere, Creamy Gel with Shea Butter, 16 fl oz | D5: 4.7 | E5: 23034 | F5: 9.98 | G5: USD | I5: https://www.amazon.com/eos-Moisturizing-Nourishing-Phthalate-Sensitive/dp/B0DPHQRLJC/ref=zg_bs_g_11060521_d_sccl_3/136-1893143-0116527
A6: 4 | B6: B09HHDHXWX | C6: Amazon Basics Gentle & Mild Clear Liquid Hand Soap Refill, Triclosan-Free, Dermatologist-Tested, pH Balanced, Cruelty-Free, 5 | D6: 4.6 | E6: 45731 | F6: 5.15 | G6: USD | I6: https://www.amazon.com/Amazon-Basics-Gentle-Liquid-Triclosan-free/dp/B09HHDHXWX/ref=zg_bs_g_11060521_d_sccl_4/136-1893143-0116527
A7: 5 | B7: B00MEDOY2G | C7: Dove Body Wash Body Wash Deep Moisture 30.6 oz Pump, Sulfate Free | Dove Deep Moisture Body Wash hydrates dry skin for 24 hou | D7: 4.8 | E7: 86156 | F7: 10.99 | G7: USD | I7: https://www.amazon.com/Dove-24hr-Lotion-Body-Moisture/dp/B00MEDOY2G/ref=zg_bs_g_11060521_d_sccl_5/136-1893143-0116527
A8: 6 | B8: B07RK4HST7 | C8: CeraVe Daily Moisturizing Lotion, Face and Body Lotion, Skin care, 19oz | Hyaluronic Acid, Lotion For Dry Skin, Skin Barrier | D8: 4.7 | E8: 150328 | F8: 18.14 | G8: USD | I8: https://www.amazon.com/CeraVe-Moisturizing-Lotion-Hyaluronic-Fragrance/dp/B07RK4HST7/ref=zg_bs_g_11060521_d_sccl_6/136-1893143-0116527
A9: 7 | B9: B0B1PDDLGZ | C9: Naturium The Glow Getter Multi-Oil Body Wash, 16.9 fl oz | Nourishing Gentle Cleanser, Dissolves Impurities, Hydrating Base P | D9: 4.6 | E9: 7549 | F9: 15.18 | G9: USD | I9: https://www.amazon.com/Getter-Multi-Oil-Hydrating-Naturium-Cleanser/dp/B0B1PDDLGZ/ref=zg_bs_g_11060521_d_sccl_7/136-1893143-0116527
A10: 8 | B10: B0BT1WL6KY | C10: method Body Wash, Simply Nourish, 28 fl oz | Soothing Formula, Leaves Skin Feeling Soft & Moisturized, Made Without Parabens, | D10: 4.7 | E10: 13383 | F10: 12 | G10: USD | I10: https://www.amazon.com/Method-Simply-Nourish-Paraben-Phthalate/dp/B0BT1WL6KY/ref=zg_bs_g_11060521_d_sccl_8/136-1893143-0116527
A11: 9 | B11: B081FFRGZB | C11: Softsoap Antibacterial Liquid Hand Soap, White Tea & Berry Scent, 50 fl oz | Refill Size, Paraben-Free, Phthalate-Free, Bathr | D11: 4.6 | E11: 22355 | F11: 5.97 | G11: USD | I11: https://www.amazon.com/Softsoap-Antibacterial-Liquid-Refill-White/dp/B081FFRGZB/ref=zg_bs_g_11060521_d_sccl_9/136-1893143-0116527
A12: 10 | B12: B09DDD6YGJ | C12: Dove Body Wash Antibacterial For All Skin Types 30.6 oz Pump, Sulfate Free | Dove Antibacterial Body Wash eliminates 99% of b | D12: 4.8 | E12: 6609 | F12: 10.97 | G12: USD | I12: https://www.amazon.com/Dove-Body-Wash-Care-Protect/dp/B09DDD6YGJ/ref=zg_bs_g_11060521_d_sccl_10/136-1893143-0116527
A13: 11 | B13: B00SK71SAG | C13: Dove Sensitive Skin Body Wash, 24hr Lotion-Soft Skin, 30.6 oz | Dove Sensitive Skin Body Wash soothes dry, sensitive skin wit | D13: 4.8 | E13: 63650 | F13: 10.97 | G13: USD | I13: https://www.amazon.com/Dove-24hr-Lotion-Body-Sensitive/dp/B00SK71SAG/ref=zg_bs_g_11060521_d_sccl_11/136-1893143-0116527
A14: 12 | B14: B001ET7IQK | C14: Dove Beauty Bar Soap Sensitive, 8 Bars for Sensitive Skin, Fragrance Free and Hypoallergenic 3.75 oz | D14: 4.8 | E14: 18305 | F14: 12.97 | G14: USD | I14: https://www.amazon.com/Dove-Beauty-Sensitive-Skin-Count/dp/B001ET7IQK/ref=zg_bs_g_11060521_d_sccl_12/136-1893143-0116527
... A32: 30 | B32: B001459IEE | C32: Aveeno Daily Moisturizing Body Lotion for Normal to Dry Skin, Moisturizer with Soothing Prebiotic Oat, Non Greasy, Non Comedo | D32: 4.8 | E32: 58966 | F32: 9.97 | G32: USD | I32: https://www.amazon.com/Aveeno-Moisturizing-Soothing-Emollients-Fragrance-Free/dp/B001459IEE/ref=zg_bs_g_11060521_d_sccl_30/136-1893143-0116527
A33: 31 | B33: B00028EYJ8
A34: 32 | B34: B07ZDHQQW1
A35: 33 | B35: B084MVWG1F
A36: 34 | B36: B0CPCYP629
A37: 35 | B37: B0FPQ3Z16S
A38: 36 | B38: B09YZ16XCN
A39: 37 | B39: B007VC9DKI
A40: 38 | B40: B003BMJGKE
A41: 39 | B41: B0C5JWKLZG
A42: 40 | B42: B0034F9K36
A43: 41 | B43: B0F1QHNFJP
A44: 42 | B44: B079FV6PRH
... A52: 50 | B52: B0DNTZTS1L
A53: 51 | B53: B08KT2Y49F | C53: eos 24H Moisture Shea Better Body Lotion- Pomegranate Raspberry, 16 fl oz | D53: 4.7 | E53: 8855 | F53: 9.97 | G53: USD | I53: https://www.amazon.com/eos-Pomegranate-Raspberry-Lightweight-Non-Greasy/dp/B08KT2Y49F/ref=zg_bs_g_11060521_d_sccl_1/136-1893143-0116527
A54: 52 | B54: B075X2KL5C | C54: Aveeno Skin Relief Body Wash with Triple Oat Complex, Fragrance-Free, Gentle Daily Body Wash for Sensitive Skin Leaves Itchy, | D54: 4.6 | E54: 40828 | F54: 12.97 | G54: USD | I54: https://www.amazon.com/Aveeno-Fragrance-Free-Soap-Free-Dye-Free-Sensitive/dp/B075X2KL5C/ref=zg_bs_g_11060521_d_sccl_2/136-1893143-0116527
A55: 53 | B55: B08TKNMW1Z | C55: Dove Men Body & Face Wash Clean Comfort Men's Body Wash with 30 oz | For dry skin, Helps hydrate and smooth skin, With Micro | D55: 4.8 | E55: 3221 | F55: 10.97 | G55: USD | I55: https://www.amazon.com/DOVE-MEN-CARE-Clean-Comfort/dp/B08TKNMW1Z/ref=zg_bs_g_11060521_d_sccl_3/136-1893143-0116527
A56: 54 | B56: B0FNWJFQFM | C56: medicube Kojic Acid Turmeric Brightening Body Wash, 13.52 fl.oz | Shower Gel for Uneven Skin - Niacinamide, Vitamin C, AHA BH | D56: 4.6 | E56: 1367 | F56: 15.12 | G56: USD | I56: https://www.amazon.com/medicube-Brightening-Niacinamide-Cleansing-Hydrating/dp/B0FNWJFQFM/ref=zg_bs_g_11060521_d_sccl_4/136-1893143-0116527
A57: 55 | B57: B0G3XN8152 | C57: Olay Body Wash for Women, Ultra Moisture, 24/7 Moisture Barrier Repair, Hydrating Formula for Visibly Healthy Soft Skin, Vita | D57: 4.8 | E57: 9106 | F57: 10.97 | G57: USD | I57: https://www.amazon.com/Olay-Moisture-Barrier-Hydrating-Hyaluronic/dp/B0G3XN8152/ref=zg_bs_g_11060521_d_sccl_5/136-1893143-0116527
A58: 56 | B58: B0DP37D91R | C58: Mirai Clinical Persimmon Soap for Old People Smell,Nonenal® Odor Eliminator | Japanese Persimmon Soap, Natural Body Odor Soap | D58: 4.3 | E58: 2371 | F58: 17.95 | G58: USD | I58: https://www.amazon.com/MIRAI-Clinical-Persimmon-Soap-Body/dp/B0DP37D91R/ref=zg_bs_g_11060521_d_sccl_6/136-1893143-0116527
A59: 57 | B59: B0CMW64H59 | C59: Cremo Body Wash for Men, Italian Bergamot, 16 Fl Oz | Rich-lathering mens body wash, Moisturizing shower gel, Italian bergamo | D59: 4.6 | E59: 13590 | F59: 9.97 | G59: USD | I59: https://www.amazon.com/Cremo-Rich-Lathering-Italian-Bergamot-Blossom/dp/B0CMW64H59/ref=zg_bs_g_11060521_d_sccl_7/136-1893143-0116527
A60: 58 | B60: B0CK4YS1SV | C60: Dr Teal's Body Wash with Pure Epsom Salt, Relax & Relief with Eucalyptus & Spearmint, 24 fl oz (Pack of 2) | D60: 4.8 | E60: 11542 | F60: 11.74 | G60: USD | I60: https://www.amazon.com/Dr-Teals-Eucalyptus-Spearmint-Packaging/dp/B0CK4YS1SV/ref=zg_bs_g_11060521_d_sccl_8/136-1893143-0116527
A61: 59 | B61: B0BJMSH4JX | C61: Hearth & Homestead Whipped Beef Tallow for Skin & Face, Unscented, 1.3oz | 100% Grass Fed & Finished, Eczema Cream & Body But | D61: 4.6 | E61: 14479 | F61: 26.97 | G61: USD | I61: https://www.amazon.com/Hearth-Homestead-Handmade-Whipped-Unscented/dp/B0BJMSH4JX/ref=zg_bs_g_11060521_d_sccl_9/136-1893143-0116527
A62: 60 | B62: B0FKC23886 | C62: Jergens Shea Fusion Vanilla Crush Body Lotion, Dry Skin, 14 fl oz | Shea Butter and Vitamin E Moisturizing Lotion, Vanilla Sc | D62: 4.5 | E62: 5043 | F62: 6.99 | G62: USD | I62: https://www.amazon.com/Jergens-Fusion-Vanilla-Moisturizer-Vitamin/dp/B0FKC23886/ref=zg_bs_g_11060521_d_sccl_10/136-1893143-0116527
A63: 61 | B63: B002TSA90M | C63: DOVE MEN + CARE 3 in Cleanser for Body, Face, and Shaving 1 Bar 3.75 oz | For dry skin, Helps cleanse and hydrate, With 1/4 m | D63: 4.7 | E63: 14498 | F63: 12.97 | G63: USD | I63: https://www.amazon.com/Cleanser-Shaving-Facial-Moisturizing-Hydrate/dp/B002TSA90M/ref=zg_bs_g_11060521_d_sccl_11/136-1893143-0116527
A64: 62 | B64: B07MG5YJLT | C64: Mrs. Meyer's Clean Day, Hand Soap, Rain Water Scent, 12.5 Fl Oz | D64: 4.7 | E64: 23736 | F64: 4.45 | G64: USD | I64: https://www.amazon.com/Mrs-Meyers-Clean-Water-Scent/dp/B07MG5YJLT/ref=zg_bs_g_11060521_d_sccl_12/136-1893143-0116527
... A82: 80 | B82: B0013OJUY4 | C82: Aveeno Skin Relief Moisturizing Body Lotion Heals Very Dry, Sensitive Skin, Fast Absorbing Lotion with Soothing Triple Oat & | D82: 4.7 | E82: 31913 | F82: 7.49 | G82: USD | I82: https://www.amazon.com/Aveeno-Moisturizing-Sensitive-Fast-Absorbing-Non-Comedogenic/dp/B0013OJUY4/ref=zg_bs_g_11060521_d_sccl_30/136-1893143-0116527
A83: 81 | B83: B01B5D3VOC
A84: 82 | B84: B0D4NKT1TH
A85: 83 | B85: B0DT5CJHQ4
A86: 84 | B86: B000RGBWPO
A87: 85 | B87: B004AI97MA
A88: 86 | B88: B0F8P4CF73
A89: 87 | B89: B0B3FVL358
A90: 88 | B90: B0CGYP4GYY
A91: 89 | B91: B088FXJ2LT
A92: 90 | B92: B0DGVP5ZPK
A93: 91 | B93: B0DB6BQ798
A94: 92 | B94: B07ND4W7WR
... A102: 100 | B102: B08D43LHYP

Sheet Moisturizers
A1: Amazon Best Sellers — Moisturizers | I1: 🔗 Best Sellers 페이지 열기
A2: rank | B2: asin | C2: title | D2: rating | E2: ratings_count | F2: price | G2: currency | H2: offers_text | I2: url
A3: 1 | B3: B08KT2Z93D | C3: eos Shea Better Body Lotion- Vanilla Cashmere, 24-Hour Moisture, 16 fl oz | D3: 4.7 | E3: 74360 | F3: 9.97 | G3: USD | I3: https://www.amazon.com/eos-Cashmere-Moisture-Lightweight-Non-Greasy/dp/B08KT2Z93D/ref=zg_bs_g_11060661_d_sccl_1/136-1893143-0116527
A4: 2 | B4: B07RK4HST7 | C4: CeraVe Daily Moisturizing Lotion, Face and Body Lotion, Skin care, 19oz | Hyaluronic Acid, Lotion For Dry Skin, Skin Barrier | D4: 4.7 | E4: 150328 | F4: 18.14 | G4: USD | I4: https://www.amazon.com/CeraVe-Moisturizing-Lotion-Hyaluronic-Fragrance/dp/B07RK4HST7/ref=zg_bs_g_11060661_d_sccl_2/136-1893143-0116527
A5: 3 | B5: B07BRDVQ4B | C5: AmLactin Daily Nourish Body Lotion, 12% Lactic Acid, 14.1 oz | 12% lactic acid body lotion exfoliates and moisturizes dry ski | D5: 4.4 | E5: 36976 | F5: 15.97 | G5: USD | I5: https://www.amazon.com/AmLactin-Moisturizing-Lotion-Bottle-Paraben/dp/B07BRDVQ4B/ref=zg_bs_g_11060661_d_sccl_3/136-1893143-0116527
A6: 4 | B6: B0060OUV5Y | C6: La Roche-Posay Cicaplast Balm B5, Barrier Repair Cream for Dry Skin | Skin healing cream with centella asiatica, shea butter | D6: 4.7 | E6: 22617 | F6: 18.99 | G6: USD | I6: https://www.amazon.com/Roche-Posay-Cicaplast-Baume-Multi-Purpose-Butter/dp/B0060OUV5Y/ref=zg_bs_g_11060661_d_sccl_4/136-1893143-0116527
A7: 5 | B7: B006IB5T4W | C7: Aquaphor Advanced Therapy Healing Ointment Skin Protectant, 14 OZ | Clinically Proven Skin Protectant Moisturizer for Cracked | D7: 4.8 | E7: 86898 | F7: 16.49 | G7: USD | I7: https://www.amazon.com/Aquaphor-Healing-Ointment-Moisturizing-Protectant/dp/B006IB5T4W/ref=zg_bs_g_11060661_d_sccl_5/136-1893143-0116527
A8: 6 | B8: B0D7XXQYNH | C8: Olay Body Lotion for Women, Firming with Collagen Peptides Serum, Visibly Firmer Skin, 24hr Moisture & Hydration, Fast Absorb | D8: 4.6 | E8: 15683 | F8: 9.97 | G8: USD | I8: https://www.amazon.com/Olay-Hydrating-Collagen-Moisturizing-Absorbing/dp/B0D7XXQYNH/ref=zg_bs_g_11060661_d_sccl_6/136-1893143-0116527
A9: 7 | B9: B0107QPFBU | C9: Aquaphor Advanced Therapy Healing Ointment, Skin Protectant, 7 OZ | Clinically Proven Skin Protectant Moisturizer for Cracked | D9: 4.8 | E9: 44924 | F9: 12.19 | G9: USD | I9: https://www.amazon.com/Aquaphor-Advanced-Therapy-Ointment-Protectant/dp/B0107QPFBU/ref=zg_bs_g_11060661_d_sccl_7/136-1893143-0116527
A10: 8 | B10: B099N1LC4R | C10: Cetaphil Moisturizing Cream, Face & Body Lotion Dry Sensitive Skin, 20oz | Fragrance-Free, Non-Comedogenic, Non-Greasy, Hydra | D10: 4.8 | E10: 40307 | F10: 14.12 | G10: USD | I10: https://www.amazon.com/Cetaphil-Moisturizing-Cream-Lotion-Sensitive/dp/B099N1LC4R/ref=zg_bs_g_11060661_d_sccl_8/136-1893143-0116527
A11: 9 | B11: B003QXZWYW | C11: La Roche-Posay Lipikar AP+MAX Triple Repair Moisturizing Body Cream | Face and body lotion for dry skin with shea butter and | D11: 4.6 | E11: 42015 | F11: 21.99 | G11: USD | I11: https://www.amazon.com/Roche-Posay-Lipikar-Intense-Repair-Cream/dp/B003QXZWYW/ref=zg_bs_g_11060661_d_sccl_9/136-1893143-0116527
A12: 10 | B12: B001459IEE | C12: Aveeno Daily Moisturizing Body Lotion for Normal to Dry Skin, Moisturizer with Soothing Prebiotic Oat, Non Greasy, Non Comedo | D12: 4.8 | E12: 58966 | F12: 9.97 | G12: USD | I12: https://www.amazon.com/Aveeno-Moisturizing-Soothing-Emollients-Fragrance-Free/dp/B001459IEE/ref=zg_bs_g_11060661_d_sccl_10/136-1893143-0116527
A13: 11 | B13: B0CPCYP629 | C13: eos 24H Moisture Travel Body Lotion- Vanilla Cashmere, 2.5 fl oz | D13: 4.8 | E13: 5900 | F13: 3.99 | G13: USD | I13: https://www.amazon.com/eos-Moisture-Lotion-Cashmere-Skincare/dp/B0CPCYP629/ref=zg_bs_g_11060661_d_sccl_11/136-1893143-0116527
A14: 12 | B14: B0FPQ3Z16S | C14: medicube Jelly Cream with Hyaluronic Acid for Long-lasting Hydration | Daily Moisturizer with Hyaluronic Acid, Ceramides, Mul | D14: 4.5 | E14: 35843 | F14: 9.9 | G14: USD | I14: https://www.amazon.com/medicube-Hyaluronic-Moisturizer-Long-lasting-Hydration/dp/B0FPQ3Z16S/ref=zg_bs_g_11060661_d_sccl_12/136-1893143-0116527
... A32: 30 | B32: B000RGBWPO | C32: Palmer's Solid Body Lotion, Cocoa Butter Formula with Vitamin E (7.25 Oz) | Body Moisturizer with Vitamin E for Extremely Dry | D32: 4.8 | E32: 36159 | F32: 7.16 | G32: USD | I32: https://www.amazon.com/Palmers-Formula-Therapy-Moisturizer-Extremely/dp/B000RGBWPO/ref=zg_bs_g_11060661_d_sccl_30/136-1893143-0116527
A33: 31 | B33: B004AI97MA
A34: 32 | B34: B000OYJ9AO
A35: 33 | B35: B08D43LHYP
A36: 34 | B36: B07H3YJD3R
A37: 35 | B37: B0FG8K9QYK
A38: 36 | B38: B0CWVSNVG6
A39: 37 | B39: B00BWTKA94
A40: 38 | B40: B08Q1J3V2T
A41: 39 | B41: B0CH9K3P3R
A42: 40 | B42: B0FD8W456T
A43: 41 | B43: B07SWJ5PVH
A44: 42 | B44: B00KTLXB4C
... A52: 50 | B52: B0071XPQQ2
A53: 51 | B53: B00DG8EZKO | C53: NIVEA Intense Healing Body Lotion, 72-Hour Moisturizing Lotion,16.9 FL OZ | Moisturizing Lotion with Glycerin, Provitamin B5 | D53: 4.7 | E53: 30487 | F53: 7.17 | G53: USD | I53: https://www.amazon.com/NIVEA-Intense-Healing-Body-Lotion/dp/B00DG8EZKO/ref=zg_bs_g_11060661_d_sccl_1/136-1893143-0116527
A54: 52 | B54: B000XY9LT4 | C54: Eucerin Intensive Repair Body Lotion with Urea, AHA and NMF, 16.9 FL OZ | Body Lotion for Dry, Flaky Skin, Enriched with Urea | D54: 4.7 | E54: 26765 | F54: 13.69 | G54: USD | I54: https://www.amazon.com/Eucerin-Intensive-Repair-Lotion-Bottle/dp/B000XY9LT4/ref=zg_bs_g_11060661_d_sccl_2/136-1893143-0116527
A55: 53 | B55: B0019LWU2K | C55: NOW Foods Solutions, Vegetable Glycerin, 100% Pure, Versatile Skin Care, Softening and Moisturizing, 16-Ounce | D55: 4.7 | E55: 48194 | F55: 8.56 | G55: USD | I55: https://www.amazon.com/Solutions-Vegetable-Versatile-Softening-Moisturizing/dp/B0019LWU2K/ref=zg_bs_g_11060661_d_sccl_3/136-1893143-0116527
A56: 54 | B56: B075G3RJDZ | C56: Lubriderm Daily Moisture Body Lotion, Fragrance Free, 24 fl. oz | Hydrating Face, Hand & Body Lotion + Pro-Ceramide for Sensi | D56: 4.8 | E56: 21826 | F56: 9.59 | G56: USD | I56: https://www.amazon.com/Lubriderm-Moisture-Lotion-Fragrance-Free-Normal/dp/B075G3RJDZ/ref=zg_bs_g_11060661_d_sccl_4/136-1893143-0116527
A57: 55 | B57: B09YT7WTFS | C57: Naturium Bio-Lipid Restoring Body Lotion, All Day Moisture, 14 fl oz | Nourishing Moisturizer with Shea Butter, Skin Hydratin | D57: 4.5 | E57: 3023 | F57: 14.88 | G57: USD | I57: https://www.amazon.com/Naturium-Bio-Lipid-Restoring-Moisturizing-Fragrance/dp/B09YT7WTFS/ref=zg_bs_g_11060661_d_sccl_5/136-1893143-0116527
A58: 56 | B58: B076G2XGY3 | C58: NIVEA Essentially Enriched Body Lotion, Value Pack, 2 x 16.9 FL OZ | Hydrating Body Lotion with Hyaluronic Acid, Almond Oil a | D58: 4.6 | E58: 25747 | F58: 13.47 | G58: USD | I58: https://www.amazon.com/NIVEA-Essentially-Enriched-Lotion-Fluid/dp/B076G2XGY3/ref=zg_bs_g_11060661_d_sccl_6/136-1893143-0116527
A59: 57 | B59: B01H6OYPU8 | C59: NIVEA Cocoa Butter Body Cream with Hyaluronic Acid, 16 OZ | Cocoa Butter Body Cream with Hyaluronic Acid and Deep Nourishing | D59: 4.7 | E59: 28798 | F59: 7.26 | G59: USD | I59: https://www.amazon.com/NIVEA-Hyaluronic-Nourishing-72-Hour-Moisturizer/dp/B01H6OYPU8/ref=zg_bs_g_11060661_d_sccl_7/136-1893143-0116527
A60: 58 | B60: B00DEX61A8 | C60: NIVEA MEN Maximum Hydration Lotion, 48-Hour Body Moisturizer, 16.9 FL OZ | Aloe Vera Body Lotion for Men, 3-in-1 Lotion for B | D60: 4.7 | E60: 25172 | F60: 7.26 | G60: USD | I60: https://www.amazon.com/NIVEA-MEN-Hydration-Moisture-Dermatologically-Tested/dp/B00DEX61A8/ref=zg_bs_g_11060661_d_sccl_8/136-1893143-0116527
A61: 59 | B61: B09HHBYQXY | C61: Amazon Essentials Petroleum Jelly White Petrolatum Skin Protectant, Unscented, 3.75 Ounce, 1-Pack (Previously Amazon Basics) | D61: 4.7 | E61: 8222 | F61: 4.18 | G61: USD | I61: https://www.amazon.com/Amazon-Basics-Petroleum-Petrolatum-Protectant/dp/B09HHBYQXY/ref=zg_bs_g_11060661_d_sccl_9/136-1893143-0116527
A62: 60 | B62: B013XKHA4M | C62: Sol de Janeiro Brazilian Bum Bum Cream Visibly Firming Body Cream | Iconic Cheirosa 62 Scent | D62: 4.6 | E62: 55088 | F62: 48 | G62: USD | I62: https://www.amazon.com/Sol-Janeiro-Brazilian-Bum-Cream/dp/B013XKHA4M/ref=zg_bs_g_11060661_d_sccl_10/136-1893143-0116527
A63: 61 | B63: B0009F3O8Q | C63: Palmer's Cocoa Butter Body Lotion Formula, Daily Skin Therapy (13.5 Fl Oz) | Intensive Moisturizer Enriched with Vitamin E to | D63: 4.8 | E63: 44127 | F63: 6.69 | G63: USD | I63: https://www.amazon.com/Palmers-Butter-Formula-Therapy-Moisturization/dp/B0009F3O8Q/ref=zg_bs_g_11060661_d_sccl_11/136-1893143-0116527
A64: 62 | B64: B0CXF7PXCF | C64: Naturium The Glow Getter Multi-Oil Body Butter, 7.7 fl oz | Nourishing Whipped Moisturizer, Oil Infused Formula with Shea But | D64: 4.4 | E64: 2985 | F64: 17.88 | G64: USD | I64: https://www.amazon.com/Naturium-Whipped-Multi-Oil-Firming-Moisturizer/dp/B0CXF7PXCF/ref=zg_bs_g_11060661_d_sccl_12/136-1893143-0116527
... A82: 80 | B82: B00QVNKSA2 | C82: Peppermint Essential Oil 4 oz. with Huge Glass Bottle, Glass Dropper, and Sprayer. Detailed User's Guide E-Book. Skin Care, G | D82: 4.6 | E82: 15716 | F82: 9.99 | G82: USD | I82: https://www.amazon.com/Peppermint-Essential-Detailed-Dropper-Essentially/dp/B00QVNKSA2/ref=zg_bs_g_11060661_d_sccl_30/136-1893143-0116527
A83: 81 | B83: B0F2ZTCZ7C
A84: 82 | B84: B01HTJTV4U
A85: 83 | B85: B08G9K79FC
A86: 84 | B86: B07DJWZLQL
A87: 85 | B87: B0CSTCYSF7
A88: 86 | B88: B0D1QYBNNQ
A89: 87 | B89: B093ZCZN92
A90: 88 | B90: B001ECQ4L2
A91: 89 | B91: B002FJ11UW
A92: 90 | B92: B000NB9LLA
A93: 91 | B93: B000VPPUEA
A94: 92 | B94: B071WJB3ZT
... A102: 100 | B102: B0DJMJS2Y3

Sheet Face
A1: Amazon Best Sellers — Face | I1: 🔗 Best Sellers 페이지 열기
A2: rank | B2: asin | C2: title | D2: rating | E2: ratings_count | F2: price | G2: currency | H2: offers_text | I2: url
A3: 1 | B3: B09V7Z4TJG | C3: medicube Toner Pads Zero Pore Pad 2.0 for Exfoliation and Pore Care | Dual-Textured Facial Pad with 4.5% AHA Lactic Acid, 0.4 | D3: 4.6 | E3: 30722 | F3: 15.12 | G3: USD | I3: https://www.amazon.com/Medicube-Zero-Pore-Pads-Dual-Textured/dp/B09V7Z4TJG/ref=zg_bs_g_11060711_d_sccl_1/136-1893143-0116527
A4: 2 | B4: B07PBXXNCY | C4: Clean Skin Club Clean Towels XL®, 100% USDA Biobased Face Towel, Disposable Face Towelette, Eczema Association Accepted, Make | D4: 4.7 | E4: 51792 | F4: 17.95 | G4: USD | I4: https://www.amazon.com/Clean-Skin-Club-Disposable-Sensitive/dp/B07PBXXNCY/ref=zg_bs_g_11060711_d_sccl_2/136-1893143-0116527
A5: 3 | B5: B074PVTPBW | C5: Mighty Patch Hero Cosmetics Original Nighttime Acne Pimple Patches, 36 Ct | #1 Hydrocolloid Acne Patches, Shrinking Zits & Wh | D5: 4.6 | E5: 184770 | F5: 12.99 | G5: USD | I5: https://www.amazon.com/Mighty-Patch-Hydrocolloid-Absorbing-count/dp/B074PVTPBW/ref=zg_bs_g_11060711_d_sccl_3/136-1893143-0116527
A6: 4 | B6: B00U2VQZDS | C6: Neutrogena Makeup Remover Micellar Wipes, 2 Pack of 25 Ct | Plant-Based Micellar Water Cleansing Cloths, Gently Removes Oil, | D6: 4.8 | E6: 121294 | F6: 9.97 | G6: USD | I6: https://www.amazon.com/Neutrogena-Makeup-Remover-Micellar-Wipes/dp/B00U2VQZDS/ref=zg_bs_g_11060711_d_sccl_4/136-1893143-0116527
A7: 5 | B7: B071914GGL | C7: The Ordinary Glycolic Acid 7% Exfoliating Toner, Brightening and Smoothing Daily Toner for More Even-Looking Skin Tone | D7: 4.7 | E7: 61699 | F7: 13.5 | G7: USD | I7: https://www.amazon.com/Ordinary-Exfoliating-Brightening-Smoothing-Even-Looking/dp/B071914GGL/ref=zg_bs_g_11060711_d_sccl_5/136-1893143-0116527
A8: 6 | B8: B081KL2QYJ | C8: PanOxyl 10% Benzoyl Peroxide Acne Foaming Wash, Maximum Strength, Daily Acne-Fighting Face and Body Cleanser, Face Wash to Cl | D8: 4.6 | E8: 82880 | F8: 10.19 | G8: USD | I8: https://www.amazon.com/PanOxyl-Foaming-Peroxide-Strength-Antimicrobial/dp/B081KL2QYJ/ref=zg_bs_g_11060711_d_sccl_6/136-1893143-0116527
A9: 7 | B9: B0B2RM68G2 | C9: BIODANCE Bio-Collagen Real Deep Mask, Hydrating Overnight Hydrogel Face Mask, Pore Minimizing, Elasticity, Plumping, Travel E | D9: 4.5 | E9: 46170 | F9: 19 | G9: USD | I9: https://www.amazon.com/Biodance-Bio-Collagen-Tightening-Hydrating-Molecular/dp/B0B2RM68G2/ref=zg_bs_g_11060711_d_sccl_7/136-1893143-0116527
A10: 8 | B10: B0DGPSZVW3 | C10: medicube Jelly Cream with Collagen & Niacinamide, 1.69 fl.oz | Freeze-Dried Hydrolyzed Collagen for Skin Barrier Hydration, 2 | D10: 4.5 | E10: 35843 | F10: 9.9 | G10: USD | I10: https://www.amazon.com/medicube-Collagen-Niacinamide-Freeze-Dried-Hydrolyzed/dp/B0DGPSZVW3/ref=zg_bs_g_11060711_d_sccl_8/136-1893143-0116527
A11: 9 | B11: B08BW46XXK | C11: Vanicream Daily Facial Moisturizer, Lightweight, Non-Greasy, 3 Fl Oz | Formulated Without Common Irritants for Sensitive Skin | D11: 4.6 | E11: 25513 | F11: 13.97 | G11: USD | I11: https://www.amazon.com/Vanicream-Moisturizer-Hyaluronic-pH-Balanced-Dermatologist/dp/B08BW46XXK/ref=zg_bs_g_11060711_d_sccl_9/136-1893143-0116527
A12: 10 | B12: B0DBF65JYY | C12: medicube PDRN Pink Peptide Serum with Salmon DNA | Pink Glow Serum - Peptides & Niacinamide for Hydration & Firm-Looking Skin | D12: 4.6 | E12: 21102 | F12: 15.12 | G12: USD | I12: https://www.amazon.com/medicube-Niacinamide-Hydrating-Moisturizing-Skincare/dp/B0DBF65JYY/ref=zg_bs_g_11060711_d_sccl_10/136-1893143-0116527
A13: 11 | B13: B0DYTQ5GYQ | C13: medicube Facial Cleanser Zero Pore Capsule Cleansing Foam | Daily Gentle Cleanser for Skin Texture, Blackhead & Pore Care - A | D13: 4.6 | E13: 3810 | F13: 12.9 | G13: USD | I13: https://www.amazon.com/medicube-Cleanser-Blackhead-Cleansing-Skincare/dp/B0DYTQ5GYQ/ref=zg_bs_g_11060711_d_sccl_11/136-1893143-0116527
A14: 12 | B14: B01N9SPQHQ | C14: La Roche-Posay Toleriane Double Repair Face Moisturizer | D14: 4.6 | E14: 51318 | F14: 24.99 | G14: USD | I14: https://www.amazon.com/Roche-Posay-Toleriane-Double-Repair-Moisturizer/dp/B01N9SPQHQ/ref=zg_bs_g_11060711_d_sccl_12/136-1893143-0116527
... A32: 30 | B32: B01N7T7JKJ | C32: La Roche-Posay Toleriane Hydrating Gentle Facial Cleanser, with Niacinamide | Face cleanser with niacinamide & ceramides, saf | D32: 4.6 | E32: 39523 | F32: 19.99 | G32: USD | I32: https://www.amazon.com/Roche-Posay-Toleriane-Hydrating-Gentle-Cleanser/dp/B01N7T7JKJ/ref=zg_bs_g_11060711_d_sccl_30/136-1893143-0116527
A33: 31 | B33: B0DK4Y2YP3
A34: 32 | B34: B0DG1DQ2S7
A35: 33 | B35: B0GVQ6NYR3
A36: 34 | B36: B00SNPCSUY
A37: 35 | B37: B0BFQ9RD5B
A38: 36 | B38: B0DFY92NDB
A39: 37 | B39: B0FVT77ZLL
A40: 38 | B40: B0BBSP2JNQ
A41: 39 | B41: B0D8W1YVBX
A42: 40 | B42: B0C3PCJ6SD
A43: 41 | B43: B07VRFC3Y7
A44: 42 | B44: B07XC569XF
... A52: 50 | B52: B01M4NFD2N
A53: 51 | B53: B0FPQGLYK9 | C53: medicube Sunscreen No Cast Just Glow Collagen, SPF 50 | SPF 50 Hydrating Face Sunscreen - Lightweight & Non-Sticky Formula, P | D53: 4.6 | E53: 2456 | F53: 13 | G53: USD | I53: https://www.amazon.com/medicube-Sunscreen-Lightweight-Non-Sticky-Hydrating/dp/B0FPQGLYK9/ref=zg_bs_g_11060711_d_sccl_1/136-1893143-0116527
A54: 52 | B54: B0C7JJG6BB | C54: CeraVe Acne Control Cleanser, Face Wash with 2% Salicylic Acid, 16 oz | Skin Care with Niacinamide, Acne Face Wash, Acne Trea | D54: 4.7 | E54: 23339 | F54: 17.24 | G54: USD | I54: https://www.amazon.com/CeraVe-Treatment-Salicylic-Purifying-Comedogenic/dp/B0C7JJG6BB/ref=zg_bs_g_11060711_d_sccl_2/136-1893143-0116527
A55: 53 | B55: B07VWSN95S | C55: CeraVe Resurfacing Retinol Face Serum with Niacinamide, Pore Minimizer, 1oz | Skin Care Brightening Serum with Licorice Root, | D55: 4.6 | E55: 56795 | F55: 16.49 | G55: USD | I55: https://www.amazon.com/CeraVe-Post-Acne-Refining-Resurfacing-Brightening/dp/B07VWSN95S/ref=zg_bs_g_11060711_d_sccl_3/136-1893143-0116527
A56: 54 | B56: B01EKUBU5Y | C56: TruSkin Brightening Vitamin C Serum for Face with Hyaluronic Acid, 2 fl oz | Anti aging face serum with Vitamin E to improve | D56: 4.4 | E56: 156495 | F56: 21.4 | G56: USD | I56: https://www.amazon.com/TruSkin-Naturals-Vitamin-Topical-Hyaluronic/dp/B01EKUBU5Y/ref=zg_bs_g_11060711_d_sccl_4/136-1893143-0116527
A57: 55 | B57: B01NCWV3KM | C57: La Roche-Posay Toleriane Double Repair UV SPF 30 Face Moisturizer | D57: 4.6 | E57: 29245 | F57: 24.99 | G57: USD | I57: https://www.amazon.com/Roche-Posay-Toleriane-Double-Repair-Moisturizer/dp/B01NCWV3KM/ref=zg_bs_g_11060711_d_sccl_5/136-1893143-0116527
A58: 56 | B58: B00PBX3L7K | C58: COSRX Snail Mucin 96% Repairing Serum for Sooothing & Hydrating 3.38 oz. | Snail Secretion Filtrate for Dull Skin & Fine Line | D58: 4.6 | E58: 106249 | F58: 18.5 | G58: USD | I58: https://www.amazon.com/COSRX-Repairing-Hydrating-Secretion-Phthalates/dp/B00PBX3L7K/ref=zg_bs_g_11060711_d_sccl_6/136-1893143-0116527
A59: 57 | B59: B0D16L5F2M | C59: medicube Exosome Shot Zero 2,000 PPM Spicule Facial Serum | Liquid Skin Booster Serum with Exosome, AHA+BHA+PHA - Pore Care, | D59: 4.5 | E59: 3794 | F59: 12.99 | G59: USD | I59: https://www.amazon.com/Medicube-Exosome-Spicule-Booster-Texture/dp/B0D16L5F2M/ref=zg_bs_g_11060711_d_sccl_7/136-1893143-0116527
A60: 58 | B60: B0BPXT3GBN | C60: medicube Triple Collagen Cream for Hydrating & Firming | Moisturizer with Hyaluronic Acid, Premium Elastin, Shea Butter - Wri | D60: 4.6 | E60: 10271 | F60: 15.84 | G60: USD | I60: https://www.amazon.com/Medicube-Triple-Collagen-Cream-Moisturizer/dp/B0BPXT3GBN/ref=zg_bs_g_11060711_d_sccl_8/136-1893143-0116527
A61: 59 | B61: B081KLNHSG | C61: PanOxyl Antimicrobial Acne Creamy Wash, 4% Benzoyl Peroxide, 6 Ounce | Dermatologist-Recommended, Antibacterial Daily Cleanse | D61: 4.6 | E61: 17726 | F61: 10.19 | G61: USD | I61: https://www.amazon.com/PanOxyl-Benzoyl-Peroxide-Control-Antimicrobial/dp/B081KLNHSG/ref=zg_bs_g_11060711_d_sccl_9/136-1893143-0116527
A62: 60 | B62: B0DC156Y5X | C62: JIYU Toner Pads - Korean Skincare for Dark Spots, Wrinkles & Dull Skin - Hydrating Facial Treatment with Snail Mucin, Niacina | D62: 4.3 | E62: 5174 | F62: 43.99 | G62: USD | I62: https://www.amazon.com/Toning-Polish-Pads-Hydrating-Niacinamide/dp/B0DC156Y5X/ref=zg_bs_g_11060711_d_sccl_10/136-1893143-0116527
A63: 61 | B63: B0B3SCM1L6 | C63: Tower 28 SOS Daily Rescue Soothing Hypochlorous Acid Spray for Face (1 oz) | Hypochlorous Acid Face Mist to Calm & Purify Sen | D63: 4.6 | E63: 5332 | F63: 12 | G63: USD | I63: https://www.amazon.com/Tower-28-Beauty-Rescue-Facial/dp/B0B3SCM1L6/ref=zg_bs_g_11060711_d_sccl_11/136-1893143-0116527
A64: 62 | B64: B08TM8DLFJ | C64: Good Molecules Hyaluronic Acid Serum for Face, Hydrating Serum, 1 fl oz | Deeply hydrates to plump the look of fine lines. Bo | D64: 4.7 | E64: 17618 | F64: 5.97 | G64: USD | I64: https://www.amazon.com/Good-Molecules-Hyaluronic-Long-Lasting-Fragrance-free/dp/B08TM8DLFJ/ref=zg_bs_g_11060711_d_sccl_12/136-1893143-0116527
... A82: 80 | B82: B07YLJPMC3 | C82: CeraVe Foaming Acne Cream Cleanser, Face Wash with 4% Benzoyl Peroxide, 5oz | Skin Care, Hyaluronic Acid, Niacinamide, Facial | D82: 4.6 | E82: 35778 | F82: 14.97 | G82: USD | I82: https://www.amazon.com/CeraVe-Treatment-Hyaluronic-Niacinamide-Sensitive/dp/B07YLJPMC3/ref=zg_bs_g_11060711_d_sccl_30/136-1893143-0116527
A83: 81 | B83: B07FPT52DY
A84: 82 | B84: B00464EC1E
A85: 83 | B85: B08CQDF382
A86: 84 | B86: B0FXH5LHN8
A87: 85 | B87: B0BTRTWWKC
A88: 86 | B88: B0CTJMB37K
A89: 87 | B89: B0FQBL8S3K
A90: 88 | B90: B099MSZX25
A91: 89 | B91: B002BADJVE
A92: 90 | B92: B09SQFPLC9
A93: 91 | B93: B0DJPB7H94
A94: 92 | B94: B0F8P3GXXH
... A102: 100 | B102: B0CV9R8DTK

Sheet Eyes
A1: Amazon Best Sellers — Eyes | I1: 🔗 Best Sellers 페이지 열기
A2: rank | B2: asin | C2: title | D2: rating | E2: ratings_count | F2: price | G2: currency | H2: offers_text | I2: url
A3: 1 | B3: B0GHMZXX8Y | C3: medicube PDRN Pink Collagen Volume Multi Balm Stick - Face & Body Balm | Volufiline, PDRN, NAD, Collagen - Under-Eyes, Neck, | D3: 3.8 | E3: 2423 | F3: 15.2 | G3: USD | I3: https://www.amazon.com/medicube-Collagen-Volufiline-Under-Eyes-Forehead/dp/B0GHMZXX8Y/ref=zg_bs_g_11061941_d_sccl_1/136-1893143-0116527
A4: 2 | B4: B0GD6R7CFJ | C4: BIODANCE Hydrogel Eye Patches for Under Eye - Collagen Peptide, Anti Wrinkle & Fine Lines (60 Count) | D4: 4.5 | E4: 3558 | F4: 23 | G4: USD | I4: https://www.amazon.com/BIODANCE-Collagen-Peptide-Patches-Essentials/dp/B0GD6R7CFJ/ref=zg_bs_g_11061941_d_sccl_2/136-1893143-0116527
A5: 3 | B5: B014E2D6BY | C5: grace & stella Award Winning Eye Patches for Puffy Eyes | Birthday Gifts for Women - Under Eye Mask for Dark Circles & Undere | D5: 4.3 | E5: 49117 | F5: 23.95 | G5: USD | I5: https://www.amazon.com/Under-Eye-Patches-Gold-24-Pairs/dp/B014E2D6BY/ref=zg_bs_g_11061941_d_sccl_3/136-1893143-0116527
A6: 4 | B6: B0G38FGSKL | C6: medicube Eye Patch PDRN Caffeine Collagen - Firming Gel Patches, | Age-Defying Care with Retinol & Collagen - Gel Patches for | D6: 4.4 | E6: 982 | F6: 16.9 | G6: USD | I6: https://www.amazon.com/medicube-Caffeine-Collagen-appearance-Age-Defying/dp/B0G38FGSKL/ref=zg_bs_g_11061941_d_sccl_4/136-1893143-0116527
A7: 5 | B7: B0DWMSM6Y9 | C7: medicube Eye Serum with Salmon DNA PDRN & Pink Peptides | 99% Purity Retinol for Fine Lines - PDRN & Niacinamide for Uneven S | D7: 4.5 | E7: 5832 | F7: 15.12 | G7: USD | I7: https://www.amazon.com/medicube-Serum-Salmon-PDRN-Peptides/dp/B0DWMSM6Y9/ref=zg_bs_g_11061941_d_sccl_5/136-1893143-0116527
A8: 6 | B8: B091NJQ29P | C8: Good Molecules Yerba Mate Wake Up Eye Gel, Caffeine Under Eye Cream, 15 ml | Refreshes and hydrates tired under eyes with caf | D8: 4.2 | E8: 33344 | F8: 5.97 | G8: USD | I8: https://www.amazon.com/Good-Molecules-Formulated-Revitalize-Fragrance/dp/B091NJQ29P/ref=zg_bs_g_11061941_d_sccl_6/136-1893143-0116527
A9: 7 | B9: B0GHNDWQFN | C9: medicube Jelly Eye Mask PDRN Pink Collagen - Hydrogel Eye Patches, 6 Pairs | Eye Patches with PDRN, Collagen, NAD - For Puffy | D9: 4.4 | E9: 355 | F9: 8.9 | G9: USD | I9: https://www.amazon.com/medicube-Collagen-Hydrogel-Refreshing-Wrinkles/dp/B0GHNDWQFN/ref=zg_bs_g_11061941_d_sccl_7/136-1893143-0116527
A10: 8 | B10: B0CNCL35CH | C10: Dr.Melaxin Collagen Multi Balm Stick, Calcium & Adenosine Korean Wrinkle Stick for Eye, Neck & Face, Firming Collagen Stick, | D10: 4.1 | E10: 9647 | F10: 19 | G10: USD | I10: https://www.amazon.com/Dr-Melaxin-Cemenrete-Collagen-Wrinkles-treatment/dp/B0CNCL35CH/ref=zg_bs_g_11061941_d_sccl_8/136-1893143-0116527
A11: 9 | B11: B0B3GCCRVH | C11: CeraVe Eye Cream for Wrinkles with Peptides, Caffeine & Niacinamide, 0.5oz | Dermatologist-Tested Skin Care Formula Targets C | D11: 4.5 | E11: 9440 | I11: https://www.amazon.com/CeraVe-Hyaluronic-Niacinamide-Ceramides-Ophthalmologist/dp/B0B3GCCRVH/ref=zg_bs_g_11061941_d_sccl_9/136-1893143-0116527
A12: 10 | B12: B01MUZVE1C | C12: The Ordinary Caffeine Solution 5% + EGCG Eye Serum, Depuffing Eye Serum for Dark Circles and Tired Eyes | D12: 4.4 | E12: 18976 | F12: 9.2 | G12: USD | I12: https://www.amazon.com/Ordinary-Caffeine-Solution-EGCG-30ml/dp/B01MUZVE1C/ref=zg_bs_g_11061941_d_sccl_10/136-1893143-0116527
A13: 11 | B13: B0B45LL4DD | C13: Beauty of Joseon Revive Eye Serum with Retinal Niacinamide Correction for Puffy Eye Bags Fine Lines Dark Circles Wrinkles, Ko | D13: 4.3 | E13: 20616 | F13: 17 | G13: USD | I13: https://www.amazon.com/Beauty-Joseon-Revive-eye-serum/dp/B0B45LL4DD/ref=zg_bs_g_11061941_d_sccl_11/136-1893143-0116527
A14: 12 | B14: B0B5DYY1HQ | C14: The Ordinary Multi-Peptide Lash and Brow Serum, Peptide-Powered Formula for Thicker, Fuller Looking Lashes & Brows | D14: 4.2 | E14: 6886 | F14: 14.9 | G14: USD | I14: https://www.amazon.com/Ordinary-Multi-Peptide-Lash-Brow-Serum/dp/B0B5DYY1HQ/ref=zg_bs_g_11061941_d_sccl_12/136-1893143-0116527
A15: 13 | B15: B01CVXSPBO | C15: Abib Vegan Collagen Eye Patches for Wrinkles & Fine Line with Jericho Rose Jelly & Peptides, 60 Count, Korean Skin Care | D15: 4.6 | E15: 3566 | F15: 17.96 | G15: USD | I15: https://www.amazon.com/Collagen-Peptide-Patches-Wrinkles-Jericho/dp/B01CVXSPBO/ref=zg_bs_g_11061941_d_sccl_13/136-1893143-0116527
A16: 14 | B16: B00JJPMXDO | C16: CeraVe Eye Repair Cream, Hyaluronic Acid Eye Cream for Dark Circles, 0.5oz | Skin Care, Under Eye Treatment for Puffiness wit | D16: 4.3 | E16: 75321 | F16: 14.44 | G16: USD | I16: https://www.amazon.com/CeraVe-Repair-Cream-Circles-Puffiness/dp/B00JJPMXDO/ref=zg_bs_g_11061941_d_sccl_14/136-1893143-0116527
A17: 15 | B17: B0C9F5GMF2 | C17: OCuSOFT Lid Scrub Plus Inflation Buster, Pre-Moistened Pads, 30+5 Count | Designed for eyelids exposed to environmental irrit | D17: 4.7 | E17: 5375 | F17: 19.95 | G17: USD | I17: https://www.amazon.com/OCuSOFT-Scrub-Count-Inflation-Buster/dp/B0C9F5GMF2/ref=zg_bs_g_11061941_d_sccl_15/136-1893143-0116527
A18: 16 | B18: B00027DMSI | C18: Frownies Forehead & Between the Eyes Wrinkle Patches, 144 Count | Overnight Patches for Forehead & 11 Lines | D18: 3.8 | E18: 41241 | F18: 25.95 | G18: USD | I18: https://www.amazon.com/Frownies-Forehead-Between-Eyes-Patches/dp/B00027DMSI/ref=zg_bs_g_11061941_d_sccl_16/136-1893143-0116527
A19: 17 | B19: B0BS8Y2FLK | C19: PEAUAMIE Under Eye Patches Gold and Hyaluronic Acid for puffy eyes,Rose Eye Masks for Dark Circles and Puffiness skin care Sm | D19: 4.4 | E19: 11107 | F19: 9.99 | G19: USD | I19: https://www.amazon.com/PEAUAMIE-Hyaluronic-Puffiness-treatment-products/dp/B0BS8Y2FLK/ref=zg_bs_g_11061941_d_sccl_17/136-1893143-0116527
A20: 18 | B20: B0009RFB76 | C20: RoC Retinol Correxion Under Eye Cream for Dark Circles & Puffiness, 0.50z | Anti-Aging Retinol Eye Treatment, Clinically Prov | D20: 4.3 | E20: 34240 | F20: 21.97 | G20: USD | I20: https://www.amazon.com/RoC-Correxion-Anti-Aging-Treatment-Puffiness/dp/B0009RFB76/ref=zg_bs_g_11061941_d_sccl_18/136-1893143-0116527
A21: 19 | B21: B0BDDJGXDY | C21: Maskiss 24k Gold Under Eye Patches (50 Pairs), eye mask, Collagen Skin Care Products, Eye Patches for Puffy Eyes, eye masks f | D21: 4.4 | E21: 14269 | F21: 26.95 | G21: USD | I21: https://www.amazon.com/Maskiss-50-Pairs-Puffiness-Collagen-Products/dp/B0BDDJGXDY/ref=zg_bs_g_11061941_d_sccl_19/136-1893143-0116527
A22: 20 | B22: B09SZ5JX2Y | C22: d'alba Piedmont White Truffle Double Serum All-in-one Multi Balm (0.35 oz) | Stick Balm, Under Eye Makeup Prep, Wrinkle Care, | D22: 4.5 | E22: 8596 | F22: 14.16 | G22: USD | I22: https://www.amazon.com/dalba-Piedmont-White-Truffle-Double/dp/B09SZ5JX2Y/ref=zg_bs_g_11061941_d_sccl_20/136-1893143-0116527
A23: 21 | B23: B0F19YY96Z | C23: Summer Fridays Jet Lag Hydrating Eye Patches - De-puffing Hydrogel Under Eye Masks with Hyaluronic Acid, Caffeine + Peptides | D23: 4.6 | E23: 612 | F23: 24 | G23: USD | I23: https://www.amazon.com/Summer-Fridays-Jet-Under-Patches/dp/B0F19YY96Z/ref=zg_bs_g_11061941_d_sccl_21/136-1893143-0116527
... A32: 30 | B32: B0D4Q8SR9Z | C32: MEDIHEAL 95% Retinol & Collagen Under Eye Patches, Wrinkle Care (60 Count) | with Retinol Liposome, Collagen | 4-Zone Firming | D32: 4.3 | E32: 1927 | F32: 13.8 | G32: USD | I32: https://www.amazon.com/Mediheal-Retinol-Collagen-Under-Patches/dp/B0D4Q8SR9Z/ref=zg_bs_g_11061941_d_sccl_30/136-1893143-0116527
A33: 31 | B33: B0CHXDKRR6
A34: 32 | B34: B0C4NWGVTF
A35: 33 | B35: B0CRXHWR48
A36: 34 | B36: B07Q1DVG7S
A37: 35 | B37: B08DG3C22G
A38: 36 | B38: B0FC5W77MB
A39: 37 | B39: B0CC6PG567
A40: 38 | B40: B0D2QP4H4K
A41: 39 | B41: B0FB5YDC23
A42: 40 | B42: B0GL3BB3V5
A43: 41 | B43: B0BV6YFW33
A44: 42 | B44: B0CYKRBVWC
... A52: 50 | B52: B07BYG7D2V
A53: 51 | B53: B004Y9GTYE | C53: Maybelline Instant Age Rewind Eraser Dark Circles Treatment Multi-Use Concealer, 120, 1 Count (Packaging May Vary) | D53: 4.4 | E53: 246109 | F53: 9.98 | G53: USD | I53: https://www.amazon.com/Maybelline-Instant-Circles-Treatment-Concealer/dp/B004Y9GTYE/ref=zg_bs_g_11061941_d_sccl_1/136-1893143-0116527
A54: 52 | B54: B0FHH37MZJ | C54: Beauty of Joseon Revive Under Eye Patch with Retinal and Ginseng, for Puffy Eyes, Fine Lines and Wrinkles, Collagen, Peptide, | D54: 4.3 | E54: 1151 | F54: 20 | G54: USD | I54: https://www.amazon.com/Beauty-Joseon-Retinal-Collagen-Skincare/dp/B0FHH37MZJ/ref=zg_bs_g_11061941_d_sccl_2/136-1893143-0116527
A55: 53 | B55: B0BLHFPFV9 | C55: Enaskin Naturals Under Eye Patches for Puffy Eyes & Dark Circles 60 Patches | Each Gel Patch Delivers Retinol and Collagen to | D55: 4.3 | E55: 4761 | F55: 16.99 | G55: USD | I55: https://www.amazon.com/Enaskin-Naturals-Patches-Treatment-Wrinkles/dp/B0BLHFPFV9/ref=zg_bs_g_11061941_d_sccl_3/136-1893143-0116527
A56: 54 | B56: B0859QS3YC | C56: Good Molecules Caffeine Energizing Hydrogel Eye Patches - Eye Mask with Hyaluronic Acid Hydrate and Reduce Puffiness - Pack o | D56: 4.3 | E56: 1729 | F56: 17.99 | G56: USD | I56: https://www.amazon.com/Good-Molecules-Energizing-Formulated-Niacinamide/dp/B0859QS3YC/ref=zg_bs_g_11061941_d_sccl_4/136-1893143-0116527
A57: 55 | B57: B0CGMC8WS9 | C57: HERO COSMETICS Mighty Patch for Tired Eyes Patches, 6 Count | 3 Pairs, Soothing Hydrogel Patches, Helps Awaken and Visibly De | D57: 4.4 | E57: 1163 | F57: 14.88 | G57: USD | I57: https://www.amazon.com/HERO-COSMETICS-Mighty-PatchTM-Tired/dp/B0CGMC8WS9/ref=zg_bs_g_11061941_d_sccl_5/136-1893143-0116527
A58: 56 | B58: B0FQG4FQ22 | C58: VT COSMETICS PDRN Reedle Shot Eye Cream, Vibrating Eye Applicator for Puffy Eyes, Dark Circles & Under Eye Bags, Firming & Wr | D58: 4.4 | E58: 769 | F58: 23.4 | G58: USD | I58: https://www.amazon.com/VT-COSMETICS-Ultra-Micro-Vibration-Elasticity/dp/B0FQG4FQ22/ref=zg_bs_g_11061941_d_sccl_6/136-1893143-0116527
A59: 57 | B59: B0F4R939KD | C59: numbuzin No.9 NAD+ Retinol Eye Cream for wrinkles & fine lines 0.33 fl oz | for Dark Circles, Eye Bags, Crow’s feet, and Crep | D59: 4.4 | E59: 2376 | F59: 15.48 | G59: USD | I59: https://www.amazon.com/numbuzin-Volumetox-Wrinkles-Niacinamide-Undereyes/dp/B0F4R939KD/ref=zg_bs_g_11061941_d_sccl_7/136-1893143-0116527
A60: 58 | B60: B00005333I | C60: L'Oreal Paris Dermo-Expertise Eye Defense Eye Cream with Caffeine and Hyaluronic Acid 0.5 oz | D60: 4.3 | E60: 23153 | F60: 12.12 | G60: USD | I60: https://www.amazon.com/LOreal-Paris-Skincare-Dermo-Expertise-Hyaluronic/dp/B00005333I/ref=zg_bs_g_11061941_d_sccl_8/136-1893143-0116527
A61: 59 | B61: B0D984G2NZ | C61: Eakroo Under Eye Patches - 60PCS Aloe Vera Eye Patches for Puffy Eyes and Dark Circles, Eye Mask Skincare, Eye Patches for Wo | D61: 4.4 | E61: 619 | F61: 6.28 | G61: USD | I61: https://www.amazon.com/Aloe-Vera-Eye-Masks-Treatments/dp/B0D984G2NZ/ref=zg_bs_g_11061941_d_sccl_9/136-1893143-0116527
A62: 60 | B62: B0DSY18LRL | C62: Patchology Eye Want Cake Under Eye Patches | Birthday Gift for Women | 5pk | Puffiness & Anti Wrinkle Patches Nonslip Grip-Te | D62: 4.6 | E62: 3083 | F62: 17 | G62: USD | I62: https://www.amazon.com/Patchology-Limited-Hydrating-Smoothing-Patches/dp/B0DSY18LRL/ref=zg_bs_g_11061941_d_sccl_10/136-1893143-0116527
A63: 61 | B63: B01D1DR514 | C63: e.l.f. SKIN Holy Hydration! Eye Cream, Rich Hydrating Eye Cream For Minimizing Dark Circles, Infused With Hyaluronic Acid, Ve | D63: 4.5 | E63: 8742 | F63: 10 | G63: USD | I63: https://www.amazon.com/l-f-Hydration-Minimizing-Hyaluronic-Cruelty-free/dp/B01D1DR514/ref=zg_bs_g_11061941_d_sccl_11/136-1893143-0116527
A64: 62 | B64: B0CVBGLZ5S | C64: grace & stella Under Eye Brightener Balm Stick - Travel Essentials | Caffeine Eye Cream for Dark Circles, Puffiness- Vegan Mo | D64: 3.9 | E64: 4347 | F64: 9.95 | G64: USD | I64: https://www.amazon.com/grace-stella-stick-reduce-circles/dp/B0CVBGLZ5S/ref=zg_bs_g_11061941_d_sccl_12/136-1893143-0116527
... A82: 80 | B82: B0FD3FSCVD | C82: Lash Serum for Eyelash Growth, Premium Lash Enhancing Serum with Advanced Formula Volumizing Longer Fuller and Thicker Lookin | D82: 4.4 | E82: 1260 | F82: 11.96 | G82: USD | I82: https://www.amazon.com/Eyelash-Enhancing-Advanced-Volumizing-Sensitive/dp/B0FD3FSCVD/ref=zg_bs_g_11061941_d_sccl_30/136-1893143-0116527
A83: 81 | B83: B0CJJZYR9Y
A84: 82 | B84: B0FDK4B3JD
A85: 83 | B85: B000KOLXKM
A86: 84 | B86: B0FNNC9CZG
A87: 85 | B87: B0FNWK7LTP
A88: 86 | B88: B0DM2PZ1B8
A89: 87 | B89: B0B641HBKN
A90: 88 | B90: B00027DMLK
A91: 89 | B91: B0C7C7DDT3
A92: 90 | B92: B00QL67MY4
A93: 91 | B93: B07ZRF416W
A94: 92 | B94: B0BLCZH72Z
... A102: 100 | B102: B08SHHLS4H

Sheet Sunscreens
A1: Amazon Best Sellers — Sunscreens | I1: 🔗 Best Sellers 페이지 열기
A2: rank | B2: asin | C2: title | D2: rating | E2: ratings_count | F2: price | G2: currency | H2: offers_text | I2: url
A3: 1 | B3: B002MSN3QQ | C3: EltaMD UV Clear Face Sunscreen with Zinc Oxide, Oil-Free, SPF 46 and SPF 50 | Calms and Protects Acne-Prone Skin and Rosacea, | D3: 4.5 | E3: 70565 | F3: 45 | G3: USD | I3: https://www.amazon.com/EltaMD-Clear-Untinted-Sunscreen-Oxide/dp/B002MSN3QQ/ref=zg_bs_g_11062651_d_sccl_1/136-1893143-0116527
A4: 2 | B4: B084ZP848Y | C4: Blue Lizard Sensitive Mineral SPF 50 Sunscreen Lotion, 100% Mineral Sunscreen, UVA/UVB Protection, Infused with organic Aloe | D4: 4.4 | E4: 21370 | F4: 15.48 | G4: USD | I4: https://www.amazon.com/Blue-Lizard-Sensitive-Mineral-Sunscreen/dp/B084ZP848Y/ref=zg_bs_g_11062651_d_sccl_2/136-1893143-0116527
A5: 3 | B5: B00J5KDCO2 | C5: EltaMD UV Daily Face Sunscreen Moisturizer, Zinc Oxide, SPF 40 and SPF 50 | Hydrates and Protects Dry Dehydrated Skin, Lightw | D5: 4.6 | E5: 44771 | F5: 43 | G5: USD | I5: https://www.amazon.com/EltaMD-Moisturizer-Hyaluronic-Mineral-Based-Protection/dp/B00J5KDCO2/ref=zg_bs_g_11062651_d_sccl_3/136-1893143-0116527
A6: 4 | B6: B0FPQGLYK9 | C6: medicube Sunscreen No Cast Just Glow Collagen, SPF 50 | SPF 50 Hydrating Face Sunscreen - Lightweight & Non-Sticky Formula, P | D6: 4.6 | E6: 2456 | F6: 13 | G6: USD | I6: https://www.amazon.com/medicube-Sunscreen-Lightweight-Non-Sticky-Hydrating/dp/B0FPQGLYK9/ref=zg_bs_g_11062651_d_sccl_4/136-1893143-0116527
A7: 5 | B7: B07YLKXV11 | C7: CeraVe Tinted Sunscreen for Face, Mineral SPF 30 Moisturizer, Medium, 1.7oz | Skin Care, Face Sunscreen, Hyaluronic Acid, Zin | D7: 4.4 | E7: 73440 | F7: 13.97 | G7: USD | I7: https://www.amazon.com/CeraVe-Sunscreen-Hydrating-Mineral-Titanium/dp/B07YLKXV11/ref=zg_bs_g_11062651_d_sccl_5/136-1893143-0116527
A8: 6 | B8: B01MQXX9US | C8: Banana Boat Sport SPF 50 Sunscreen Spray, 6 oz (2 Pack) | Sweat and water resistant sunblock spray, UVA/UVB broad spectrum pr | D8: 4.8 | E8: 26608 | F8: 13.86 | G8: USD | I8: https://www.amazon.com/Banana-Boat-Sunscreen-Performance-Spectrum/dp/B01MQXX9US/ref=zg_bs_g_11062651_d_sccl_6/136-1893143-0116527
A9: 7 | B9: B005IHT94S | C9: Neutrogena Ultra Sheer Dry Touch Sunscreen Lotion, SPF 70, 3 fl. oz | Broad Spectrum for UVA/UVB Protection, Lightweight, Wat | D9: 4.5 | E9: 39925 | F9: 9.88 | G9: USD | I9: https://www.amazon.com/Neutrogena-Ultra-Dry-Touch-Sunscreen-Spectrum/dp/B005IHT94S/ref=zg_bs_g_11062651_d_sccl_7/136-1893143-0116527
A10: 8 | B10: B00F97FHAW | C10: CeraVe AM Oil Face Moisturizer Lotion, Sunscreen for Face, SPF 30, 3oz | Skin Care with Hyaluronic Acid & Niacinamide, Oil-Fr | D10: 4.5 | E10: 97876 | F10: 14.97 | G10: USD | I10: https://www.amazon.com/CeraVe-Facial-Moisturizing-Lotion-AM/dp/B00F97FHAW/ref=zg_bs_g_11062651_d_sccl_8/136-1893143-0116527
A11: 9 | B11: B007U54P36 | C11: La Roche-Posay Anthelios Mineral Light Fluid Sunscreen for Face in 5 shades | Broad spectrum sunscreen, antioxidants, titaniu | D11: 4.4 | E11: 32358 | F11: 33.97 | G11: USD | I11: https://www.amazon.com/Roche-Posay-Anthelios-Sunscreen-Ultra-Light-Sensitive/dp/B007U54P36/ref=zg_bs_g_11062651_d_sccl_9/136-1893143-0116527
A12: 10 | B12: B093W7CDWD | C12: Colorescience, Total Protection Face Shield Flex, SPF 50 | D12: 4.4 | E12: 10054 | F12: 58 | G12: USD | I12: https://www.amazon.com/Colorescience-Total-Protection-Shield-Medium/dp/B093W7CDWD/ref=zg_bs_g_11062651_d_sccl_10/136-1893143-0116527
A13: 11 | B13: B0DKJ3BX2F | C13: d'alba Piedmont Waterfull Tone-Up Sunscreen Serum (1.69 fl oz), SPF 50+ | BROAD SPECTRUM SPF 50 +, Makeup Base, Foundation-Fr | D13: 4.3 | E13: 5553 | F13: 15.2 | G13: USD | I13: https://www.amazon.com/dalba-Piedmont-Waterfull-Sunscreen-SPECTRUM/dp/B0DKJ3BX2F/ref=zg_bs_g_11062651_d_sccl_11/136-1893143-0116527
A14: 12 | B14: B0FXH5LHN8 | C14: SKIN1004 Hyalu-Cica Water-Fit Sun Serum UV, SPF 50 Sunscreen, 1.69 fl.oz | UV Protection Centella Sunscreen for Face with Hya | D14: 4.4 | E14: 1851 | F14: 17.95 | G14: USD | I14: https://www.amazon.com/SKIN1004-Hyalu-Cica-Water-Fit-Essentials-Hyaluronic/dp/B0FXH5LHN8/ref=zg_bs_g_11062651_d_sccl_12/136-1893143-0116527
... A32: 30 | B32: B088ZRZ668 | C32: Supergoop! Glowscreen SPF 40 - Glowy Primer + Broad Spectrum Tinted Sunscreen - Helps Filter Blue Light - Hydration - Hyaluro | D32: 4.6 | E32: 9559 | F32: 34.99 | G32: USD | I32: https://www.amazon.com/Supergoop-Glowscreen-SPF-1-7-fl/dp/B088ZRZ668/ref=zg_bs_g_11062651_d_sccl_30/136-1893143-0116527
A33: 31 | B33: B0C69Z5LSP
A34: 32 | B34: B001P92FMG
A35: 33 | B35: B07GRBQXTV
A36: 34 | B36: B087H5FFGK
A37: 35 | B37: B0GR23K9GY
A38: 36 | B38: B076GZX3KL
A39: 37 | B39: B0BQCSMD63
A40: 38 | B40: B0DJGWH3TC
A41: 39 | B41: B004CDQ73K
A42: 40 | B42: B01A0NT3D6
A43: 41 | B43: B08K9HFC31
A44: 42 | B44: B07KLY4RYG
... A52: 50 | B52: B0FPNZXRGZ
A53: 51 | B53: B09ZY7468X | C53: COSRX Vitamin E Sunscreen SPF 50, Natural Glow, for Oily Skin, 1.69 fl oz | Hydrating Face Sunscreen, Lightweight, Non-Sticky | D53: 4.5 | E53: 5128 | F53: 18.19 | G53: USD | I53: https://www.amazon.com/COSRX-Sunscreen-Whitecast-Vitalizing-Protection/dp/B09ZY7468X/ref=zg_bs_g_11062651_d_sccl_1/136-1893143-0116527
A54: 52 | B54: B09MV3MHJD | C54: Neutrogena Ultra Sheer Sunscreen Serum SPF 60, Fragrance-Free, 1.7 fl. oz | Broad Spectrum UVA/UVB Protection, Lightweight Se | D54: 4.6 | E54: 10653 | F54: 15.88 | G54: USD | I54: https://www.amazon.com/Neutrogena-Moisturizing-Protection-Fragrance-Free-Oxybenzone-Free/dp/B09MV3MHJD/ref=zg_bs_g_11062651_d_sccl_2/136-1893143-0116527
A55: 53 | B55: B00K3JQO9Y | C55: Thinksport Mineral Sunscreen SPF 50+ Zinc Oxide, Water Resistant, 6 Fl Oz | Reef friendly, water resistant (80 minutes), spor | D55: 4.3 | E55: 9714 | F55: 16.79 | G55: USD | I55: https://www.amazon.com/Thinksport-Sunscreen-SPF-50-Ounce/dp/B00K3JQO9Y/ref=zg_bs_g_11062651_d_sccl_3/136-1893143-0116527
A56: 54 | B56: B004D2DR0Q | C56: Neutrogena Ultra Sheer Dry Touch Sunscreen Lotion SPF 45, 2 x 3 fl. oz | UVA/UVB Protection, Lightweight, Water-Resistant up | D56: 4.7 | E56: 18339 | F56: 13.97 | G56: USD | I56: https://www.amazon.com/Neutrogena-Dry-Touch-Resistant-Non-Greasy-Sunscreen/dp/B004D2DR0Q/ref=zg_bs_g_11062651_d_sccl_4/136-1893143-0116527
A57: 55 | B57: B0CLVM67FV | C57: Eucerin Sun Age Defense Tinted Face Lotion SPF 50, 2.5 FL OZ | Universal Tinted Sunscreen for Face with Hyaluronic Acid, Non | D57: 4.4 | E57: 4287 | F57: 15.88 | G57: USD | I57: https://www.amazon.com/Eucerin-Defense-Tinted-Face-Lotion/dp/B0CLVM67FV/ref=zg_bs_g_11062651_d_sccl_5/136-1893143-0116527
A58: 56 | B58: B09MJG6X4W | C58: Eucerin Clear Skin Face Sunscreen Lotion, SPF 50, 2.5 FL OZ | Face Sunscreen for Acne Prone, Oily Skin with Oil-Absorbing Min | D58: 4.6 | E58: 9956 | F58: 14.39 | G58: USD | I58: https://www.amazon.com/Eucerin-Control-Sunscreen-Absorbing-Minerals/dp/B09MJG6X4W/ref=zg_bs_g_11062651_d_sccl_6/136-1893143-0116527
A59: 57 | B59: B002CML1XE | C59: La Roche-Posay Anthelios Ultra Light Fluid Sunscreen for Face SPF 60, 1.7oz | Lightweight face sunscreen with antioxidants. A | D59: 4.6 | E59: 8478 | F59: 26.99 | G59: USD | I59: https://www.amazon.com/Roche-Posay-Anthelios-Ultra-Light-Sunscreen/dp/B002CML1XE/ref=zg_bs_g_11062651_d_sccl_7/136-1893143-0116527
A60: 58 | B60: B0BSP3N82M | C60: e.l.f. SKIN Suntouchable Whoa Glow SPF 30, Sunbeam | Face Sunscreen & Makeup Primer with Hyaluronic Acid, Vegan & Cruelty-Fre | D60: 4.4 | E60: 4820 | F60: 9.25 | G60: USD | I60: https://www.amazon.com/l-f-Suntouchable-Lightweight-Hyaluronic-Cruelty-Free/dp/B0BSP3N82M/ref=zg_bs_g_11062651_d_sccl_8/136-1893143-0116527
A61: 59 | B61: B07X1YDGSF | C61: Neutrogena Beach Defense Sunscreen Spray, SPF 50, 6.5 oz | Face & Body, Broad Spectrum for UVA/UVB Protection, Lightweight Su | D61: 4.7 | E61: 12107 | F61: 8.99 | G61: USD | I61: https://www.amazon.com/Neutrogena-Protection-Sunscreen-Water-Resistant-Lightweight/dp/B07X1YDGSF/ref=zg_bs_g_11062651_d_sccl_9/136-1893143-0116527
A62: 60 | B62: B079YXK3L8 | C62: UV AOX Elements Tinted Mineral Face Sunscreen Lotion, Tinted Moisturizer for Face SPF 50 with Antioxidants | D62: 4.6 | E62: 14840 | F62: 46 | G62: USD | I62: https://www.amazon.com/EltaMD-Antioxidant-Protection-Environmental-Aggressors/dp/B079YXK3L8/ref=zg_bs_g_11062651_d_sccl_10/136-1893143-0116527
A63: 61 | B63: B00G17U5K6 | C63: Biocorneum Silicone Scar Gel with SPF 30, Fast-Drying Scar Cream, 10g | Advanced Scar Treatment with Silishield®, Water Resis | D63: 4.5 | E63: 6772 | F63: 54.99 | G63: USD | I63: https://www.amazon.com/BioCorneum-Scar-Treatment-Silicone-Sientra/dp/B00G17U5K6/ref=zg_bs_g_11062651_d_sccl_11/136-1893143-0116527
A64: 62 | B64: B0FXBR5T6R | C64: Relief Sun Organic Korean sunscreen SPF50+, PA++++ Riceand Probiotics | Korean Skin Care Solution for All Skin TypesNourishin | D64: 4.2 | E64: 526 | F64: 17.99 | G64: USD | I64: https://www.amazon.com/sunscreen-Probiotics-Solution-TypesNourishing-Protection/dp/B0FXBR5T6R/ref=zg_bs_g_11062651_d_sccl_12/136-1893143-0116527
... A82: 80 | B82: B0DLFRDD2Z | C82: La Roche-Posay Anthelios UV Pro-Sport SPF Face & Body Sunscreen | Long-lasting water resistant invisible, fast absorbing, sun | D82: 4.5 | E82: 792 | F82: 28.02 | G82: USD | I82: https://www.amazon.com/Anthelios-Pro-Sport-Sunscreen-Invisible-Protection/dp/B0DLFRDD2Z/ref=zg_bs_g_11062651_d_sccl_30/136-1893143-0116527
A83: 81 | B83: B09MJGJS5V
A84: 82 | B84: B0CM4JVK6H
A85: 83 | B85: B0CNKXCL4X
A86: 84 | B86: B00CICLTAI
A87: 85 | B87: B07T2DP3TK
A88: 86 | B88: B07YZR5WXC
A89: 87 | B89: B0GMKY45D7
A90: 88 | B90: B09J9X2NNR
A91: 89 | B91: B0FR5GLN1G
A92: 90 | B92: B0CYTB1BWV
A93: 91 | B93: B0935NNYK1
A94: 92 | B94: B0BFJVZPDC
... A102: 100 | B102: B072QXB8KX

Sheet Serums
A1: Amazon Best Sellers — Serums | I1: 🔗 Best Sellers 페이지 열기
A2: rank | B2: asin | C2: title | D2: rating | E2: ratings_count | F2: price | G2: currency | H2: offers_text | I2: url
A3: 1 | B3: B0DBF65JYY | C3: medicube PDRN Pink Peptide Serum with Salmon DNA | Pink Glow Serum - Peptides & Niacinamide for Hydration & Firm-Looking Skin | D3: 4.6 | E3: 21102 | F3: 15.12 | G3: USD | I3: https://www.amazon.com/medicube-Niacinamide-Hydrating-Moisturizing-Skincare/dp/B0DBF65JYY/ref=zg_bs_g_7792528011_d_sccl_1/136-1893143-0116527
A4: 2 | B4: B0DG4WXBCF | C4: MEDITHERAPY Retinal Skin Booster Serum 5.07 fl oz | Retinaldehyde, Niacinamide, Cica | Korean Hydrating Face & Body Serum for | D4: 4.3 | E4: 10803 | F4: 17.49 | G4: USD | I4: https://www.amazon.com/MEDITHERAPY-Retinaldehyde-Niacinamide-Hydrating-K-Beauty/dp/B0DG4WXBCF/ref=zg_bs_g_7792528011_d_sccl_2/136-1893143-0116527
A5: 3 | B5: B01MYEZPC8 | C5: The Ordinary Hyaluronic Acid 2% + B5 (with Ceramides), Multi-Depth Hydration Serum for Plumper, Smoother Skin | D5: 4.7 | E5: 40152 | F5: 9.9 | G5: USD | I5: https://www.amazon.com/Ordinary-Hyaluronic-Acid-2-30ml/dp/B01MYEZPC8/ref=zg_bs_g_7792528011_d_sccl_3/136-1893143-0116527
A6: 4 | B6: B01MDTVZTZ | C6: The Ordinary Niacinamide 10% + Zinc 1%, Smoothing Serum for Blemish-Prone Skin | D6: 4.7 | E6: 64018 | F6: 6 | G6: USD | I6: https://www.amazon.com/Ordinary-Niacinamide-10-Zinc-30ml/dp/B01MDTVZTZ/ref=zg_bs_g_7792528011_d_sccl_4/136-1893143-0116527
A7: 5 | B7: B0DK4Y2YP3 | C7: celimax The Vita A Retinal Shot Tightening Booster (0.51 fl.oz) | 0.1% Retinal, 3% Matryxyl, High-Strength Retinoid, Anti Agi | D7: 4.4 | E7: 23643 | F7: 18.89 | G7: USD | I7: https://www.amazon.com/celimax-Tightening-Liposomized-Matryxyl-Minimizer/dp/B0DK4Y2YP3/ref=zg_bs_g_7792528011_d_sccl_5/136-1893143-0116527
A8: 6 | B8: B0DG1DQ2S7 | C8: Anua Azelaic Acid 10 Hyaluron Redness Soothing Serum, 1.01 fl oz | Facial Serum for Blemish-Prone & Oily-Prone Skin, Lightwei | D8: 4.5 | E8: 6302 | F8: 22 | G8: USD | I8: https://www.amazon.com/Azelaic-Hyaluron-Redness-Soothing-Serum/dp/B0DG1DQ2S7/ref=zg_bs_g_7792528011_d_sccl_6/136-1893143-0116527
A9: 7 | B9: B0D8W1YVBX | C9: EQQUALBERRY Vitamin Illuminating Serum | Niacinamide 4% & TXA | Brightening Vitamin C Serum for Face Glow with Hyaluronic Aci | D9: 4.2 | E9: 17735 | F9: 19.99 | G9: USD | I9: https://www.amazon.com/EQQUALBERRY-Vitamin-Illuminating-Serum-Brightening/dp/B0D8W1YVBX/ref=zg_bs_g_7792528011_d_sccl_7/136-1893143-0116527
A10: 8 | B10: B0C3PCJ6SD | C10: The Ordinary Salicylic Acid 2% Solution, Acne-Fighting Serum for Blemish-Prone Skin | D10: 4.7 | E10: 12935 | F10: 6.7 | G10: USD | I10: https://www.amazon.com/Ordinary-Salicylic-Exfoliating-Blemish-Solution/dp/B0C3PCJ6SD/ref=zg_bs_g_7792528011_d_sccl_8/136-1893143-0116527
A11: 9 | B11: B0GCC2JV65 | C11: medicube NAD EGF Firming Serum for Face & Neck | Anti-Aging Serum with EGF Peptide, NAD & Collagen - Wrinkle Appearance, Elas | D11: 4.6 | E11: 1710 | F11: 15.12 | G11: USD | I11: https://www.amazon.com/medicube-Firming-Serum-Face-Neck/dp/B0GCC2JV65/ref=zg_bs_g_7792528011_d_sccl_9/136-1893143-0116527
A12: 10 | B12: B0FGQ3J31K | C12: EQQUALBERRY NAD+ Peptide Boosting Serum | 14 Peptide Serum for Face, Neck & Body | Vegan Collagen & Pink Serum for Anti-Aging | D12: 4.3 | E12: 5027 | F12: 19.99 | G12: USD | I12: https://www.amazon.com/EQQUALBERRY-Peptide-Boosting-Smoothie-Serum/dp/B0FGQ3J31K/ref=zg_bs_g_7792528011_d_sccl_10/136-1893143-0116527
A13: 11 | B13: B07VWSN95S | C13: CeraVe Resurfacing Retinol Face Serum with Niacinamide, Pore Minimizer, 1oz | Skin Care Brightening Serum with Licorice Root, | D13: 4.6 | E13: 56795 | F13: 16.49 | G13: USD | I13: https://www.amazon.com/CeraVe-Post-Acne-Refining-Resurfacing-Brightening/dp/B07VWSN95S/ref=zg_bs_g_7792528011_d_sccl_11/136-1893143-0116527
A14: 12 | B14: B01EKUBU5Y | C14: TruSkin Brightening Vitamin C Serum for Face with Hyaluronic Acid, 2 fl oz | Anti aging face serum with Vitamin E to improve | D14: 4.4 | E14: 156495 | F14: 21.4 | G14: USD | I14: https://www.amazon.com/TruSkin-Naturals-Vitamin-Topical-Hyaluronic/dp/B01EKUBU5Y/ref=zg_bs_g_7792528011_d_sccl_12/136-1893143-0116527
... A32: 30 | B32: B0H3KJ25GN | C32: medicube Vita A Retinal Volume Booster Serum, with Volufiline, 4X-Retinoid | Retinal, Volufiline & 4X Retinoid Complex, Pore | D32: 4.7 | E32: 22 | F32: 15.12 | G32: USD | I32: https://www.amazon.com/medicube-Retinal-Booster-Volufiline-4X-Retinoid/dp/B0H3KJ25GN/ref=zg_bs_g_7792528011_d_sccl_30/136-1893143-0116527
A33: 31 | B33: B072K1LNNY
A34: 32 | B34: B0CM4B43DZ
A35: 33 | B35: B07PM79MSC
A36: 34 | B36: B0DBRVHR38
A37: 35 | B37: B0FG7VLJKG
A38: 36 | B38: B07K3261ZD
A39: 37 | B39: B0BJ4GZTK1
A40: 38 | B40: B0C9DXGXZ3
A41: 39 | B41: B074NNVLCM
A42: 40 | B42: B06XCZFCFZ
A43: 41 | B43: B0DLKGLBPG
A44: 42 | B44: B0DHRQXYCH
... A52: 50 | B52: B0DJV8MYYN
A53: 51 | B53: B072JH13CD | C53: Argireline Solution 10%, Serum Good for Reducing the Appearance of Fine Lines, 1 Fl Oz | D53: 4.5 | E53: 8052 | F53: 9.7 | G53: USD | I53: https://www.amazon.com/Ordinary-Argireline-Solution-10-1-Pack/dp/B072JH13CD/ref=zg_bs_g_7792528011_d_sccl_1/136-1893143-0116527
A54: 52 | B54: B0GS1DYZHG | C54: SUNGBOON EDITOR Intensive Deep Collagen Silk Peptide EGF Ampoule,1.35fl.oz | Copper peptides, EGF, 13-peptide complex and 24K | D54: 4.5 | E54: 564 | F54: 20.5 | G54: USD | I54: https://www.amazon.com/SUNGBOON-EDITOR-Intensive-Collagen-1-35fl-oz/dp/B0GS1DYZHG/ref=zg_bs_g_7792528011_d_sccl_2/136-1893143-0116527
A55: 53 | B55: B0FPFDSC7X | C55: medicube Retinol Boosting Serum for Intensive Firming Care | Hydration & Plumping Care with Retinol, Peptides & Vitamins - Re | D55: 4.6 | E55: 1061 | F55: 15.12 | G55: USD | I55: https://www.amazon.com/medicube-Boosting-Intensive-Hydration-Pore-Refining/dp/B0FPFDSC7X/ref=zg_bs_g_7792528011_d_sccl_3/136-1893143-0116527
A56: 54 | B56: B0BMZF7H3P | C56: Topicals, Faded Brightening Serum, Reduces Discoloration, 0.5 Fl Oz | Clears Post-Blemish Marks, Scars & Spots, Kojic Acid & | D56: 4.2 | E56: 6939 | F56: 18 | G56: USD | I56: https://www.amazon.com/Topicals-Faded-Serum-Spots-Discoloration/dp/B0BMZF7H3P/ref=zg_bs_g_7792528011_d_sccl_4/136-1893143-0116527
A57: 55 | B57: B0C2TQ24VY | C57: VT COSMETICS CICA Reedle Shot 100 Microneedling Serum | Spicule, Pore Care & Exfoliation, Exosome, Centella Asiatica for Glas | D57: 4.5 | E57: 12744 | F57: 19.5 | G57: USD | I57: https://www.amazon.com/VT-COSMETICS-Hydrated-Poreless-Hyaluronic/dp/B0C2TQ24VY/ref=zg_bs_g_7792528011_d_sccl_5/136-1893143-0116527
A58: 56 | B58: B07WZ2YTDP | C58: Torriden DIVE IN Hyaluronic Acid Serum for Deep Hydration | Korean K-Beauty Glass Skin Plump Glow | Lightweight Fast-Absorbin | D58: 4.5 | E58: 4322 | F58: 22 | G58: USD | I58: https://www.amazon.com/Torriden-Hyaluronic-Hydration-Panthenol-Allantoin/dp/B07WZ2YTDP/ref=zg_bs_g_7792528011_d_sccl_6/136-1893143-0116527
A59: 57 | B59: B076611KCY | C59: Vitamin C Serum For Face – Anti Aging Face Serum with Vitamin C, Hyaluronic Acid, Vitamin E. Brightening Formula. Improve App | D59: 4.4 | E59: 133085 | F59: 13.99 | G59: USD | I59: https://www.amazon.com/Organic-Vitamin-Face-Serum-Hyaluronic/dp/B076611KCY/ref=zg_bs_g_7792528011_d_sccl_7/136-1893143-0116527
A60: 58 | B60: B071J1PBQ6 | C60: Matrixyl 10% + Hyaluronic Acid, Anti-Aging Serum for Fine Lines and Wrinkles, 1 Fl Oz | D60: 4.6 | E60: 4173 | F60: 10.9 | G60: USD | I60: https://www.amazon.com/Ordinary-Matrixyl-10-HA-30ml/dp/B071J1PBQ6/ref=zg_bs_g_7792528011_d_sccl_8/136-1893143-0116527
A61: 59 | B61: B00UOLIOC6 | C61: Neutrogena On-The-Spot Acne Spot Treatment Cream, 0.75 oz | 2.5% Benzoyl Peroxide, Gentle Blemish Medicine, Acne-Prone Skin, | D61: 4.6 | E61: 4419 | F61: 8.97 | G61: USD | I61: https://www.amazon.com/Neutrogena-Treatment-Benzoyl-Peroxide-Medicine/dp/B00UOLIOC6/ref=zg_bs_g_7792528011_d_sccl_9/136-1893143-0116527
A62: 60 | B62: B0DVSNQ37F | C62: medicube TXA&Niacinamide 15% Glow Serum | Lightweight Daily Serum - For Uneven Skin Tone, Texture, and After Spot Care, High- | D62: 4.5 | E62: 3139 | F62: 15.12 | G62: USD | I62: https://www.amazon.com/medicube-Niacinamide-Hydration-High-Potency-Tranexamic/dp/B0DVSNQ37F/ref=zg_bs_g_7792528011_d_sccl_10/136-1893143-0116527
A63: 61 | B63: B091MTKS35 | C63: Good Molecules Super Peptide Serum - Anti-aging Facial Serum with Peptides and Copper Tripeptides to Plump and Firm - Water-B | D63: 4.6 | E63: 3958 | F63: 12 | G63: USD | I63: https://www.amazon.com/Good-Molecules-Formulated-Tripeptides-Youthful-Looking/dp/B091MTKS35/ref=zg_bs_g_7792528011_d_sccl_11/136-1893143-0116527
A64: 62 | B64: B085VWWJJT | C64: Medicube Triple Collagen Serum for Nourishment | Lightweight serum with Triple Collagen Complex, Niacinamide & Hyaluronic Aci | D64: 4.7 | E64: 3835 | F64: 15.12 | G64: USD | I64: https://www.amazon.com/medicube-Triple-Collagen-Essential-Serum/dp/B085VWWJJT/ref=zg_bs_g_7792528011_d_sccl_12/136-1893143-0116527
... A82: 80 | B82: B0CRDQPLCM | C82: SUNGBOON EDITOR Deep Collagen Serum, 5% Volufiline, Hydrating, 1.01 fl oz | Ultra-fine 300Da French collagen with 5% Volufili | D82: 4.3 | E82: 3092 | F82: 21.03 | G82: USD | I82: https://www.amazon.com/SUNGBOON-EDITOR-Anti-wrinkle-Elasticity-Improvement/dp/B0CRDQPLCM/ref=zg_bs_g_7792528011_d_sccl_30/136-1893143-0116527
A83: 81 | B83: B071HHSMTT
A84: 82 | B84: B08936CZHQ
A85: 83 | B85: B0090UJFYI
A86: 84 | B86: B07Z9Y4M3C
A87: 85 | B87: B0GSSMD97S
A88: 86 | B88: B0C7MQQSW4
A89: 87 | B89: B0GV2J43Q9
A90: 88 | B90: B088419TZG
A91: 89 | B91: B07GVCVYB9
A92: 90 | B92: B088C7S4VL
A93: 91 | B93: B0DGLCRZZ3
A94: 92 | B94: B07WSS5M4Z
... A102: 100 | B102: B0DNMWJN1R

Sheet Fragrances
A1: Amazon Best Sellers — Fragrances | I1: 🔗 Best Sellers 페이지 열기
A2: rank | B2: asin | C2: title | D2: rating | E2: ratings_count | F2: price | G2: currency | H2: offers_text | I2: url
A3: 1 | B3: B001O8MI2K | C3: Boss Bottled Eau de Toilette für Männer | D3: 4.7 | E3: 36668 | F3: 91293 | G3: KRW | I3: https://www.amazon.com/-/en/Hugo-Boss-Homme-Toilette-Spray/dp/B001O8MI2K/ref=zg_bs_g_122877031_d_sccl_1/701-5081554-7062441
A4: 2 | B4: B00S2WDIGG | C4: Calvin Klein ck one Eau de Toilette, aromatisch-zitrischer Unisex-Duft für Frauen und Männer | D4: 4.6 | E4: 34221 | F4: 40991 | G4: KRW | I4: https://www.amazon.com/-/en/Calvin-Klein-one-Eau-Toilette/dp/B00S2WDIGG/ref=zg_bs_g_122877031_d_sccl_2/701-5081554-7062441
A5: 3 | B5: B08GBLSDCZ | C5: Nivea Eau de Toilette (30 ml) with the Unparalleled Fragrance of Nivea Cream in an Elegant Perfume Bottle and Nivea Gift Box, | D5: 4.6 | E5: 8786 | F5: 28190 | G5: KRW | I5: https://www.amazon.com/-/en/Toilette-Unparalleled-Fragrance-Complements-Products/dp/B08GBLSDCZ/ref=zg_bs_g_122877031_d_sccl_3/701-5081554-7062441
A6: 4 | B6: B000RPDBJU | C6: Joop! Le Bain Eau de Parfum | D6: 4.6 | E6: 12097 | F6: 27258 | G6: KRW | I6: https://www.amazon.com/-/en/Joop-Bain-Eau-Parfum-Women/dp/B000RPDBJU/ref=zg_bs_g_122877031_d_sccl_4/701-5081554-7062441
A7: 5 | B7: B00M3IFUMK | C7: Armaf Club De Nuit Intense For Men Eau de Toilette, 105ml Black | D7: 4.3 | E7: 75411 | F7: 77190 | G7: KRW | I7: https://www.amazon.com/-/en/Armaf-Intense-Toilette-105ml-Black/dp/B00M3IFUMK/ref=zg_bs_g_122877031_d_sccl_5/701-5081554-7062441
A8: 6 | B8: B0B92Y18GT | C8: Lattafa Khamrah Eau De Parfum 100 ml | Oriental, gourmand, spicy, sweet, warm | D8: 4.5 | E8: 37783 | F8: 57892 | G8: KRW | I8: https://www.amazon.com/-/en/Lattafa-Khamrah-Eau-Parfum-100/dp/B0B92Y18GT/ref=zg_bs_g_122877031_d_sccl_6/701-5081554-7062441
A9: 7 | B9: B0G1BPC8D5 | C9: NIVEA MEN Sensitive After Shave Fluid, Face Care After Shaving for Sensitive Men's Skin, Soothing Skin Care to Relieve Skin I | D9: 4.7 | E9: 70 | F9: 7992 | G9: KRW | I9: https://www.amazon.com/-/en/NIVEA-MEN-Sensitive-Soothing-Irritation/dp/B0G1BPC8D5/ref=zg_bs_g_122877031_d_sccl_7/701-5081554-7062441
A10: 8 | B10: B00AQYSLHY | C10: Tattoo Toomed Tattoo Aftercare 100ml | D10: 4.7 | E10: 7282 | F10: 17143 | G10: KRW | I10: https://www.amazon.com/-/en/Tattoo-Toomed-Aftercare-100ml/dp/B00AQYSLHY/ref=zg_bs_g_122877031_d_sccl_8/701-5081554-7062441
A11: 9 | B11: B0009OAI40 | C11: Elizabeth Arden Green Tea Eau de Parfum for Women 100 ml | Invigorating fragrance with green tea and bergamot, refreshes the | D11: 4.6 | E11: 13638 | F11: 19137 | G11: KRW | I11: https://www.amazon.com/-/en/Elizabeth-Arden-Green-Parfum-Women/dp/B0009OAI40/ref=zg_bs_g_122877031_d_sccl_9/701-5081554-7062441
A12: 10 | B12: B001D64YXY | C12: JOOP! HOMME Eau de Toilette | D12: 4.6 | E12: 59620 | F12: 30715 | G12: KRW | I12: https://www.amazon.com/-/en/Joop-Homme-Eau-Toilette-75/dp/B001D64YXY/ref=zg_bs_g_122877031_d_sccl_10/701-5081554-7062441
A13: 11 | B13: B0FR46YJJM | C13: Spray Bottle 4 x 20 ml Small Spray Bottle Transparent Atomiser Bottles Portable Travel Bottles Set Empty Small Cosmetics Spra | D13: 4.4 | E13: 144 | F13: 6400 | G13: KRW | I13: https://www.amazon.com/-/en/Transparent-Atomiser-Portable-Cosmetics-Perfumes/dp/B0FR46YJJM/ref=zg_bs_g_122877031_d_sccl_11/701-5081554-7062441
A14: 12 | B14: B09SHYR3HN | C14: Bruno Banani Fragrance Man Eau de Toilette Natural Spray Herb Aromatic Mens Perfume Bottle with Atomiser 100ml | D14: 4.7 | E14: 2649 | F14: 26952 | G14: KRW | I14: https://www.amazon.com/-/en/Bruno-Banani-Fragrance-Toilette-Aromatic/dp/B09SHYR3HN/ref=zg_bs_g_122877031_d_sccl_12/701-5081554-7062441
... A32: 30 | B32: B0746B4718 | C32: Refillable Perfume Atomiser Aluminium 8 ml Rotatable with Hidden Top, Empty Glass Pocket Travel Atomiser for Perfume and Afte | D32: 4.4 | E32: 5447 | F32: 12849 | G32: KRW | I32: https://www.amazon.com/-/en/Refillable-Atomiser-Aluminium-Rotatable-Aftershave/dp/B0746B4718/ref=zg_bs_g_122877031_d_sccl_30/701-5081554-7062441
A33: 31 | B33: B0FQJN4S4Z
A34: 32 | B34: B07WRMFTF2
A35: 33 | B35: B0DGLVFL8Q
A36: 34 | B36: B000XEATY0
A37: 35 | B37: B07417JWRR
A38: 36 | B38: B0GWNF7TTS
A39: 37 | B39: B0DR8DT2VZ
A40: 38 | B40: B0D8L92LQW
A41: 39 | B41: B0B3NFT6CN
A42: 40 | B42: B0DYK9JF9J
A43: 41 | B43: B09DCXVC4H
A44: 42 | B44: B00HWQFR3A
... A52: 50 | B52: B09X31TQFZ
A53: 51 | B53: B07V9N1133 | C53: HAWAIIAN Tropic Tropic Aloha Coco Fragrance Spray 250ml | D53: 4.4 | E53: 1399 | F53: 15197 | G53: KRW | I53: https://www.amazon.com/-/en/HAWAIIAN-Tropic-Aloha-Fragrance-Spray/dp/B07V9N1133/ref=zg_bs_g_122877031_d_sccl_1/701-5081554-7062441
A54: 52 | B54: B0725GYPC9 | C54: Boss The Scent Eau de Parfum | D54: 4.6 | E54: 6745 | F54: 51942 | G54: KRW | I54: https://www.amazon.com/-/en/Hugo-Boss-Scent-Toilette-pack/dp/B0725GYPC9/ref=zg_bs_g_122877031_d_sccl_2/701-5081554-7062441
A55: 53 | B55: B0GTR9PV9N | C55: Jean & Len Body Mist Dream Cloud, Macadamia, Vanilla & Caramel 100 ml | With panthenol and vanilla extract, long-lasting, veg | D55: 4.1 | E55: 47 | F55: 6352 | G55: KRW | I55: https://www.amazon.com/-/en/Jean-Len-Macadamia-Vanilla-Caramel/dp/B0GTR9PV9N/ref=zg_bs_g_122877031_d_sccl_3/701-5081554-7062441
A56: 54 | B56: B00QAIYM6O | C56: Roberto Cavalli Paradiso Femme/Woman, Eau de Parfum, Vaporiser/Spray, Pack of 1 | D56: 4.6 | E56: 3294 | F56: 43049 | G56: KRW | I56: https://www.amazon.com/-/en/Roberto-Cavalli-Paradiso-Parfum-Women/dp/B00QAIYM6O/ref=zg_bs_g_122877031_d_sccl_4/701-5081554-7062441
A57: 55 | B57: B0BLGJHQLJ | C57: Khamrah Eau de Parfum for Men 100ml | D57: 4.5 | E57: 3890 | F57: 46040 | G57: KRW | I57: https://www.amazon.com/-/en/Khamrah-Eau-Parfum-Men-100ml/dp/B0BLGJHQLJ/ref=zg_bs_g_122877031_d_sccl_5/701-5081554-7062441
A58: 56 | B58: B0B8TQ7YRW | C58: Lattafa Asad Unisex Eau de Parfum Spray, Perfume for Men and Women, 100 ml | D58: 4.3 | E58: 28142 | F58: 44223 | G58: KRW | I58: https://www.amazon.com/-/en/Lattafa-Unisex-Parfum-Spray-Perfume/dp/B0B8TQ7YRW/ref=zg_bs_g_122877031_d_sccl_6/701-5081554-7062441
A59: 57 | B59: B000UUO5VA | C59: Calvin Klein CK IN2U Eau de Toilette for her, floral-fruchtiger Damenduft | D59: 4.6 | E59: 35478 | F59: 28142 | G59: KRW | I59: https://www.amazon.com/-/en/Calvin-Klein-IN2U-Toilette-Women/dp/B000UUO5VA/ref=zg_bs_g_122877031_d_sccl_7/701-5081554-7062441
A60: 58 | B60: B07R2QDXLL | C60: Störtebekker® Premium Alum Stone - Natural Aftershave - Alum Blood Stiller - Soothes the Skin After Shaving with Safety Razor | D60: 4.7 | E60: 2830 | F60: 17673 | G60: KRW | I60: https://www.amazon.com/-/en/St%C3%B6rtebekker%C2%AE-Premium-Alum-Stone-Aftershave/dp/B07R2QDXLL/ref=zg_bs_g_122877031_d_sccl_8/701-5081554-7062441
A61: 59 | B61: B00BOH71IC | C61: Laura Biagiotti Laura Eau De Toilette Spray – 25 ml | Floral-fruity, aquatic composition, fresh and delicate notes, sculptura | D61: 4.7 | E61: 555 | F61: 36826 | G61: KRW | I61: https://www.amazon.com/-/en/Laura-Biagiotti-Eau-Toilette-Spray/dp/B00BOH71IC/ref=zg_bs_g_122877031_d_sccl_9/701-5081554-7062441
A62: 60 | B62: B003PQANKS | C62: Tommy Girl EDT 100ml - Red Stripe | Fruity and floral, fresh floral fragrance with fruity notes, transparent glass bottle | D62: 4.7 | E62: 8510 | F62: 69937 | G62: KRW | I62: https://www.amazon.com/-/en/Tommy-Girl-EDT-100ml-Stripe/dp/B003PQANKS/ref=zg_bs_g_122877031_d_sccl_10/701-5081554-7062441
A63: 61 | B63: B0D5YMGXLL | C63: MEXX Black Man Eau de Parfum Seductive Intense Fragrance with Aquatic Woody Notes for Sensual Men, 50 ml | D63: 4.4 | E63: 630 | F63: 22433 | G63: KRW | I63: https://www.amazon.com/-/en/Seductive-Intense-Fragrance-Aquatic-Sensual/dp/B0D5YMGXLL/ref=zg_bs_g_122877031_d_sccl_11/701-5081554-7062441
A64: 62 | B64: B0CWS7V7TT | C64: KORRES WHITE TEA Eau de Toilette for Women Travel Size, Floral & Fresh | Deluxe travel size. Vegan eau de toilette with white | D64: 4.4 | E64: 226 | F64: 17046 | G64: KRW | I64: https://www.amazon.com/-/en/KORRES-Toilette-Fragrance-Delicate-Jasmine/dp/B0CWS7V7TT/ref=zg_bs_g_122877031_d_sccl_12/701-5081554-7062441
... A82: 80 | B82: B0FJ2D52DC | C82: bruno banani Vanilla Muse Body & Hair Splash for Her, Fruity Amber Fragrance with White Flowers, Peach and Vanilla, Intense, | D82: 4.5 | E82: 82 | F82: 9633 | G82: KRW | I82: https://www.amazon.com/-/en/Vanilla-Fragrance-Long-Lasting-Seductively-Feminine/dp/B0FJ2D52DC/ref=zg_bs_g_122877031_d_sccl_30/701-5081554-7062441
A83: 81 | B83: B0C6F9ZY7D
A84: 82 | B84: B07K1BW1XY
A85: 83 | B85: B0H34M9PDR
A86: 84 | B86: B000C1UC8C
A87: 85 | B87: B07WCVW56S
A88: 86 | B88: B0FQJLTJR7
A89: 87 | B89: B0030M2PVC
A90: 88 | B90: B0DZBZ7VVS
A91: 89 | B91: B0CW6F8GPD
A92: 90 | B92: B0G4MZCWKX
A93: 91 | B93: B0FCYTSQJY
A94: 92 | B94: B0FQJYQSX6
... A102: 100 | B102: B0H2FTDF28

Sheet Skin Care1
A1: Amazon Best Sellers — Skin Care | I1: 🔗 Best Sellers 페이지 열기
A2: rank | B2: asin | C2: title | D2: rating | E2: ratings_count | F2: price | G2: currency | H2: offers_text | I2: url
A3: 1 | B3: B09V7Z4TJG | C3: medicube Zero Pore Pad 2.0 Peeling Toner Pads for Pore Care | Double-sided face pad with 4.5% AHA & 0.45% BHA, lactic acid, s | D3: 4.6 | E3: 30031 | F3: 33771 | G3: KRW | I3: https://www.amazon.com/-/en/medicube-Zero-Pore-Peeling-Toner/dp/B09V7Z4TJG/ref=zg_bs_g_122878031_d_sccl_1/701-5081554-7062441
A4: 2 | B4: B0B2RM68G2 | C4: Biodance Bio-Collagen Real Deep Mask Pack of 4 - Face Masks, Face Mask, Women, Face Mask, Face Mask, Pore Refining, Wrinkle T | D4: 4.4 | E4: 43404 | F4: 18911 | G4: KRW | I4: https://www.amazon.com/-/en/Biodance-Bio-Collagen-Real-Deep-Mask/dp/B0B2RM68G2/ref=zg_bs_g_122878031_d_sccl_2/701-5081554-7062441
A5: 3 | B5: B0DK4Y2YP3 | C5: celimax The Vita A Retinal Shot Tightening Booster | 0.1% retinal, 3% matryxyl, highly effective retinoid, anti-ageing, pore | D5: 4.4 | E5: 23203 | F5: 46861 | G5: KRW | I5: https://www.amazon.com/-/en/celimax-Vita-Retinal-Tightening-Booster/dp/B0DK4Y2YP3/ref=zg_bs_g_122878031_d_sccl_3/701-5081554-7062441
A6: 4 | B6: B0BFQ9RD5B | C6: d'alba Piedmont Italian White Truffle First Spray Serum (100 ml) | Moisturizing Facial Spray Radiant Skin Soothing Vegan Kore | D6: 4.4 | E6: 33969 | F6: 34398 | G6: KRW | I6: https://www.amazon.com/-/en/dalba-Piedmont-Italian-White-Truffle/dp/B0BFQ9RD5B/ref=zg_bs_g_122878031_d_sccl_4/701-5081554-7062441
A7: 5 | B7: B01MDTVZTZ | C7: The Ordinary Niacinamide 10% + Zinc 1%, 30 ml | D7: 4.6 | E7: 62076 | F7: 8121 | G7: KRW | I7: https://www.amazon.com/-/en/Ordinary-Niacinamide-10-Zinc-1/dp/B01MDTVZTZ/ref=zg_bs_g_122878031_d_sccl_5/701-5081554-7062441
A8: 6 | B8: B0DBF65JYY | C8: medicube PDRN Pink Peptide Serum with Salmon DNA 30 ml | Glow Serum, Peptides, Niacinamide, Moisture, Firming Care, Even Comp | D8: 4.6 | E8: 20840 | F8: 29396 | G8: KRW | I8: https://www.amazon.com/-/en/medicube-PDRN-Peptide-Serum-Salmon/dp/B0DBF65JYY/ref=zg_bs_g_122878031_d_sccl_6/701-5081554-7062441
A9: 7 | B9: B071914GGL | C9: The Ordinary Glycolic Acid 7% Exfoliating Toner, Aufhellender und glättender täglicher Toner für einen gleichmäßigeren Hautto | D9: 4.6 | E9: 60026 | F9: 18526 | G9: KRW | I9: https://www.amazon.com/-/en/Ordinary-Glycolic-Acid-Toning-Solution/dp/B071914GGL/ref=zg_bs_g_122878031_d_sccl_7/701-5081554-7062441
A10: 8 | B10: B09SZ5JX2Y | C10: d'alba Piedmont White Truffle Double Serum All-in-One Multi Balm | Vegan Skin Care, 3-in-1 Eye Care with White Truffle Agains | D10: 4.2 | E10: 8560 | F10: 43178 | G10: KRW | I10: https://www.amazon.com/-/en/dalba-Piedmont-White-Truffle-Double/dp/B09SZ5JX2Y/ref=zg_bs_g_122878031_d_sccl_8/701-5081554-7062441
A11: 9 | B11: B0B7RQ46LD | C11: CeraVe Deep Pore Cleansing Face Wash Gel for Pimples, 236 ml | For blemished skin. Frees pores with salicylic acid and clay. | D11: 4.5 | E11: 34593 | F11: 25119 | G11: KRW | I11: https://www.amazon.com/-/en/CeraVe-Deep-Pore-Cleansing-Pimples/dp/B0B7RQ46LD/ref=zg_bs_g_122878031_d_sccl_9/701-5081554-7062441
A12: 10 | B12: B0FVT77ZLL | C12: Anua PDRN Collagen Glow Facial Serum Spray, Feuchtigkeitsspendender Gesichtsspray, Mit Hyaluronsäure, Für Alle Hauttypen, Feu | D12: 4.6 | E12: 6023 | F12: 45011 | G12: KRW | I12: https://www.amazon.com/-/en/Feuchtigkeitsspendender-Gesichtsspray-Hyalurons%C3%A4ure-Feuchtigkeit-aufpolsternde/dp/B0FVT77ZLL/ref=zg_bs_g_122878031_d_sccl_10/701-5081554-7062441
A13: 11 | B13: B0GD6R7CFJ | C13: Biodance Collagen Peptide Eye Pads, Anti-Wrinkle Pads for Face and Laughter Wrinkles, Eye Mask for Fine Lines, Bags and Wrink | D13: 4.5 | E13: 3482 | F13: 46619 | G13: KRW | I13: https://www.amazon.com/-/en/Biodance-Collagen-Anti-Wrinkle-Laughter-Wrinkles/dp/B0GD6R7CFJ/ref=zg_bs_g_122878031_d_sccl_11/701-5081554-7062441
A14: 12 | B14: B09JVNZVH3 | C14: Beauty of Joseon Relief Sun Rice + Probiotics, Korean Skincare, Korean Cosmetics, No White Veil, Hydrating Sun Cream Face SPF | D14: 4.6 | E14: 12617 | F14: 22433 | G14: KRW | I14: https://www.amazon.com/-/en/Beauty-Joseon-Probiotics-Cosmetics-Hydrating/dp/B09JVNZVH3/ref=zg_bs_g_122878031_d_sccl_12/701-5081554-7062441
... A32: 30 | B32: B0CNCL35CH | C32: Dr.Melaxin Collagen Multi Balm Stick, Korean Anti-Wrinkle Stick with Calcium and Adenosine for Eyes, Neck and Face, Firming C | D32: 3.7 | E32: 9453 | F32: 28946 | G32: KRW | I32: https://www.amazon.com/-/en/Dr-Melaxin-Collagen-Anti-Wrinkle-Calcium-Adenosine/dp/B0CNCL35CH/ref=zg_bs_g_122878031_d_sccl_30/701-5081554-7062441
A33: 31 | B33: B0CGJLC8G9
A34: 32 | B34: B0DG2T4R5R
A35: 33 | B35: B0C3QV923Z
A36: 34 | B36: B0124BRNGG
A37: 35 | B37: B0FX418XT8
A38: 36 | B38: B0DWFLY18Y
A39: 37 | B39: B0CM2PPNMW
A40: 38 | B40: B0BPSWK6Y5
A41: 39 | B41: B0BRMYHMS5
A42: 40 | B42: B08CCM3Q2T
A43: 41 | B43: B0D4Y6MNTF
A44: 42 | B44: B087QX6CMQ
... A52: 50 | B52: B0CPT5V23G
A53: 51 | B53: B0GS97T2MV | C53: celimax The Vita-A Retinal Shot Tightening Dual Cream, 1.69 fl.oz | 0.05% Retinal, 3% Matryxyl, 5% Panthenol, Highly Effectiv | D53: 4.2 | E53: 251 | F53: 34575 | G53: KRW | I53: https://www.amazon.com/-/en/celimax-Vita-Retinal-Tightening-Cream/dp/B0GS97T2MV/ref=zg_bs_g_122878031_d_sccl_1/701-5081554-7062441
A54: 52 | B54: B0DWMSM6Y9 | C54: medicube Eye Serum with Salmon DNA PDRN & Pink Peptides | Retinol Serum, PDRN, Niacinamide, Moisture, Care for Fine Lines, Ev | D54: 4.4 | E54: 5752 | F54: 25714 | G54: KRW | I54: https://www.amazon.com/-/en/medicube-Serum-Salmon-PDRN-Peptides/dp/B0DWMSM6Y9/ref=zg_bs_g_122878031_d_sccl_2/701-5081554-7062441
A55: 53 | B55: B0FPCC599C | C55: medicube Body Peel Shot with Hypochloric Acid | Gentle body scrub for skin cells & uneven complexion with rice extract and pa | D55: 4.2 | E55: 1785 | F55: 35218 | G55: KRW | I55: https://www.amazon.com/-/en/medicube-Body-Peel-Shot-Hypochloric/dp/B0FPCC599C/ref=zg_bs_g_122878031_d_sccl_3/701-5081554-7062441
A56: 54 | B56: B01LEJ5MSK | C56: Cosrx Advanced Snail 92 All-in-One Creme 100 g | D56: 4.4 | E56: 60274 | F56: 24524 | G56: KRW | I56: https://www.amazon.com/-/en/Cosrx-Advanced-Snail-All-Creme/dp/B01LEJ5MSK/ref=zg_bs_g_122878031_d_sccl_4/701-5081554-7062441
A57: 55 | B57: B0FDWVV76F | C57: L'Oréal Paris Instant Lifting Anti-Tear Bag - Effective Against Eye Bags, Wrinkles and Swelling - Tightens and Smooths in Jus | D57: 3.4 | E57: 480 | F57: 25714 | G57: KRW | I57: https://www.amazon.com/-/en/LOr%C3%A9al-Paris-Instant-Lifting-Anti-Tear/dp/B0FDWVV76F/ref=zg_bs_g_122878031_d_sccl_5/701-5081554-7062441
A58: 56 | B58: B0GCC2JV65 | C58: medicube NAD EGF Firming Serum for Face & Neck | Anti-Aging Serum, EGF Peptide, NAD, Collagen, Elasticity Care, Pore Care, Fi | D58: 4.6 | E58: 1673 | I58: https://www.amazon.com/-/en/medicube-Firming-Serum-Face-Neck/dp/B0GCC2JV65/ref=zg_bs_g_122878031_d_sccl_6/701-5081554-7062441
A59: 57 | B59: B0798LQHHZ | C59: Hawaiian Tropic Silk Hydration Air Soft After Sun Lotion Coconut Papaya 180 ml, Pack of 1. | D59: 4.7 | E59: 9484 | F59: 8845 | G59: KRW | I59: https://www.amazon.com/-/en/Hawaiian-Tropic-Hydration-Lotion-Coconut/dp/B0798LQHHZ/ref=zg_bs_g_122878031_d_sccl_7/701-5081554-7062441
A60: 58 | B60: B08J58X1BS | C60: Nivea Double Effect Eye Make-Up Remover, Make-Up Water for Sensitive Eye Area, Facial Cleanser Removes Extremely Waterproof M | D60: 4.6 | E60: 1536 | F60: 12704 | G60: KRW | I60: https://www.amazon.com/-/en/Make-Up-Sensitive-Cleanser-Extremely-Waterproof/dp/B08J58X1BS/ref=zg_bs_g_122878031_d_sccl_8/701-5081554-7062441
A61: 59 | B61: B0D1G7XF9X | C61: medicube Zero Pore Blackhead Mud Mask for Pore Cleansing | AHA BHA PHA Clay Mask, Pore & Blackhead Care, Cooling Skin Feeling | D61: 4.4 | E61: 6662 | F61: 33722 | G61: KRW | I61: https://www.amazon.com/-/en/medicube-Zero-Pore-Blackhead-Cleansing/dp/B0D1G7XF9X/ref=zg_bs_g_122878031_d_sccl_9/701-5081554-7062441
A62: 60 | B62: B006O8NYOQ | C62: Vaseline – Vaseline original jelly, 1 x 50 ml | D62: 4.7 | E62: 33115 | F62: 18638 | G62: KRW | I62: https://www.amazon.com/-/en/Vaseline-original-jelly-50/dp/B006O8NYOQ/ref=zg_bs_g_122878031_d_sccl_10/701-5081554-7062441
A63: 61 | B63: B0GF86QJK7 | C63: BIODANCE Collagen Peptide Jelly Serum Spray, Feuchtigkeitsspendendes Gesichtsspray, Hydrogel zum Aufsprühen, Reiseutensilien | D63: 4.3 | E63: 3358 | F63: 26357 | G63: KRW | I63: https://www.amazon.com/-/en/BIODANCE-Feuchtigkeitsspendendes-Gesichtsspray-Reiseutensilien-Selbstpflege-Geschenke/dp/B0GF86QJK7/ref=zg_bs_g_122878031_d_sccl_11/701-5081554-7062441
A64: 62 | B64: B07N74F8NP | C64: The Ordinary Natural Moisturising Factors + HA, Natural Moisturising Factors and Hyaluronic Acid to Support the Skin Barrier | D64: 4.5 | E64: 14136 | F64: 18011 | G64: KRW | I64: https://www.amazon.com/-/en/Ordinary-Natural-Moisturising-Hyaluronic-Hydration/dp/B07N74F8NP/ref=zg_bs_g_122878031_d_sccl_12/701-5081554-7062441
A65: 63 | B65: B0DH3TMC9Q | C65: TALLOW Naturals Barrier Repair Pure - Known from the Cave of the Lions - 100% Organic Beef Tallow Cream, Organic Beef Tallow | D65: 3.9 | E65: 556 | F65: 56268 | G65: KRW | I65: https://www.amazon.com/-/en/TALLOW-Naturals-Barrier-Repair-Pure/dp/B0DH3TMC9Q/ref=zg_bs_g_122878031_d_sccl_13/701-5081554-7062441
A66: 64 | B66: B0849D9GB4 | C66: Neutrogena Hydro Boost Aqua Gel, Moisturising Face Cream with Hyaluronic Acid, Amino Acids and Electrolytes, Fast Absorbing M | D66: 4.5 | E66: 4654 | F66: 10903 | G66: KRW | I66: https://www.amazon.com/-/en/Neutrogena-Moisturising-Hyaluronic-Electrolytes-Combination/dp/B0849D9GB4/ref=zg_bs_g_122878031_d_sccl_14/701-5081554-7062441
A67: 65 | B67: B0DL92QM79 | C67: Anua Niacinamide 10 + TXA 4 Serum, Pflege bei dunklen Flecken, Hyaluronsäure, Tranexamsäure, Leichtes & hydratisierendes All- | D67: 4.5 | E67: 3658 | F67: 32468 | G67: KRW | I67: https://www.amazon.com/-/en/Niacinamide-Hyalurons%C3%A4ure-Tranexams%C3%A4ure-Leichtes-hydratisierendes/dp/B0DL92QM79/ref=zg_bs_g_122878031_d_sccl_15/701-5081554-7062441
A68: 66 | B68: B0DKSVZR69 | C68: Anua Heartleaf Quercetinol Pore Deep Cleansing Foam, Korean Skincare, 150 | Gentle Facial Cleanser, for Double Cleansing, BHA | D68: 4.6 | E68: 2125 | F68: 24041 | G68: KRW | I68: https://www.amazon.com/-/en/Heartleaf-Quercetinol-Cleansing-Korean-Skincare/dp/B0DKSVZR69/ref=zg_bs_g_122878031_d_sccl_16/701-5081554-7062441
A69: 67 | B69: B0FJY64RQT | C69: Whipped Beef Tallow Cream, Beef Tallow Skincare, 100% Grass-Fed Beef Tallow and Honey Balm, Beef Tallow for Skin Care, Moistu | D69: 4.5 | E69: 387 | F69: 13653 | G69: KRW | I69: https://www.amazon.com/-/en/Whipped-Skincare-Grass-Fed-Moisturising-Unscented/dp/B0FJY64RQT/ref=zg_bs_g_122878031_d_sccl_17/701-5081554-7062441
A70: 68 | B70: B07LGCGG6R | C70: Erborian CC Red Correct - Cream against Redness with Centella Asiatica - Korean Face Care with Soothing Effect for a Naturall | D70: 4.4 | E70: 8936 | F70: 22498 | G70: KRW | I70: https://www.amazon.com/-/en/Erborian-Red-Correct-Naturally-Complexion/dp/B07LGCGG6R/ref=zg_bs_g_122878031_d_sccl_18/701-5081554-7062441
... A82: 80 | B82: B0B42WD1J2 | C82: Garnier SkinActive Moisturising Cloth Masks for Sensitive Skin, with Hyaluronic Acid and Vitamin C, for Radiant Skin and a Gl | D82: 4.6 | E82: 977 | F82: 10790 | G82: KRW | I82: https://www.amazon.com/-/en/Garnier-SkinActive-Moisturising-Sensitive-Hyaluronic/dp/B0B42WD1J2/ref=zg_bs_g_122878031_d_sccl_30/701-5081554-7062441
A83: 81 | B83: B00F713IK6
A84: 82 | B84: B09V95T26W
A85: 83 | B85: B00X68X3CU
A86: 84 | B86: B0DG2TN9MC
A87: 85 | B87: B09HR6X5C7
A88: 86 | B88: B000ORV3NC
A89: 87 | B89: B0CYS776TR
A90: 88 | B90: B084PVVPSM
A91: 89 | B91: B086VKZZZY
A92: 90 | B92: B0DJRK6N71
A93: 91 | B93: B01DD5LOQ2
A94: 92 | B94: B0B5M2VD5B
... A102: 100 | B102: B0FWK57DL4

Sheet Make-up
A1: Amazon Best Sellers — Make-up | I1: 🔗 Best Sellers 페이지 열기
A2: rank | B2: asin | C2: title | D2: rating | E2: ratings_count | F2: price | G2: currency | H2: offers_text | I2: url
A3: 1 | B3: B08P4YPB8Q | C3: Maybelline New York Black Mascara for Extremely Long Eyelashes, Lash Sensational Sky High Mascara, Very Black, 7.2 ml | D3: 4.4 | E3: 37313 | F3: 14039 | G3: KRW | I3: https://www.amazon.com/-/en/Maybelline-Mascara-Extremely-Eyelashes-Sensational/dp/B08P4YPB8Q/ref=zg_bs_g_122880031_d_sccl_1/701-5081554-7062441
A4: 2 | B4: B07LGPCY2B | C4: Golecha 100% Natural Henna Paste Cones (Red–Brown) No Mix, No PPD (Paraphenylenediamine), 125 g 4 pcs | D4: 3.9 | E4: 4199 | F4: 8362 | G4: KRW | I4: https://www.amazon.com/-/en/Golecha-Natural-Henna-Red-Brown-Paraphenylenediamine/dp/B07LGPCY2B/ref=zg_bs_g_122880031_d_sccl_2/701-5081554-7062441
A5: 3 | B5: B01N5QC1CL | C5: M.Asam Magic Finish, 30 ml | 4-in-1 primer, make-up, powder & concealer, concealed, balances, beautifies and perfected, for l | D5: 4.4 | E5: 27127 | F5: 61109 | G5: KRW | I5: https://www.amazon.com/-/en/M-Asam-Magic-Finish-30-ml/dp/B01N5QC1CL/ref=zg_bs_g_122880031_d_sccl_3/701-5081554-7062441
A6: 4 | B6: B07NYTY2QG | C6: Syoss Eyebrow Kit 4-1 Dark Brown, 17 ml, Pack of 1 (1 x 17 ml) | Permanent eyebrow colour, water and smudgeproof, natural loo | D6: 4.5 | E6: 8160 | F6: 11176 | G6: KRW | I6: https://www.amazon.com/-/en/Syoss-Eyebrow-Dark-Brown-Pack/dp/B07NYTY2QG/ref=zg_bs_g_122880031_d_sccl_4/701-5081554-7062441
A7: 5 | B7: B0CGMBM6D4 | C7: L'Oréal Paris Setting Spray for Fixing Make-Up, Transfer Resistant in 3 | No transfer, quick drying, look up to 36 hours, swe | D7: 4.4 | E7: 6237 | F7: 11578 | G7: KRW | I7: https://www.amazon.com/-/en/Paris-Setting-Make-Up-Transfer-Resistant/dp/B0CGMBM6D4/ref=zg_bs_g_122880031_d_sccl_5/701-5081554-7062441
A8: 6 | B8: B07XZ7PXD8 | C8: Lashcocaine® Professional Eyelash Serum, Eyelash Booster, Svenja Walberg®, Includes Measuring Cards for Visible Success | D8: 4.1 | E8: 18095 | F8: 104512 | G8: KRW | I8: https://www.amazon.com/-/en/Lashcocaine%C2%AE-Professional-Svenja-Walberg%C2%AE-Measuring/dp/B07XZ7PXD8/ref=zg_bs_g_122880031_d_sccl_6/701-5081554-7062441
A9: 7 | B9: B00PFCSXD4 | C9: Maybelline New York Mascara for Volume and Definition, Lash Sensational, Very Black, 9.5 ml | D9: 4.4 | E9: 72333 | F9: 10678 | G9: KRW | I9: https://www.amazon.com/-/en/Maybelline-Mascara-Definition-Sensational-Black/dp/B00PFCSXD4/ref=zg_bs_g_122880031_d_sccl_7/701-5081554-7062441
A10: 8 | B10: B00CDO12Z8 | C10: Maybelline New York Instant Anti-Age Effect Concealer, with Micro Eraser Applicator, No. 01 Light, 6.8 ml | D10: 4.4 | E10: 5565 | F10: 8780 | G10: KRW | I10: https://www.amazon.com/-/en/Maybelline-Instant-Anti-Age-Concealer-Applicator/dp/B00CDO12Z8/ref=zg_bs_g_122880031_d_sccl_8/701-5081554-7062441
A11: 9 | B11: B093VK76NH | C11: KIKO Milano 3D Hydra Lip Gloss - Shade 32 Pearly Natural Rose | Moisturising | 3D volume effect | non sticky | flocked applic | D11: 4.6 | E11: 31372 | F11: 13251 | G11: KRW | I11: https://www.amazon.com/-/en/KIKO-Milano-Hydra-Lip-Gloss/dp/B093VK76NH/ref=zg_bs_g_122880031_d_sccl_9/701-5081554-7062441
A12: 10 | B12: B01N5TO559 | C12: Manhattan Endless Stay Waterproof Gel Eyeliner | D12: 4.4 | E12: 9653 | F12: 3168 | G12: KRW | I12: https://www.amazon.com/-/en/Manhattan-Endless-Stay-Waterproof-Eyeliner/dp/B01N5TO559/ref=zg_bs_g_122880031_d_sccl_10/701-5081554-7062441
A13: 11 | B13: B0F1XMFGF4 | C13: VEYESBEAUTY Eyelash Extensions Set Cluster Lash Extension Manga 8-18 mm | Newbie's Five-Second Eyelash Cluster Wispy Cluster | D13: 4.5 | E13: 1011 | F13: 51444 | G13: KRW | I13: https://www.amazon.com/-/en/VEYESBEAUTY-Eyelash-Extensions-Cluster-Extension/dp/B0F1XMFGF4/ref=zg_bs_g_122880031_d_sccl_11/701-5081554-7062441
A14: 12 | B14: B0CZ63J96Q | C14: NYX Professional Makeup Buttermelt Blush, Blush, Creamy Texture with Shea Butter, Almond Butter & Mango Butter, Easy to Blend | D14: 4.5 | E14: 12813 | F14: 12093 | G14: KRW | I14: https://www.amazon.com/-/en/NYX-Professional-Makeup-Buttermelt-Texture/dp/B0CZ63J96Q/ref=zg_bs_g_122880031_d_sccl_12/701-5081554-7062441
... A32: 30 | B32: B07LGCGG6R | C32: Erborian CC Red Correct - Cream against Redness with Centella Asiatica - Korean Face Care with Soothing Effect for a Naturall | D32: 4.4 | E32: 8936 | F32: 22498 | G32: KRW | I32: https://www.amazon.com/-/en/Erborian-Red-Correct-Naturally-Complexion/dp/B07LGCGG6R/ref=zg_bs_g_122880031_d_sccl_30/701-5081554-7062441
A33: 31 | B33: B0B5DYY1HQ
A34: 32 | B34: B07VRLQ8TS
A35: 33 | B35: B00QPNVC0I
A36: 34 | B36: B0G52CKKMT
A37: 35 | B37: B08M58SWB1
A38: 36 | B38: B003HL9SVG
A39: 37 | B39: B0FDTCZB8Q
A40: 38 | B40: B0BQZ36ZDZ
A41: 39 | B41: B0BWDKRMHV
A42: 40 | B42: B07ZR1DXGX
A43: 41 | B43: B0GS5V8NMR
A44: 42 | B44: B0GLM4C9X7
... A52: 50 | B52: B0GX74XLZS
A53: 51 | B53: B0B2Q36W37 | C53: Manhattan Lasting Perfection Lip Liner Fb.94 F Penny Brown Long Lasting Opaque Contour Pen 2g | D53: 4.5 | E53: 1666 | F53: 3168 | G53: KRW | I53: https://www.amazon.com/-/en/Manhattan-Lasting-Perfection-Opaque-Contour/dp/B0B2Q36W37/ref=zg_bs_g_122880031_d_sccl_1/701-5081554-7062441
A54: 52 | B54: B0FPCP6KDM | C54: Lvmixwig Manga Eyelash Extensions Natural Artificial Eyelashes Anime Lash Cluster Fairy Cluster Lashes Wispy CD Curly 10-16 m | D54: 4.2 | E54: 198 | F54: 14457 | G54: KRW | I54: https://www.amazon.com/-/en/Lvmixwig-Extensions-Artificial-Eyelashes-Extension/dp/B0FPCP6KDM/ref=zg_bs_g_122880031_d_sccl_2/701-5081554-7062441
A55: 53 | B55: B0CCV8KF6C | C55: eLander 3 x Temporary Tattoos Natural + 10 x Henna Stencil, Mehndi Tattoos, Cones, Tattoo (Brown) | D55: 4.1 | E55: 508 | F55: 12286 | G55: KRW | I55: https://www.amazon.com/-/en/eLander-Temporary-Tattoos-Natural-Stencil/dp/B0CCV8KF6C/ref=zg_bs_g_122880031_d_sccl_3/701-5081554-7062441
A56: 54 | B56: B0CQKHPPJZ | C56: essence THE Slim Stick Lipstick, No. 104, Pink, Long-Lasting, Nourishing, Express Result, Colour-Intensive, Matte, Vegan, Per | D56: 4.4 | E56: 4792 | F56: 2026 | G56: KRW | I56: https://www.amazon.com/-/en/Lipstick-Long-Lasting-Nourishing-Colour-Intensive-Parabens/dp/B0CQKHPPJZ/ref=zg_bs_g_122880031_d_sccl_4/701-5081554-7062441
A57: 55 | B57: B06XGM135P | C57: Maybelline New York Powder, Mattifying, Pore-refining and Long Lasting, Fit Me! Matte + Poreless, No. 105 Natural | D57: 4.5 | E57: 7167 | F57: 8089 | G57: KRW | I57: https://www.amazon.com/-/en/Maybelline-Mattifying-Pore-refining-Lasting-Poreless/dp/B06XGM135P/ref=zg_bs_g_122880031_d_sccl_5/701-5081554-7062441
A58: 56 | B58: B0DJVVVMCS | C58: Sandstone Scandinavia Kajal Waterproof Eyeliner (Black) | Hypoallergenic, smudge-proof & for sensitive eyes | D58: 4.2 | E58: 2525 | F58: 16065 | G58: KRW | I58: https://www.amazon.com/-/en/Sandstone-Scandinavia-Kajal-Waterproof-Eyeliner/dp/B0DJVVVMCS/ref=zg_bs_g_122880031_d_sccl_6/701-5081554-7062441
A59: 57 | B59: B001HBJ3UE | C59: L 'Oréal Paris Voluminous Mascara, Mascara for 4x Volume and powerful Eyelashes/Lip Gloss 8 ml | D59: 4.4 | E59: 1255 | F59: 9182 | G59: KRW | I59: https://www.amazon.com/-/en/Paris-Voluminous-Mascara-powerful-Eyelashes/dp/B001HBJ3UE/ref=zg_bs_g_122880031_d_sccl_7/701-5081554-7062441
A60: 58 | B60: B0F5PZVH8R | C60: Sixstarhair Eyelash Extensions Set with Eyelash Glue and Remover 544 Pieces | 60D 100D 120D 150D lash cluster, natural to vol | D60: 3.9 | E60: 990 | F60: 20889 | G60: KRW | I60: https://www.amazon.com/-/en/Sixstarhair-Eyelash-Extensions-Remover-Pieces/dp/B0F5PZVH8R/ref=zg_bs_g_122880031_d_sccl_8/701-5081554-7062441
A61: 59 | B61: B0CRSKLX2L | C61: NYX Professional Makeup Buttermelt Bronze Bronzer for Face and Body With Shea Butter, Almond Butter & Mango Butter, For a Sun | D61: 4.6 | E61: 5768 | F61: 11048 | G61: KRW | I61: https://www.amazon.com/-/en/NYX-Professional-Buttermelt-Bronzer-Sun-kissed/dp/B0CRSKLX2L/ref=zg_bs_g_122880031_d_sccl_9/701-5081554-7062441
A62: 60 | B62: B0D1V3PGJP | C62: MIYADIVA 30X Magnifying Mirror with Handle - Double Sided Makeup Mirror (1X/30X), Foldable & Portable for Precise Makeup on t | D62: 4.5 | E62: 2880 | F62: 14457 | G62: KRW | I62: https://www.amazon.com/-/en/MIYADIVA-30X-Magnifying-Mirror-Handle/dp/B0D1V3PGJP/ref=zg_bs_g_122880031_d_sccl_10/701-5081554-7062441
A63: 61 | B63: B00PXSRAM0 | C63: ARTDECO High Performance Eyeshadow Stylo - 3-in-1 pen: Eyeshadow Pen, Eyeliner and Kohl - 1 x 1.4 g | 3 in 1 Stift: Lidschatt | D63: 4.5 | E63: 1694 | F63: 9102 | G63: KRW | I63: https://www.amazon.com/-/en/ARTDECO-High-Performance-Eyeshadow-Stylo/dp/B00PXSRAM0/ref=zg_bs_g_122880031_d_sccl_11/701-5081554-7062441
A64: 62 | B64: B0FPX87BRC | C64: L'Oréal Paris Telescopic Extensionist Mascara, Lengthening Mascara (Colour Black), for Long Eyelashes and an Extreme Lash Ext | D64: 4.2 | E64: 1483 | F64: 16146 | G64: KRW | I64: https://www.amazon.com/-/en/Paris-Telescopic-Extensionist-Lengthening-Eyelashes/dp/B0FPX87BRC/ref=zg_bs_g_122880031_d_sccl_12/701-5081554-7062441
... A82: 80 | B82: B0CL1H6W3L | C82: e.l.f. Halo Glow Liquid Filter, Complexion Booster for a Radiant, Soft Focused Look, with Hyaluronic Acid, Vegan & Cruelty Fr | D82: 4.5 | E82: 1557 | F82: 18381 | G82: KRW | I82: https://www.amazon.com/-/en/l-f-Complexion-Booster-Radiant-Hyaluronic/dp/B0CL1H6W3L/ref=zg_bs_g_122880031_d_sccl_30/701-5081554-7062441
A83: 81 | B83: B0CD21BNBF
A84: 82 | B84: B0FHBX6XS7
A85: 83 | B85: B0GGMKM7SD
A86: 84 | B86: B0DDPTRFJN
A87: 85 | B87: B0C1KF73K9
A88: 86 | B88: B0GBRNLXK1
A89: 87 | B89: B002W5VWTE
A90: 88 | B90: B0932TM32L
A91: 89 | B91: B0C1FN7M8H
A92: 90 | B92: B0FY6CHSGP
A93: 91 | B93: B0BRK9NHJW
A94: 92 | B94: B07BL1CJRN
... A102: 100 | B102: B005U1WKVG

Sheet Bath & Body
A1: Amazon Best Sellers — Bath & Body | I1: 🔗 Best Sellers 페이지 열기
A2: rank | B2: asin | C2: title | D2: rating | E2: ratings_count | F2: price | G2: currency | H2: offers_text | I2: url
A3: 1 | B3: B0CS68SFRB | C3: Sensitive Hand Soap Refill Pack, 2 x 1000 ml, by Amazon | D3: 4.4 | E3: 7245 | F3: 5226 | G3: KRW | I3: https://www.amazon.com/-/en/Sensitive-Hand-Soap-Refill-Amazon/dp/B0CS68SFRB/ref=zg_bs_g_64272031_d_sccl_1/701-5081554-7062441
A4: 2 | B4: B0CQHWV2QX | C4: L'Oréal Men Expert Hydra Energy XXXL Shower Gel/Shampoo for Men, Men’s Body Care, Shower/Bath Set for Cleansing Body, Hair an | D4: 4.8 | E4: 4158 | F4: 8041 | G4: KRW | I4: https://www.amazon.com/-/en/LOr%C3%A9al-Shampoo-Cleansing-Long-Lasting-Freshness/dp/B0CQHWV2QX/ref=zg_bs_g_64272031_d_sccl_2/701-5081554-7062441
A5: 3 | B5: B0CQHXCP1X | C5: L'Oréal Men Expert XXXL 5-in-1 Shower Gel and Shampoo for Men, Shower Bath for Cleansing Body, Hair and Face, Men's Body Care | D5: 4.8 | E5: 3748 | F5: 7253 | G5: KRW | I5: https://www.amazon.com/-/en/LOr%C3%A9al-Shampoo-Cleansing-Long-Lasting-Freshness/dp/B0CQHXCP1X/ref=zg_bs_g_64272031_d_sccl_3/701-5081554-7062441
A6: 4 | B6: B06VT4G8BD | C6: Tea tree oil | Essential tea tree oil - aromatherapy skin care body cold-pressed. (60ml) | D6: 4.5 | E6: 51976 | F6: 16001 | G6: KRW | I6: https://www.amazon.com/-/en/Tea-tree-oil-Essential-cold-pressed/dp/B06VT4G8BD/ref=zg_bs_g_64272031_d_sccl_4/701-5081554-7062441
A7: 5 | B7: B01G3NW5UK | C7: Sagrotan No-Touch Refills Aloe vera. | D7: 4.8 | E7: 15496 | F7: 21340 | G7: KRW | I7: https://www.amazon.com/-/en/Sagrotan-No-Touch-Refills-Aloe-vera/dp/B01G3NW5UK/ref=zg_bs_g_64272031_d_sccl_5/701-5081554-7062441
A8: 6 | B8: B00017Y63O | C8: Biotherm Lait Corporel L'Original Moisturising Body Lotion with Life Plankton for Smooth Skin, Gentle Body Care with Delicate | D8: 4.7 | E8: 4770 | F8: 26293 | G8: KRW | I8: https://www.amazon.com/-/en/BIOTHERM-CUERPO-LECHE-DESECANTE-400ML/dp/B00017Y63O/ref=zg_bs_g_64272031_d_sccl_6/701-5081554-7062441
A9: 7 | B9: B01G3NW5XM | C9: Sagrotan No-Touch Refills Blackberry & Forest fruits | D9: 4.8 | E9: 7218 | F9: 17416 | G9: KRW | I9: https://www.amazon.com/-/en/Sagrotan-No-Touch-Refills-Blackberry-Forest/dp/B01G3NW5XM/ref=zg_bs_g_64272031_d_sccl_7/701-5081554-7062441
A10: 8 | B10: B0996HN6Q9 | C10: by Amazon Vanilla and Coconut Shower Gel, 2 x 500 ml | D10: 4.5 | E10: 5729 | F10: 3506 | G10: KRW | I10: https://www.amazon.com/-/en/Amazon-Vanilla-Coconut-Shower-Gel/dp/B0996HN6Q9/ref=zg_bs_g_64272031_d_sccl_8/701-5081554-7062441
A11: 9 | B11: B0CS623NCL | C11: by Amazon Sensitive Hand Soap 4 x 500 ml | D11: 4.5 | E11: 3311 | F11: 4599 | G11: KRW | I11: https://www.amazon.com/-/en/Amazon-Sensitive-Hand-Soap-500/dp/B0CS623NCL/ref=zg_bs_g_64272031_d_sccl_9/701-5081554-7062441
A12: 10 | B12: B07CG2TD9F | C12: CeraVe Feuchtigkeitslotion für trockene Haut, Körper & Gesicht | Leichte Lotion mit Hyaluron und 3 Essenziellen Ceramiden, 48 | D12: 4.6 | E12: 66196 | F12: 20809 | G12: KRW | I12: https://www.amazon.com/-/en/Cerave-moisturising-lotion-236-ml/dp/B07CG2TD9F/ref=zg_bs_g_64272031_d_sccl_10/701-5081554-7062441
A13: 11 | B13: B00JEBK6JG | C13: WELEDA Shower Gel 1 Set For Man Energy 200 ml | Eucalyptus vetiver fragrance, mild sugar surfactants, washing active amino ac | D13: 4.6 | E13: 1697 | F13: 8041 | G13: KRW | I13: https://www.amazon.com/-/en/WELEDA-Shower-Gel-Set-Energy/dp/B00JEBK6JG/ref=zg_bs_g_64272031_d_sccl_11/701-5081554-7062441
A14: 12 | B14: B0FD3SSVRZ | C14: L'Oréal Men Expert XXXL Shower Gel and Shampoo for Men, Shower Bath for Cleansing Body, Hair, Face and Beard, Men's Body Care | D14: 4.8 | E14: 1425 | F14: 8041 | G14: KRW | I14: https://www.amazon.com/-/en/LOr%C3%A9al-Shampoo-Cleansing-Fragrance-Cedarwood/dp/B0FD3SSVRZ/ref=zg_bs_g_64272031_d_sccl_12/701-5081554-7062441
... A32: 30 | B32: B078VBX61T | C32: Jean & Len Rosemary & Ginger Paraben Free Hand Soap 250ml | Cleans stressed hands, for daily use, liquid soap in refillable p | D32: 4.6 | E32: 6043 | F32: 5339 | G32: KRW | I32: https://www.amazon.com/-/en/Jean-Len-Rosemary-Ginger-Paraben/dp/B078VBX61T/ref=zg_bs_g_64272031_d_sccl_30/701-5081554-7062441
A33: 31 | B33: B0F1YFQ8TJ
A34: 32 | B34: B0CHWDKTG9
A35: 33 | B35: B0GVT87RRG
A36: 34 | B36: B0CPT5V23G
A37: 35 | B37: B0DH3TMC9Q
A38: 36 | B38: B0FJY64RQT
A39: 37 | B39: B0CZFB3T8B
A40: 38 | B40: B0FY6D5X9M
A41: 39 | B41: B0CZS7WH1Y
A42: 40 | B42: B0CZS611TX
A43: 41 | B43: B006O8NYOQ
A44: 42 | B44: B074D5ZKX9
... A52: 50 | B52: B0BCH2XG9T
A53: 51 | B53: B0BTJ9B9SG | C53: L'Oréal Men Expert Shower Gel for Body, Face and Hair, Ice Effect and Extra Cooling Kick for Men, Ultimate Vitality, 1 x 250 | D53: 4.7 | E53: 1645 | F53: 2155 | G53: KRW | I53: https://www.amazon.com/-/en/LOr%C3%A9al-Expert-Cooling-Ultimate-Vitality/dp/B0BTJ9B9SG/ref=zg_bs_g_64272031_d_sccl_1/701-5081554-7062441
A54: 52 | B54: B0CY2GKD62 | C54: Rexona Nonstop Protection Deodorant Stick Cotton Dry Anti Perspirant with 72 Hours Protection Against Sweat and Body Odour 50 | D54: 4.6 | E54: 982 | F54: 4664 | G54: KRW | I54: https://www.amazon.com/-/en/Rexona-Nonstop-Protection-Deodorant-Perspirant/dp/B0CY2GKD62/ref=zg_bs_g_64272031_d_sccl_2/701-5081554-7062441
A55: 53 | B55: B08L4DMDHY | C55: Litamin Blue Dream Bubble Bath 750 ml - with Seaweed & Chestnut Essence - Moisturising Bath Foam for Relaxing Wellness Moment | D55: 4.7 | E55: 279 | F55: 2943 | G55: KRW | I55: https://www.amazon.com/-/en/Litamin-Blue-Dream-Bubble-Bath/dp/B08L4DMDHY/ref=zg_bs_g_64272031_d_sccl_3/701-5081554-7062441
A56: 54 | B56: B00763AAUO | C56: Rexona Max Protection | D56: 4.5 | E56: 4737 | F56: 8041 | G56: KRW | I56: https://www.amazon.com/-/en/Rexona-9012759-Max-Protection/dp/B00763AAUO/ref=zg_bs_g_64272031_d_sccl_4/701-5081554-7062441
A57: 55 | B57: B0CVL5FJYY | C57: Rexona Maximum Protection Anti Perspirant Stick Antibacterial Deodorant Protection Deodorant with 96 Hours Protection Against | D57: 4.6 | E57: 420 | F57: 5339 | G57: KRW | I57: https://www.amazon.com/-/en/Rexona-Protection-Perspirant-Antibacterial-Deodorant/dp/B0CVL5FJYY/ref=zg_bs_g_64272031_d_sccl_5/701-5081554-7062441
A58: 56 | B58: B07RQ895CR | C58: Kneipp Aroma Shower Care - Be Free, Crazy And Happy! Pack Of One, 1 x 200 Ml | D58: 4.7 | E58: 1959 | F58: 2605 | G58: KRW | I58: https://www.amazon.com/-/en/Kneipp-Aroma-Shower-Care-Crazy/dp/B07RQ895CR/ref=zg_bs_g_64272031_d_sccl_6/701-5081554-7062441
A59: 57 | B59: B0CN4YS3PT | C59: Kneipp Aroma Shower Gel with Natural Extracts of Cornflower, Mallow and Naturally Nourishing Oil, Delicate and Smooth Skin Fe | D59: 4.8 | E59: 964 | F59: 3313 | G59: KRW | I59: https://www.amazon.com/-/en/Kneipp-Extracts-Cornflower-Naturally-Nourishing/dp/B0CN4YS3PT/ref=zg_bs_g_64272031_d_sccl_7/701-5081554-7062441
A60: 58 | B60: B0FL7ZW692 | C60: method Simply Nourish Shower Gel, Coconut & Rice Milk, 532 ml | D60: 4.6 | E60: 313 | F60: 7960 | G60: KRW | I60: https://www.amazon.com/-/en/method-Simply-Nourish-Shower-Coconut/dp/B0FL7ZW692/ref=zg_bs_g_64272031_d_sccl_8/701-5081554-7062441
A61: 59 | B61: B00763ABGC | C61: Rexona Max Protection | D61: 4.4 | E61: 11272 | F61: 8041 | G61: KRW | I61: https://www.amazon.com/-/en/Rexona-8712561723435-Max-Protection/dp/B00763ABGC/ref=zg_bs_g_64272031_d_sccl_9/701-5081554-7062441
A62: 60 | B62: B01MEBLP9U | C62: Eucerin UreaRepair Plus 10% Urea Lotion 400 ml | Skin care provides 72 hours of intensive moisture, relieves itching, for rou | D62: 4.5 | E62: 1901 | F62: 41120 | G62: KRW | I62: https://www.amazon.com/-/en/Eucerin-UreaRepair-Plus-Urea-Lotion/dp/B01MEBLP9U/ref=zg_bs_g_64272031_d_sccl_10/701-5081554-7062441
A63: 61 | B63: B007PM1A82 | C63: Embryolisse Lait-Crème Concentré 75 ml | D63: 4.5 | E63: 38066 | F63: 28287 | G63: KRW | I63: https://www.amazon.com/-/en/Embryolisse-Lait-Cr%C3%A8me-Concentr%C3%A9-75-ml/dp/B007PM1A82/ref=zg_bs_g_64272031_d_sccl_11/701-5081554-7062441
A64: 62 | B64: B07YNZH5FM | C64: Dove Deodorant Spray Original Antiperspirant 150 ml | D64: 4.7 | E64: 2194 | F64: 3618 | G64: KRW | I64: https://www.amazon.com/-/en/Dove-Deodorant-Spray-Original-Antiperspirant/dp/B07YNZH5FM/ref=zg_bs_g_64272031_d_sccl_12/701-5081554-7062441
... A82: 80 | B82: B0F2MXR817 | C82: Neutrogena Norwegian Formula Deep Moisture Body Lotion 400ml | Non-greasy body lotion with 10% glycerine and pro-ceramide tec | D82: 4.7 | E82: 665 | F82: 6690 | G82: KRW | I82: https://www.amazon.com/-/en/Neutrogena-Norwegian-Formula-Deep-Moisture/dp/B0F2MXR817/ref=zg_bs_g_64272031_d_sccl_30/701-5081554-7062441
A83: 81 | B83: B0006V5W10
A84: 82 | B84: B08B3H3LZ5
A85: 83 | B85: B07C5XPXDC
A86: 84 | B86: B079L9XX1Y
A87: 85 | B87: B0DMFN6D7J
A88: 86 | B88: B09Q6Q8JP4
A89: 87 | B89: B0B2W7TB5S
A90: 88 | B90: B0D45P5WP1
A91: 89 | B91: B007MCXGO6
A92: 90 | B92: B0GNSXVT8N
A93: 91 | B93: B001O1M8R2
A94: 92 | B94: B08MFDC1N6
... A102: 100 | B102: B003A5OAQW

Sheet Hair Care
A1: Amazon Best Sellers — Hair Care | I1: 🔗 Best Sellers 페이지 열기
A2: rank | B2: asin | C2: title | D2: rating | E2: ratings_count | F2: price | G2: currency | H2: offers_text | I2: url
A3: 1 | B3: B08DJ18C85 | C3: Remington D3198 Ionic Hair Dryer, 2200 W, Ion Care Ceramic Ring: Gentle Styling & Even Heat Distribution, 3 Heat Settings & 2 | D3: 4.5 | E3: 37848 | F3: 21790 | G3: KRW | I3: https://www.amazon.com/Remington-D3198-Ionic-Dryer-Ceramic/dp/B08DJ18C85/ref=zg_bs_g_64486031_d_sccl_1/701-5081554-7062441
A4: 2 | B4: B0F2TQW9QD | C4: BIONOBLE Rosemary Oil Hair Organic - Hair Oil Growth, Scalp Oil, Beard - 50 | 100% natural, hexane-free, rosemary oil, rosema | D4: 4.4 | E4: 64411 | F4: 16049 | G4: KRW | I4: https://www.amazon.com/-/en/BIONOBLE-Rosemary-Oil-Hair-Organic/dp/B0F2TQW9QD/ref=zg_bs_g_64486031_d_sccl_2/701-5081554-7062441
A5: 3 | B5: B09QXNHHK5 | C5: Ninabella Hair Brush without Pulling, Detangler Brush, Detangling Brush & Curling Brush for Fine and Long Hair, Hair Brush fo | D5: 4.8 | E5: 57006 | F5: 16065 | G5: KRW | I5: https://www.amazon.com/-/en/Ninabella-without-Detangler-Detangling-Children/dp/B09QXNHHK5/ref=zg_bs_g_64486031_d_sccl_3/701-5081554-7062441
A6: 4 | B6: B00M9B66BU | C6: UniqOne Hair Treatment Classic, 150 ml, Spray Treatment for More Volume, Smoothness & Easier Combing, Hair Care without Rinsi | D6: 4.6 | E6: 65072 | F6: 16885 | G6: KRW | I6: https://www.amazon.com/-/en/UniqOne-Treatment-Classic-Smoothness-Combing/dp/B00M9B66BU/ref=zg_bs_g_64486031_d_sccl_4/701-5081554-7062441
A7: 5 | B7: B07FFGQY8V | C7: Wella Professionals Koleston Perfect Rich Naturals Permanent Hair Colour, Professional Colouration with up to 100% Grey Cover | D7: 4.6 | E7: 890 | F7: 8893 | G7: KRW | I7: https://www.amazon.com/-/en/Wella-Professionals-Professional-Colouration-Technology/dp/B07FFGQY8V/ref=zg_bs_g_64486031_d_sccl_5/701-5081554-7062441
A8: 6 | B8: B083JKPCFB | C8: Kérastase Genesis Sérum Anti-Chute Fortifiant, Stärkende Haarkur für feines und brüchiges Haar, Gegen Haarausfall und Haarbru | D8: 4.5 | E8: 8478 | F8: 88447 | G8: KRW | I8: https://www.amazon.com/-/en/K%C3%A9rastase-Genesis-Strengthening-Scalp-Brittle/dp/B083JKPCFB/ref=zg_bs_g_64486031_d_sccl_6/701-5081554-7062441
A9: 7 | B9: B00CZCD63O | C9: Revlon Professional Equave Hydro Instant Detangling Conditioner, 500 ml, Detangling Leave in Spray Conditioner for Normal to | D9: 4.6 | E9: 15986 | F9: 25730 | G9: KRW | I9: https://www.amazon.com/-/en/Revlon-Equave-Conditioner-Keratin-500/dp/B00CZCD63O/ref=zg_bs_g_64486031_d_sccl_7/701-5081554-7062441
A10: 8 | B10: B06Y1YBBMV | C10: Wella Professionals FUSION Intense Repair Shampoo | Tiefenreinigungsshampoo, Haarshampoo für bessere Kämmbarkeit, Haarpflege | D10: 4.6 | E10: 15914 | F10: 58423 | G10: KRW | I10: https://www.amazon.com/-/en/Wella-Fusion-Repair-Shampoo-1000/dp/B06Y1YBBMV/ref=zg_bs_g_64486031_d_sccl_8/701-5081554-7062441
A11: 9 | B11: B00MCSW8X0 | C11: Remington Pro-Ceramic Hair straightener, Extra Long, Extra Wide styling plates, Black, S5525 | D11: 4.6 | E11: 25364 | F11: 27016 | G11: KRW | I11: https://www.amazon.com/-/en/Remington-Pro-Ceramic-straightener-styling-plates/dp/B00MCSW8X0/ref=zg_bs_g_64486031_d_sccl_9/701-5081554-7062441
A12: 10 | B12: B01FTBDBJ6 | C12: REVLON PROFESSIONAL Equave Hydro Nutritive Conditioner, 200 ml | D12: 4.5 | E12: 15778 | F12: 28962 | G12: KRW | I12: https://www.amazon.com/-/en/REVLON-PROFESSIONAL-Equave-Nutritive-Conditioner/dp/B01FTBDBJ6/ref=zg_bs_g_64486031_d_sccl_10/701-5081554-7062441
A13: 11 | B13: B0B6LJ9SWM | C13: Tangle Teezer Ultimate Detangler Hair Brush - For Wet & Dry Hair - Detangling Brush for All Hair Types - Two-Stage Bristles R | D13: 4.7 | E13: 65837 | F13: 15583 | G13: KRW | I13: https://www.amazon.com/-/en/Tangle-Teezer-Ultimate-Detangler-Brush/dp/B0B6LJ9SWM/ref=zg_bs_g_64486031_d_sccl_11/701-5081554-7062441
A14: 12 | B14: B0CB121J49 | C14: Wella Professionals Welloxon Perfect Entwickler – Wasserstoffperoxid für Haarfarbe & Tönung – Oxidant für Koleston, Illumina | D14: 4.7 | E14: 419 | F14: 15936 | G14: KRW | I14: https://www.amazon.com/-/en/Wella-Professionals-Welloxon-Perfect-Developer/dp/B0CB121J49/ref=zg_bs_g_64486031_d_sccl_12/701-5081554-7062441
... A32: 30 | B32: B07ZHKTQL3 | C32: Olaplex N°.7 Bonding Oil: Schwereloses Styling-Öl Für Sofortigen Glanz Und Schutz, 30 mL | D32: 4.6 | E32: 16478 | F32: 26534 | G32: KRW | I32: https://www.amazon.com/-/en/OLAPLEX-N%C2%B0-7-Bonding-Shine-Protection/dp/B07ZHKTQL3/ref=zg_bs_g_64486031_d_sccl_30/701-5081554-7062441
A33: 31 | B33: B0DCZXV6HL
A34: 32 | B34: B0F3XPPPJF
A35: 33 | B35: B0DGXF8MVF
A36: 34 | B36: B0B18VMXRL
A37: 35 | B37: B073CWSQ51
A38: 36 | B38: B007CST74S
A39: 37 | B39: B0BM4W3MN2
A40: 38 | B40: B000KEIPC6
A41: 39 | B41: B0DG5ZL41V
A42: 40 | B42: B0D98PWHXN
A43: 41 | B43: B09RPH1148
A44: 42 | B44: B07XYDMY9F
... A52: 50 | B52: B00CGPMEAQ
A53: 51 | B53: B07XQBW27W | C53: Goldwell Elumen Deep NB@5 200ml (3584) | D53: 4.7 | E53: 3219 | F53: 51170 | G53: KRW | I53: https://www.amazon.com/Elumen-Colour-Pure-Red-all/dp/B07XQBW27W/ref=zg_bs_g_64486031_d_sccl_1/701-5081554-7062441
A54: 52 | B54: B083JJHLT4 | C54: Kérastase Genesis Bain Hydra-Fortifiant, Kräftigendes Shampoo bei Haarverlust durch Haarbruch, Haarpflege bei brüchigem Haar | D54: 4.6 | E54: 10056 | F54: 49241 | G54: KRW | I54: https://www.amazon.com/-/en/Kerastase-Genesis-Hydra-Fortifiant-Shampoo-250ml/dp/B083JJHLT4/ref=zg_bs_g_64486031_d_sccl_2/701-5081554-7062441
A55: 53 | B55: B09WX6PPK5 | C55: Olaplex No 6 Bond Smoother, Leave-In Styling Hair Cream Treatment, Smooths, Nourishes and Strengthens, Frizz Control for up t | D55: 4.6 | E55: 6610 | F55: 27338 | G55: KRW | I55: https://www.amazon.com/-/en/Olaplex-Smoother-Treatment-Nourishes-Strengthens/dp/B09WX6PPK5/ref=zg_bs_g_64486031_d_sccl_3/701-5081554-7062441
A56: 54 | B56: B01KLXFBVI | C56: Remington ion hair dryer PROluxe AC9140, 2400 watts, OPTIheat technology, two styling nozzles, diffuser, rose gold | D56: 4.6 | E56: 17226 | F56: 40911 | G56: KRW | I56: https://www.amazon.com/-/en/Remington-AC9140-OPTIheat-technology-diffuser/dp/B01KLXFBVI/ref=zg_bs_g_64486031_d_sccl_4/701-5081554-7062441
A57: 55 | B57: B07BZ59LTB | C57: IMPERIO Scatter Hair Fibre Powder for Fuller and Thicker Hair in Seconds, Hair Bulking Shaker for an Authentic Look, 100% nat | D57: 4.4 | E57: 849 | F57: 33610 | G57: KRW | I57: https://www.amazon.com/-/en/IMPERIO-Scatter-Thicker-Seconds-Authentic/dp/B07BZ59LTB/ref=zg_bs_g_64486031_d_sccl_5/701-5081554-7062441
A58: 56 | B58: B0GHSXYY3Z | C58: Olaplex N°3PLUS Complete Repair Treatment: Die Haarkur Zur Reparatur Von Haarschäden Für Sofort Stärkeres, Geschmeidigeres Ha | D58: 4.5 | E58: 1548 | F58: 41731 | G58: KRW | I58: https://www.amazon.com/-/en/Olaplex-N%C2%B0-3PLUS-Complete-Repair-Treatment/dp/B0GHSXYY3Z/ref=zg_bs_g_64486031_d_sccl_6/701-5081554-7062441
A59: 57 | B59: B071CWXLY5 | C59: Ulg Extra Sharp Hairdressing Scissors 6.5 Inch Au Professional Hair Styling Scissors Japanese Stainless Steel with Removable | D59: 4.5 | E59: 28444 | F59: 11225 | G59: KRW | I59: https://www.amazon.com/-/en/Hairdressing-Scissors-Professional-Stainless-Removable/dp/B071CWXLY5/ref=zg_bs_g_64486031_d_sccl_7/701-5081554-7062441
A60: 58 | B60: B017NHI25M | C60: ghd bodyguard Hitzeschutzspray: Hitzeschutz für Haare bis 230°C, Anti Frizz | Hitzeschutzspray für alle Haartypen, leichter u | D60: 4.5 | E60: 20457 | F60: 68409 | G60: KRW | I60: https://www.amazon.com/-/en/ghd-Bodyguard-Heat-Protection-Spray/dp/B017NHI25M/ref=zg_bs_g_64486031_d_sccl_8/701-5081554-7062441
A61: 59 | B61: B0CCYPDLCQ | C61: ghd Gold Hair Straighteners: For All Hair Types, 26 mm Plates, Long-Lasting Styling, for Sleeks, Straight Hair with More Shin | D61: 4.4 | E61: 6183 | F61: 170670 | G61: KRW | I61: https://www.amazon.com/-/en/ghd-Gold-Straighteners-Styler-Black/dp/B0CCYPDLCQ/ref=zg_bs_g_64486031_d_sccl_9/701-5081554-7062441
A62: 60 | B62: B09HR5KSR8 | C62: K18 Leave-In Repair Hair Mask | D62: 4.3 | E62: 35259 | F62: 56043 | G62: KRW | I62: https://www.amazon.com/-/en/K18-Mini-Leave-Molecular-Hair/dp/B09HR5KSR8/ref=zg_bs_g_64486031_d_sccl_10/701-5081554-7062441
A63: 61 | B63: B07NPNFB41 | C63: FemMas Hair Colour, Professional Cream Hair Colour with Argan Oil, Keratin & Ceramides, as Permanent Hair Colouring or Tint f | D63: 4.5 | E63: 465 | F63: 16049 | G63: KRW | I63: https://www.amazon.com/-/en/Professional-Keratin-Ceramides-Permanent-Colouring/dp/B07NPNFB41/ref=zg_bs_g_64486031_d_sccl_11/701-5081554-7062441
A64: 62 | B64: B08HRP742K | C64: Revlon Professional Nutri Colour Filters | D64: 4.2 | E64: 801 | F64: 45671 | G64: KRW | I64: https://www.amazon.com/-/en/Revlon-Professional-Nutri-Colour-Filters/dp/B08HRP742K/ref=zg_bs_g_64486031_d_sccl_12/701-5081554-7062441
... A82: 80 | B82: B09HR58J5B | C82: L'Oréal Paris Permanent Hair Colour for All Skin Tones, Colouration without Ammonia, Universal Nude Tones with Full Grey Hair | D82: 4.6 | E82: 152 | F82: 9552 | G82: KRW | I82: https://www.amazon.com/-/en/Paris-Permanent-Colouration-Universal-Excellence/dp/B09HR58J5B/ref=zg_bs_g_64486031_d_sccl_30/701-5081554-7062441
A83: 81 | B83: B086SR1KML
A84: 82 | B84: B07Y3GJJ4G
A85: 83 | B85: B003SI2KVS
A86: 84 | B86: B0FCY7DQBG
A87: 85 | B87: B0DT4DFQHW
A88: 86 | B88: B0090Y79SS
A89: 87 | B89: B0DG62KR2Y
A90: 88 | B90: B08NPZRJZX
A91: 89 | B91: B0D3ZG9PSV
A92: 90 | B92: B0DW96HKZ8
A93: 91 | B93: B0C9V91171
A94: 92 | B94: B08P67N41H
... A102: 100 | B102: B07FTGLWDR

Sheet Bath & Body1
A1: Amazon Best Sellers — Bath & Body | I1: 🔗 Best Sellers 페이지 열기
A2: rank | B2: asin | C2: title | D2: rating | E2: ratings_count | F2: price | G2: currency | H2: offers_text | I2: url
A3: 1 | B3: B06Y5P4Z5M | C3: Lancaster Eau de Lancaster Desodorante Crema, 125 ml, Versión actual (Paquete de 2) | D3: 4.8 | E3: 1697 | F3: 11176 | G3: KRW | I3: https://www.amazon.com/-/en/LANCASTER-UAE-Lancaster-Deodorant-Cream/dp/B06Y5P4Z5M/ref=zg_bs_g_4347676031_d_sccl_1/522-8505739-1189111
A4: 2 | B4: B017WK9A3I | C4: Black Tulip - Strawberry and Cream Bath Gel, Nourishing and Moisturizing, Shower Gel with Strawberry Extract and Irresistible | D4: 4.6 | E4: 9105 | F4: 2251 | G4: KRW | I4: https://www.amazon.com/-/en/Black-Tulip-Strawberry-Moisturizing-Irresistible/dp/B017WK9A3I/ref=zg_bs_g_4347676031_d_sccl_2/522-8505739-1189111
A5: 3 | B5: B002SSDHUW | C5: Elizabeth Arden Green Tea Honey Drops Body Cream 500 ml | Body moisturizer with honey and green tea that moisturizes, revital | D5: 4.7 | E5: 21835 | F5: 21694 | G5: KRW | I5: https://www.amazon.com/-/en/Elizabeth-Arden-Green-Honey-Drops/dp/B002SSDHUW/ref=zg_bs_g_4347676031_d_sccl_3/522-8505739-1189111
A6: 4 | B6: B07BYMJMJZ | C6: Kanzy Rosehip Oil 120ml Cold Pressed Unrefined Rosehip Oil for Scars and Stretch Marks, Used as Moisturizer for Body and Skin | D6: 4.5 | E6: 49097 | F6: 19281 | G6: KRW | I6: https://www.amazon.com/-/en/Rosehip-Pressed-Unrefined-Stretch-Moisturizer/dp/B07BYMJMJZ/ref=zg_bs_g_4347676031_d_sccl_4/522-8505739-1189111
A7: 5 | B7: B08829RTWL | C7: Perspirex ® | Original | Anti-Perspirant Deodorant Underarms Roll On for Protection and Freshness Anti Sweat for up to 5 Days | D7: 4.6 | E7: 5998 | F7: 37276 | G7: KRW | I7: https://www.amazon.com/-/en/Perspirex-Anti-Perspirant-Deodorant-Underarms-Protection/dp/B08829RTWL/ref=zg_bs_g_4347676031_d_sccl_5/522-8505739-1189111
A8: 6 | B8: B09XN22JBT | C8: CeraVe, Loción Hidratante de Rostro SPF 50, Para Piel Normal a Seca, Hidratación y Alta Protección Contra los Rayos UVB/UVA, | D8: 4.7 | E8: 9997 | F8: 15743 | G8: KRW | I8: https://www.amazon.com/-/en/CERAVE-Loci%C3%B3n-Hidratante-Rostro-SPF50/dp/B09XN22JBT/ref=zg_bs_g_4347676031_d_sccl_6/522-8505739-1189111
A9: 7 | B9: B08R9NZ65K | C9: Axe Dark Temptation Deodorant - 150ml - Pack of 6, Packaging May Vary | D9: 4.7 | E9: 2160 | F9: 24733 | G9: KRW | I9: https://www.amazon.com/-/en/Axe-Dark-Temptation-Deodorant-Packaging/dp/B08R9NZ65K/ref=zg_bs_g_4347676031_d_sccl_7/522-8505739-1189111
A10: 8 | B10: B0C8ZN274P | C10: Trofolastin Antistretch mark cream Centella asiatica Flexible skin 400 ml | D10: 4.7 | E10: 1041 | F10: 43837 | G10: KRW | I10: https://www.amazon.com/-/en/Trofolastin-Antistretch-Centella-asiatica-Flexible/dp/B0C8ZN274P/ref=zg_bs_g_4347676031_d_sccl_8/522-8505739-1189111
A11: 9 | B11: B0D1GK2ZKB | C11: Neutrogena Norwegian Formula CICA Body Cream, 750 ml, 2 pcs | Intense Repair, With Centella Asiatica and Glycerin, 72 h Hydra | D11: 4.7 | E11: 1173 | F11: 19925 | G11: KRW | I11: https://www.amazon.com/-/en/Neutrogena-Norwegian-Repairing-Moisturizer-Centella/dp/B0D1GK2ZKB/ref=zg_bs_g_4347676031_d_sccl_9/522-8505739-1189111
A12: 10 | B12: B07QL8WW2G | C12: Rexona Invisible Deodorant Spray Antiperspirant for Men Ice 200ml - Pack of 6, Packaging May Vary | D12: 4.7 | E12: 4086 | F12: 22192 | G12: KRW | I12: https://www.amazon.com/-/en/Rexona-Invisible-Deodorant-Spray-Antiperspirant/dp/B07QL8WW2G/ref=zg_bs_g_4347676031_d_sccl_10/522-8505739-1189111
A13: 11 | B13: B0FB3G2H7J | C13: Tulip Black - Bergamot & Cedar Body Wash, Moisturizing Shower Gel with Fresh and Long Lasting Floral Fragrance, 650 ml | D13: 4.5 | E13: 614 | F13: 2251 | G13: KRW | I13: https://www.amazon.com/-/en/Tulip-Black-Bergamot-Moisturizing-Fragrance/dp/B0FB3G2H7J/ref=zg_bs_g_4347676031_d_sccl_11/522-8505739-1189111
A14: 12 | B14: B0DKF8Y6DN | C14: Dove Moisturizing Shower Gel Gentle Cleansing for Soft Skin 720ml | D14: 4.8 | E14: 586 | F14: 5114 | G14: KRW | I14: https://www.amazon.com/-/en/Dove-Moisturizing-Shower-Gentle-Cleansing/dp/B0DKF8Y6DN/ref=zg_bs_g_4347676031_d_sccl_12/522-8505739-1189111
... A32: 30 | B32: B003Q3FPR6 | C32: Trofolastin Antistretch mark cream Centella asiatica Flexible skin 250 ml | D32: 4.6 | E32: 5866 | F32: 28689 | G32: KRW | I32: https://www.amazon.com/-/en/Trofolastin-Antistretch-Centella-asiatica-Flexible/dp/B003Q3FPR6/ref=zg_bs_g_4347676031_d_sccl_30/522-8505739-1189111
A33: 31 | B33: B0FPCC599C
A34: 32 | B34: B0D45LZBML
A35: 33 | B35: B0BYDXSZMG
A36: 34 | B36: B0DCNYL5HK
A37: 35 | B37: B0BQ77QJFM
A38: 36 | B38: B017WK9SSK
A39: 37 | B39: B09BBHBDWW
A40: 38 | B40: B0BYDWFYHV
A41: 39 | B41: B077MPSQ8K
A42: 40 | B42: B07M6GD8LH
A43: 41 | B43: B0CSNH2238
A44: 42 | B44: B00K7ZD802
... A52: 50 | B52: B01HGLUJGA
A53: 51 | B53: B0D1GMN61F | C53: Neutrogena Hydro Boost Ultralight Gel Body Lotion, 750 ml, 2 pcs | With Hyaluronic Acid and Glycerin, Refreshing, Non-Grease, | D53: 4.6 | E53: 541 | F53: 19925 | G53: KRW | I53: https://www.amazon.com/-/en/Neutrogena-Hydro-Boost-Ultralight-Lotion/dp/B0D1GMN61F/ref=zg_bs_g_4347676031_d_sccl_1/522-8505739-1189111
A54: 52 | B54: B07GSFWR73 | C54: NIVEA MEN Black & White Invisible Original Spray en pack de 6 (6 x 200 ml), desodorante antimanchas de cuidado masculino, des | D54: 4.7 | E54: 1973 | F54: 20745 | G54: KRW | I54: https://www.amazon.com/-/en/NIVEA-MEN-Invisible-desodorante-antimanchas/dp/B07GSFWR73/ref=zg_bs_g_4347676031_d_sccl_2/522-8505739-1189111
A55: 53 | B55: B000O7JOT2 | C55: Vichy Deodorant in Roll-On Format, for Women, Anti-Mark, Antiperspirant, Suitable for Sensitive or Newly Depilated Skin, Prot | D55: 4.7 | E55: 2964 | F55: 12849 | G55: KRW | I55: https://www.amazon.com/-/en/Vichy-Regulating-Deodorant-Sensitive-Efficiency/dp/B000O7JOT2/ref=zg_bs_g_4347676031_d_sccl_3/522-8505739-1189111
A56: 54 | B56: B07CG2TD9F | C56: CeraVe, Moisturizing Lotion, Dry and Very Dry Body Skin, 8 fl oz | Hydrates and helps restore the protective barrier of the f | D56: 4.6 | E56: 45628 | F56: 14956 | G56: KRW | I56: https://www.amazon.com/-/en/CeraVe-Moisturizing-Lotion-Very-Body/dp/B07CG2TD9F/ref=zg_bs_g_4347676031_d_sccl_4/522-8505739-1189111
A57: 55 | B57: B0825C7R65 | C57: Annote 120 Disposable Soap Sponges for Babies, Children and Adults – Sensitive Skin, pH Neutral – Pack of 5 Packs of 24 Units | D57: 4.2 | E57: 1334 | F57: 11836 | G57: KRW | I57: https://www.amazon.com/-/en/Annote-Disposable-Sponges-Babies-Children/dp/B0825C7R65/ref=zg_bs_g_4347676031_d_sccl_5/522-8505739-1189111
A58: 56 | B58: B01BLEBM5K | C58: Tired Legs Lotion with Arnica - Instituto Español 500 ML | D58: 4.4 | E58: 3037 | F58: 3924 | G58: KRW | I58: https://www.amazon.com/-/en/Tired-Legs-Lotion-Arnica-Instituto/dp/B01BLEBM5K/ref=zg_bs_g_4347676031_d_sccl_6/522-8505739-1189111
A59: 57 | B59: B0F9YGNBDY | C59: Sanex Zero% Extra Control, Roll-On Deodorant, Men and Women, Pack 6x50ml | Roll-on Antiperspirant 48h, Aluminium-free and Alc | D59: 4.3 | E59: 79 | F59: 12173 | G59: KRW | I59: https://www.amazon.com/-/en/Sanex-Zero-Control-Deodorant-6x50ml/dp/B0F9YGNBDY/ref=zg_bs_g_4347676031_d_sccl_7/522-8505739-1189111
A60: 58 | B60: B07VMFSCTN | C60: Instituto Español Gel De Baño De Coco - 1250 Ml, Frutal | D60: 4.6 | E60: 1319 | F60: 3329 | G60: KRW | I60: https://www.amazon.com/-/en/Instituto-Espa%C3%B1ol-Coconut-Bath-Gel/dp/B07VMFSCTN/ref=zg_bs_g_4347676031_d_sccl_8/522-8505739-1189111
A61: 59 | B61: B01773JH10 | C61: Bepanthol Tattoo Ointment with Panthenol 30g, Unscented | Moisturizes and repairs skin after tattooing and preserves its beau | D61: 4.7 | E61: 6593 | F61: 10614 | G61: KRW | I61: https://www.amazon.com/-/en/BEPANTHOL-Panthenol-Tattoo-Cream-Preservative/dp/B01773JH10/ref=zg_bs_g_4347676031_d_sccl_9/522-8505739-1189111
A62: 60 | B62: B00CY9Z7EO | C62: Vichy, Ball Anti-Marking Deodorant 48H, Roll On Deodorant, 50 ml | Control sweating with 48 hours of anti-perspirant efficacy | D62: 4.5 | E62: 916 | F62: 14135 | G62: KRW | I62: https://www.amazon.com/-/en/Vichy-Ball-Anti-Marking-Deodorant-Roll/dp/B00CY9Z7EO/ref=zg_bs_g_4347676031_d_sccl_10/522-8505739-1189111
A63: 61 | B63: B09RR229FY | C63: Avena Kinesia - Oleo Soap-Free Shower Gel for Extra Dry and Atopic Skin | Its oil base generates little foam but cleans and n | D63: 4.5 | E63: 741 | F63: 3972 | G63: KRW | I63: https://www.amazon.com/-/en/Avena-Kinesia-Soap-Free-Shower-Atopic/dp/B09RR229FY/ref=zg_bs_g_4347676031_d_sccl_11/522-8505739-1189111
A64: 62 | B64: B076QFQTXD | C64: Tulip Black - Candy Fantasy Body Wash, Nourishing and Moisturizing, Shower Gel with Sweet Fragrance, 650 ml | D64: 4.6 | E64: 5212 | F64: 2251 | G64: KRW | I64: https://www.amazon.com/-/en/Tulip-Black-Nourishing-Moisturizing-Fragrance/dp/B076QFQTXD/ref=zg_bs_g_4347676031_d_sccl_12/522-8505739-1189111
... A82: 80 | B82: B09L8ZZV95 | C82: Sante Naturkosmetik Naturkosmetik Organic Pineapple & Lime Shower Gel Family Size 500ml with Dispenser, Fruity Fresh Scent, V | D82: 4.5 | E82: 837 | F82: 8459 | G82: KRW | I82: https://www.amazon.com/-/en/Sante-Naturkosmetik-Pineapple-Dispenser-Microplastic-Free/dp/B09L8ZZV95/ref=zg_bs_g_4347676031_d_sccl_30/522-8505739-1189111
A83: 81 | B83: B0CS62LY6P
A84: 82 | B84: B079MGZT6Q
A85: 83 | B85: B087XGVFL1
A86: 84 | B86: B08W8H13RH
A87: 85 | B87: B0D1GL8D5D
A88: 86 | B88: B0F3PGFHXT
A89: 87 | B89: B0G8WXQGLZ
A90: 88 | B90: B01GRN9YZU
A91: 89 | B91: B000NRVG26
A92: 90 | B92: B0D45KJ86P
A93: 91 | B93: B0BTZ7YHHZ
A94: 92 | B94: B089KKCQRQ
... A102: 100 | B102: B0FC3Y1Z61

Sheet Hair Care1
A1: Amazon Best Sellers — Hair Care | I1: 🔗 Best Sellers 페이지 열기
A2: rank | B2: asin | C2: title | D2: rating | E2: ratings_count | F2: price | G2: currency | H2: offers_text | I2: url
A3: 1 | B3: B00M9B66BU | C3: REVLON PROFESSIONAL UniqOne All in One Thermal Hair Protector, Deep Hydration Hair, Spray Treatment Without Rinse, Detangler | D3: 4.5 | E3: 102588 | F3: 37710 | G3: KRW | I3: https://www.amazon.com/-/en/REVLON-PROFESSIONAL-Protector-Hydration-Treatment/dp/B00M9B66BU/ref=zg_bs_g_4347698031_d_sccl_1/522-8505739-1189111
A4: 2 | B4: B083JKPCFB | C4: Kérastase, Genesis, Anti-Hair Loss Serum, Fortifying, Activator and Daily Strengthener, For Weak or Fragile Hair, Anti-Chute | D4: 4.5 | E4: 8389 | F4: 88447 | G4: KRW | I4: https://www.amazon.com/-/en/K%C3%A9rastase-Genesis-Professional-Treatment-Serum/dp/B083JKPCFB/ref=zg_bs_g_4347698031_d_sccl_2/522-8505739-1189111
A5: 3 | B5: B0BZZJWGPQ | C5: Kérastase Nutritive Night Repair Serum for Dry Hair, Revitalizes, Nourishes and Repairs, With Anti-Dryness Niacinamide, 8H Ma | D5: 4.5 | E5: 8374 | F5: 87433 | G5: KRW | I5: https://www.amazon.com/-/en/K%C3%A9rastase-Nutritive-Magic-Night-Professional/dp/B0BZZJWGPQ/ref=zg_bs_g_4347698031_d_sccl_3/522-8505739-1189111
A6: 4 | B6: B07PZ2H67L | C6: Beter - Natural Fiber Anti-Pull Skeleton Hair Brush Made of Wheat Fibers, Detangling Hair Brush, Anti-Tangle and Anti-Breakag | D6: 4.6 | E6: 8510 | F6: 6513 | G6: KRW | I6: https://www.amazon.com/-/en/Beter-Anti-Pull-Detangling-Anti-Tangle-Anti-Breakage/dp/B07PZ2H67L/ref=zg_bs_g_4347698031_d_sccl_4/522-8505739-1189111
A7: 5 | B7: B0F2TQW9QD | C7: BIONOBLE Rosemary Oil for Hair Bio, Pure - Growth - 50 ml | 100% Natural Origin - Rosemary Oil Hair Growth, Castor, Argan, Jo | D7: 4.4 | E7: 63519 | F7: 15792 | G7: KRW | I7: https://www.amazon.com/-/en/BIONOBLE-Rosemary-Oil-Hair-Pure/dp/B0F2TQW9QD/ref=zg_bs_g_4347698031_d_sccl_5/522-8505739-1189111
A8: 6 | B8: B087R9HVRR | C8: Alpecin Caffeine Shampoo C1 2x 375ml | Anti-Hair Loss Shampoo for Men and Caffeine | Treatment for Hair Loss | Alpecin Shampo | D8: 4.4 | E8: 8463 | F8: 35363 | G8: KRW | I8: https://www.amazon.com/-/en/Alpecin-Caffeine-Shampoo-Anti-Hair-Treatment/dp/B087R9HVRR/ref=zg_bs_g_4347698031_d_sccl_6/522-8505739-1189111
A9: 7 | B9: B00WN2BY7G | C9: Vichy, Dercos Technique, Anti-Dandruff Shampoo, For Oily Hair, 390 ml | Double effectiveness against adherent dandruff and it | D9: 4.7 | E9: 11907 | F9: 25666 | G9: KRW | I9: https://www.amazon.com/-/en/Vichy-Dercos-Technique-Anti-Dandruff-Shampoo/dp/B00WN2BY7G/ref=zg_bs_g_4347698031_d_sccl_7/522-8505739-1189111
A10: 8 | B10: B00X9WCH9S | C10: L'Oréal Paris Elvive Extraordinary Oil Multi-Purpose Nourishing Serum, 100 ml | Sérum Enriquecido Con Aceites de Camellia y M | D10: 4.7 | E10: 4356 | F10: 29991 | G10: KRW | I10: https://www.amazon.com/-/en/LOr%C3%A9al-Paris-Extraordinary-Multi-Purpose-Nourishing/dp/B00X9WCH9S/ref=zg_bs_g_4347698031_d_sccl_8/522-8505739-1189111
A11: 9 | B11: B082DDM32Y | C11: Cecotec Bamba PrecisionCare Wet&Dry Hair Clipper. Stainless Steel Blades with Titanium Coating, Lithium Battery, Autonomy up | D11: 4.5 | E11: 3535 | F11: 26454 | G11: KRW | I11: https://www.amazon.com/-/en/Cecotec-PrecisionCare-Clipper-Stainless-Titanium/dp/B082DDM32Y/ref=zg_bs_g_4347698031_d_sccl_9/522-8505739-1189111
A12: 10 | B12: B0007506U2 | C12: Catwalk by TIGI Curls Rock Amplifier, Styling Cream, 150 ml | Anti-Frizz Moisturizing Definer for Natural Curly & Wavy Hair, | D12: 4.4 | E12: 35517 | F12: 10067 | G12: KRW | I12: https://www.amazon.com/-/en/Catwalk-TIGI-Curls-Amplifier-Styling/dp/B0007506U2/ref=zg_bs_g_4347698031_d_sccl_10/522-8505739-1189111
A13: 11 | B13: B083JJHLT4 | C13: Kérastase Genesis Hydra-Fortifiant Professional Anti-Hair Loss Shampoo 250 | Professional moisturizing shampoo that strengthe | D13: 4.6 | E13: 10857 | F13: 49241 | G13: KRW | I13: https://www.amazon.com/-/en/K%C3%A9rastase-Genesis-Hydra-Fortifiant-Professional-Anti-Hair/dp/B083JJHLT4/ref=zg_bs_g_4347698031_d_sccl_11/522-8505739-1189111
A14: 12 | B14: B08P67N41H | C14: Redken ABC Leave-In Conditioner for Long and Dry Hair 150ml | Hydration treatment hair, ideal for dry, burned and balayage hi | D14: 4.4 | E14: 14882 | F14: 32114 | G14: KRW | I14: https://www.amazon.com/-/en/Redken-Leave-Conditioner-Long-150ml/dp/B08P67N41H/ref=zg_bs_g_4347698031_d_sccl_12/522-8505739-1189111
... A32: 30 | B32: B0CY3GR4FS | C32: KERASTASE | D32: 4.6 | E32: 2491 | F32: 59709 | G32: KRW | I32: https://www.amazon.com/-/en/K%C3%A9rastase-Elixir-Ultime-Professional-Refillable/dp/B0CY3GR4FS/ref=zg_bs_g_4347698031_d_sccl_30/522-8505739-1189111
A33: 31 | B33: B008OUY6QM
A34: 32 | B34: B07ZHKTQL3
A35: 33 | B35: B01N39SZ87
A36: 34 | B36: B01L2FIUO4
A37: 35 | B37: B0CB6T1ZP6
A38: 36 | B38: B07SBS14T3
A39: 37 | B39: B0CB6V8T1D
A40: 38 | B40: B00CP3EA5G
A41: 39 | B41: B0GL3BZ3LR
A42: 40 | B42: B0CCYPDLCQ
A43: 41 | B43: B00YO38G4Q
A44: 42 | B44: B0CDPT26TQ
... A52: 50 | B52: B00J5FY8BI
A53: 51 | B53: B0007CXWC4 | C53: American Crew - Fiber, Cera para el Pelo Hombre, Fijación Fuerte y Flexible, Moldea y Aumenta el Brillo, para Pelo Corto, Est | D53: 4.3 | E53: 33304 | F53: 22433 | G53: KRW | I53: https://www.amazon.com/-/en/American-Crew-Strong-Flexible-Shapes/dp/B0007CXWC4/ref=zg_bs_g_4347698031_d_sccl_1/522-8505739-1189111
A54: 52 | B54: B0DWFSJ9Y4 | C54: L'Oréal Paris Elvive Growth Booster Anti-Hair Loss Treatment Serum, 100 ml | Formulated with Aminexil-R™, Stimulates Hair Gro | D54: 3.7 | E54: 59 | F54: 17609 | G54: KRW | I54: https://www.amazon.com/-/en/LOr%C3%A9al-Paris-Growth-Booster-Anti-Hair/dp/B0DWFSJ9Y4/ref=zg_bs_g_4347698031_d_sccl_2/522-8505739-1189111
A55: 53 | B55: B084TLZWP7 | C55: OGX Coconut Miracle Oil Extra Strength Repair Hair Oil 100ml | Anti-Frizz, Softens and Brings Shine, With Coconut Oil and Tia | D55: 4.4 | E55: 4769 | F55: 7960 | G55: KRW | I55: https://www.amazon.com/-/en/OGX-Coconut-Miracle-Strength-Repair/dp/B084TLZWP7/ref=zg_bs_g_4347698031_d_sccl_3/522-8505739-1189111
A56: 54 | B56: B0947D38SM | C56: Instituto Español Biotin + Collagen Shampoo 750 ml | D56: 4.4 | E56: 1214 | F56: 3650 | G56: KRW | I56: https://www.amazon.com/-/en/Instituto-Espa%C3%B1ol-Biotin-Collagen-Shampoo/dp/B0947D38SM/ref=zg_bs_g_4347698031_d_sccl_4/522-8505739-1189111
A57: 55 | B57: B00CZCD63O | C57: REVLON PROFESSIONAL - Equave, Hair Conditioner, No Rinse, Instantly Detangles, Reduces Frizz and Increases Flexibility, with | D57: 4.6 | E57: 15562 | F57: 27338 | G57: KRW | I57: https://www.amazon.com/-/en/REVLON-PROFESSIONAL-Conditioner-Instantly-Flexibility/dp/B00CZCD63O/ref=zg_bs_g_4347698031_d_sccl_5/522-8505739-1189111
A58: 56 | B58: B0F9B2B3YH | C58: Bellissima Imetec Diffon Ceramic & Argan: Diffuser for Curly Hair with Argan Oil for Defined, Shiny and Hydrated Curls – Anti | D58: 4.4 | E58: 577 | F58: 66431 | G58: KRW | I58: https://www.amazon.com/-/en/Bellissima-Imetec-Diffon-Ceramic-Argan/dp/B0F9B2B3YH/ref=zg_bs_g_4347698031_d_sccl_6/522-8505739-1189111
A59: 57 | B59: B0F1FTS182 | C59: iLamvie 2 Pieces Silk Hat, Sleeping Silk Cap for Curly Hair with Elastic Wide Band for Women and Girls, Satin for Sleeping Cu | D59: 4.3 | E59: 3839 | F59: 8025 | G59: KRW | I59: https://www.amazon.com/-/en/iLamvie-Pieces-Sleeping-Curly-Elastic/dp/B0F1FTS182/ref=zg_bs_g_4347698031_d_sccl_7/522-8505739-1189111
A60: 58 | B60: B006U111TC | C60: Camomile Intea – Natural Blonde Hair Lightening Lotion – With Natural | Lightens hair up to three shades with natural chamomi | D60: 4.4 | E60: 6809 | F60: 30538 | G60: KRW | I60: https://www.amazon.com/-/en/Camomile-Intea-Lightening-Chamomile-Lightens/dp/B006U111TC/ref=zg_bs_g_4347698031_d_sccl_8/522-8505739-1189111
A61: 59 | B61: B07R4CNDRM | C61: American Crew Matte Clay, Matte Wax Men's Hair Medium-High Hold Wax with Matte Finish, Hair Shaper with Clay and Fixer Hair P | D61: 4.4 | E61: 6212 | F61: 14763 | G61: KRW | I61: https://www.amazon.com/-/en/American-Crew-Medium-High-Finish-Shaper/dp/B07R4CNDRM/ref=zg_bs_g_4347698031_d_sccl_9/522-8505739-1189111
A62: 60 | B62: B0BRKBSM7H | C62: SWEET VIEW Silk Satin Bonnet, Hair Wrap for Sleeping, Soft and Comfortable Beanie, Black, Peacock Blue | D62: 4.2 | E62: 14266 | F62: 11016 | G62: KRW | I62: https://www.amazon.com/-/en/SWEET-VIEW-Sleeping-Comfortable-Peacock/dp/B0BRKBSM7H/ref=zg_bs_g_4347698031_d_sccl_10/522-8505739-1189111
A63: 61 | B63: B0D7SSTSZR | C63: Professional Curling Brush – Shape and Define Curlers | Reduces pull, frizz and separation. Soft edges, unisex. | D63: 4.5 | E63: 2333 | F63: 13733 | G63: KRW | I63: https://www.amazon.com/-/en/Curling-Styling-Corners-Shaping-Separating/dp/B0D7SSTSZR/ref=zg_bs_g_4347698031_d_sccl_11/522-8505739-1189111
A64: 62 | B64: B08HZZ8TXS | C64: REVLON PROFESSIONAL ProYou The Twister Scrunch, Curl Activator Gel, For Curly or Wavy Hair, Defined and Hydrated Curls, Curly | D64: 4.4 | E64: 2723 | F64: 26791 | G64: KRW | I64: https://www.amazon.com/-/en/REVLON-PROFESSIONAL-Activator-Hydrated-Friendly/dp/B08HZZ8TXS/ref=zg_bs_g_4347698031_d_sccl_12/522-8505739-1189111
... A82: 80 | B82: B0DGGB6NY1 | C82: Pantene Pro-V Repara Y Protege Champú 2x1000ML, Dispensador, Pelo Seco Y Dañado. Limpia Y Protege Los Enlaces Capilares. Sin | D82: 4.8 | E82: 1668 | F82: 27322 | G82: KRW | I82: https://www.amazon.com/-/en/Pantene-Pro-V-Dispensador-Capilares-Siliconas/dp/B0DGGB6NY1/ref=zg_bs_g_4347698031_d_sccl_30/522-8505739-1189111
A83: 81 | B83: B0FJ2L86K3
A84: 82 | B84: B08JHTD3JX
A85: 83 | B85: B0D6YPGQ8D
A86: 84 | B86: B08CB4QDHB
A87: 85 | B87: B01CVTRC8U
A88: 86 | B88: B0BFRFGPPW
A89: 87 | B89: B0FRFXMPT6
A90: 88 | B90: B0CRHK7TVB
A91: 89 | B91: B0D3XBBDZD
A92: 90 | B92: B0GHSXYY3Z
A93: 91 | B93: B005EFZUO2
A94: 92 | B94: B09RKNFWWM
... A102: 100 | B102: B0DRXK7WXM

Sheet Fragrances1
A1: Amazon Best Sellers — Fragrances | I1: 🔗 Best Sellers 페이지 열기
A2: rank | B2: asin | C2: title | D2: rating | E2: ratings_count | F2: price | G2: currency | H2: offers_text | I2: url
A3: 1 | B3: B0DB88MVYC | C3: HIQILI Tea Tree Oil, for Skin, Hair, Nails, Diffuser | Can be added shampoo, shower gel and spray – 118mL / 4 fl.oz | D3: 4.5 | E3: 234 | F3: 16065 | G3: KRW | I3: https://www.amazon.com/-/en/HIQILI-Tree-Skin-Nails-Diffuser/dp/B0DB88MVYC/ref=zg_bs_g_6397798031_d_sccl_1/522-8505739-1189111
A4: 2 | B4: B0CB8V2LP4 | C4: DKNY Be Delicious 100% Pure New York, Fruity Floral Mist, 250ml | D4: 4.3 | E4: 2065 | F4: 9600 | G4: KRW | I4: https://www.amazon.com/-/en/DKNY-Delicious-Fruity-Floral-250ml/dp/B0CB8V2LP4/ref=zg_bs_g_6397798031_d_sccl_2/522-8505739-1189111
A5: 3 | B5: B0009OAI40 | C5: Elizabeth Arden Green Tea Eau de Toilette for Women 100 ml | Refreshing women's cologne with green tea and bergamot brings a | D5: 4.5 | E5: 13642 | F5: 19201 | G5: KRW | I5: https://www.amazon.com/-/en/Elizabeth-Arden-Green-Toilette-Women/dp/B0009OAI40/ref=zg_bs_g_6397798031_d_sccl_3/522-8505739-1189111
A6: 4 | B6: B0H4GR8S59 | C6: Nenuco Classic Eau De Toilette Original Fragrance 650 ml (Pack of 3) | D6: 4.6 | E6: 860 | F6: 8684 | G6: KRW | I6: https://www.amazon.com/-/en/Nenuco-Classic-Toilette-Original-Fragrance/dp/B0H4GR8S59/ref=zg_bs_g_6397798031_d_sccl_4/522-8505739-1189111
A7: 5 | B7: B07VQTL4HL | C7: Lavender True BIO (Lavandula officinalis) - 10 mL - Chemotyping and AB Certified Essential Oil - Relaxation & Rest - Aroma La | D7: 4.4 | E7: 1799 | F7: 8266 | G7: KRW | I7: https://www.amazon.com/-/en/Lavender-True-BIO-Lavandula-officinalis/dp/B07VQTL4HL/ref=zg_bs_g_6397798031_d_sccl_5/522-8505739-1189111
A8: 6 | B8: B000P275F6 | C8: Nautical Fragrance Set for Men - 50ml | D8: 4.4 | E8: 3477 | F8: 17689 | G8: KRW | I8: https://www.amazon.com/-/en/Nautical-Fragrance-Set-Men-50ml/dp/B000P275F6/ref=zg_bs_g_6397798031_d_sccl_6/522-8505739-1189111
A9: 7 | B9: B00HAOP8UQ | C9: CALVIN KLEIN CK ONE Eau de Toilette | D9: 4.6 | E9: 34130 | F9: 35218 | G9: KRW | I9: https://www.amazon.com/-/en/Calvin-Klein-Eau-Toilette-Men/dp/B00HAOP8UQ/ref=zg_bs_g_6397798031_d_sccl_7/522-8505739-1189111
A10: 8 | B10: B0C7ZR2XQ4 | C10: AESHORY Essential Oils for Humidifier TOP 6 x 10ML, Natural Aromatic Oil, Set of Essential Oils Aromatherapy for Diffuser, SP | D10: 4.1 | E10: 6306 | F10: 15261 | G10: KRW | I10: https://www.amazon.com/-/en/Essential-Oils-Humidifier-Aromatic-Aromatherapy/dp/B0C7ZR2XQ4/ref=zg_bs_g_6397798031_d_sccl_8/522-8505739-1189111
A11: 9 | B11: B000P20R8I | C11: Britney Spears Fantasy 100 ml, Eau de Parfum for Women | Juicy Red Lychee Notes, Cupcake Chord and Creamy Musk, Pink Glass Ja | D11: 4.6 | E11: 20373 | F11: 27258 | G11: KRW | I11: https://www.amazon.com/-/en/Britney-Spears-Fantasy-Parfum-Women/dp/B000P20R8I/ref=zg_bs_g_6397798031_d_sccl_9/522-8505739-1189111
A12: 10 | B12: B0FDQQY72G | C12: MUNUSNA Vanilla Essential Oil 100ML, Vanilla Oil for DIY Soap | Pure Natural Essential Oils for Diffuser Humidifier, Candles | D12: 4.2 | E12: 526 | F12: 16001 | G12: KRW | I12: https://www.amazon.com/-/en/MUNUSNA-Vanilla-Essential-100ML-Soap/dp/B0FDQQY72G/ref=zg_bs_g_6397798031_d_sccl_10/522-8505739-1189111
A13: 11 | B13: B0FK4VDXFL | C13: MAYJAM Eucalyptus Essential Oil for Diffuser 100ML | Eucalyptus Oil Humidifier, DIY, Home, Accessories | D13: 4.3 | E13: 7807 | F13: 16065 | G13: KRW | I13: https://www.amazon.com/-/en/MAYJAM-Eucalyptus-Essential-Diffuser-100ML/dp/B0FK4VDXFL/ref=zg_bs_g_6397798031_d_sccl_11/522-8505739-1189111
A14: 12 | B14: B0035FTTYA | C14: PRANAROM - Organic Lavender - Chemotyping Essential Oil - Sleep and Stress | Articulations et muscles Sommeil et détente Cosm | D14: 4.6 | E14: 2193 | F14: 11096 | G14: KRW | I14: https://www.amazon.com/-/en/PRANAROM-Organic-Lavender-Chemotyping-Essential/dp/B0035FTTYA/ref=zg_bs_g_6397798031_d_sccl_12/522-8505739-1189111
A15: 13 | B15: B00V88L9LC | C15: PARFUMS SAPHIR Perfect Man Eau de Parfum, Men, 200 ml | D15: 4.4 | E15: 3718 | F15: 34719 | G15: KRW | I15: https://www.amazon.com/-/en/PARFUMS-SAPHIR-Perfect-Man-Parfum/dp/B00V88L9LC/ref=zg_bs_g_6397798031_d_sccl_13/522-8505739-1189111
A16: 14 | B16: B0DSXQMHGZ | C16: DKNY 24/7 EU | D16: 4.5 | E16: 626 | I16: https://www.amazon.com/-/en/DKNY-Womens-Parfum-Woody-Floral/dp/B0DSXQMHGZ/ref=zg_bs_g_6397798031_d_sccl_14/522-8505739-1189111
A17: 15 | B17: B00XAFFABQ | C17: NIVEA MEN Sensitive After Shave Balm (1 x 100 ml) for Sensitive Skin Care - Anti Irritation Balm with 0% Alcohol to Soothe Sk | D17: 4.7 | E17: 1809 | F17: 7639 | G17: KRW | I17: https://www.amazon.com/-/en/NIVEA-MEN-Sensitive-After-Shave/dp/B00XAFFABQ/ref=zg_bs_g_6397798031_d_sccl_15/522-8505739-1189111
A18: 16 | B18: B000VOLKEA | C18: Calvin Klein CKIN2U para él Eau de Toilette | D18: 4.5 | E18: 17829 | F18: 28030 | G18: KRW | I18: https://www.amazon.com/-/en/CALVIN-KLEIN-CKIN2U-Toilette-100ml/dp/B000VOLKEA/ref=zg_bs_g_6397798031_d_sccl_16/522-8505739-1189111
A19: 17 | B19: B07JQJS5Q4 | C19: PRANAROM Zen Essential Oil Organic Diffusion 30ml – Citrus and Cedar Relax | Ecological synergy for citrus and cedar diffuser | D19: 4.5 | E19: 357 | F19: 32082 | G19: KRW | I19: https://www.amazon.com/-/en/PRANAROM-Essential-Organic-Diffusion-30ml/dp/B07JQJS5Q4/ref=zg_bs_g_6397798031_d_sccl_17/522-8505739-1189111
A20: 18 | B20: B0GVJZS81N | C20: Davidoff Cool Water Eau de Toilette for Men; Fresh and masculine fragrance with notes of coriander, mint and lavender; Medium | D20: 4.6 | E20: 42 | I20: https://www.amazon.com/-/en/Davidoff-Cool-Water-Eau-Toilette/dp/B0GVJZS81N/ref=zg_bs_g_6397798031_d_sccl_18/522-8505739-1189111
A21: 19 | B21: B00M3IFUMK | C21: Armaf Club De Nuit Men's EDT Intense Perfume 105 ml | D21: 4.3 | E21: 74710 | F21: 61913 | G21: KRW | I21: https://www.amazon.com/-/en/Armaf-Club-Nuit-Intense-Perfume/dp/B00M3IFUMK/ref=zg_bs_g_6397798031_d_sccl_19/522-8505739-1189111
A22: 20 | B22: B0CN2K68QF | C22: Pret A Porter Eau De Toilette Spray for Women - 50 ml. | D22: 4.5 | E22: 2296 | F22: 11595 | G22: KRW | I22: https://www.amazon.com/-/en/Pret-Porter-Toilette-Spray-Women/dp/B0CN2K68QF/ref=zg_bs_g_6397798031_d_sccl_20/522-8505739-1189111
A23: 21 | B23: B001NYSS6U | C23: PRANAROM Tea Tree Essential Oil 10ml – Natural Defenses HECT Puro | 100% pure and chemotyped HECT. Melaleuca alternifolia for | D23: 4.6 | E23: 7240 | F23: 14393 | G23: KRW | I23: https://www.amazon.com/-/en/PRANAROM-Tea-Tree-Essential-10ml/dp/B001NYSS6U/ref=zg_bs_g_6397798031_d_sccl_21/522-8505739-1189111
A24: 22 | B24: B000UUO5VA | C24: CALVIN KLEIN CK IN2U Eau de Toilette para mujer | Fragancia femenina cítrica y floral con notas de bergamota y cedro rojo| La | D24: 4.6 | E24: 32104 | F24: 27145 | G24: KRW | I24: https://www.amazon.com/-/en/CALVIN-KLEIN-CKIN2U-Toilette-100ml/dp/B000UUO5VA/ref=zg_bs_g_6397798031_d_sccl_22/522-8505739-1189111
A25: 23 | B25: B006A5HTI0 | C25: Nenuco Eau de Toilette Recommended for Babies, Original Fragrance - Spray Format 240 ml | D25: 4.6 | E25: 2235 | F25: 5628 | G25: KRW | I25: https://www.amazon.com/-/en/Nenuco-Toilette-Recommended-Original-Fragrance/dp/B006A5HTI0/ref=zg_bs_g_6397798031_d_sccl_23/522-8505739-1189111
A26: 24 | B26: B003WF3JPS | C26: Suavinex, Baby Cologne Classic, Eau de Toilette for Babies, 100 ml | Low Alcohol, Does Not Stain Clothes, Dermatologically Te | D26: 4.6 | E26: 2853 | F26: 37308 | G26: KRW | I26: https://www.amazon.com/-/en/Suavinex-Cologne-Classic-Toilette-Babies/dp/B003WF3JPS/ref=zg_bs_g_6397798031_d_sccl_24/522-8505739-1189111
A27: 25 | B27: B0010MG8NU | C27: Elizabeth Arden - 5th Avenue, Eau de Parfum, Perfume Femenino en Spray, Elegante y Lujoso con Notas Florales de Magnolia Rosa | D27: 4.5 | E27: 15870 | F27: 28801 | G27: KRW | I27: https://www.amazon.com/-/en/Elizabeth-Arden-Avenue-Parfum-Women/dp/B0010MG8NU/ref=zg_bs_g_6397798031_d_sccl_25/522-8505739-1189111
A28: 26 | B28: B07RG7FMWF | C28: IAP Pharma Parfums nº 34 - Floral Eau de Parfum - Women - 150 ml | D28: 4.3 | E28: 201 | F28: 12929 | G28: KRW | I28: https://www.amazon.com/-/en/IAP-Pharma-Parfums-n%C2%BA-34/dp/B07RG7FMWF/ref=zg_bs_g_6397798031_d_sccl_26/522-8505739-1189111
A29: 27 | B29: B0C3B6F9Y3 | C29: Migcaput Lavender Essential Oil 100ML, 100% Pure Natural Therapeutic Grade Aromatherapy Essential Oils for Skin Care, Anti Ac | D29: 4.3 | E29: 5492 | F29: 22498 | G29: KRW | I29: https://www.amazon.com/-/en/Migcaput-Essential-Oil-Therapeutic-Aromatherapy/dp/B0C3B6F9Y3/ref=zg_bs_g_6397798031_d_sccl_27/522-8505739-1189111
A30: 28 | B30: B0C3G9J5Q8 | C30: Armaf ARMAF Odyssey Mandarin Sky Ep 100 for professional use to improve performance in every use with measurement or specific | D30: 4.6 | E30: 11735 | F30: 81097 | G30: KRW | I30: https://www.amazon.com/-/en/ARMAF-professional-performance-measurement-specification/dp/B0C3G9J5Q8/ref=zg_bs_g_6397798031_d_sccl_28/522-8505739-1189111
A31: 29 | B31: B000C1Z6NS | C31: Halloween, Eau de Toilette para Mujer, Aroma Floral Semioriental, con Vaporizador | D31: 4.7 | E31: 9416 | F31: 37148 | G31: KRW | I31: https://www.amazon.com/-/en/Halloween-Womens-Toilette-Semi-Oriental-Floral/dp/B000C1Z6NS/ref=zg_bs_g_6397798031_d_sccl_29/522-8505739-1189111
A32: 30 | B32: B0746B4718 | C32: Toureal Aluminium 10 ml Refillable Perfume Atomizer, Travel Perfume Dispenser, Small Spray Spray for Cologne (Matte Black) | D32: 4.5 | E32: 5399 | F32: 12849 | G32: KRW | I32: https://www.amazon.com/-/en/Toureal-Aluminium-Refillable-Atomizer-Dispenser/dp/B0746B4718/ref=zg_bs_g_6397798031_d_sccl_30/522-8505739-1189111
A33: 31 | B33: B071CMCSB7
A34: 32 | B34: B0BT84NXB6
A35: 33 | B35: B01E32N67O
A36: 34 | B36: B0FJGQHDTH
A37: 35 | B37: B000C2104G
A38: 36 | B38: B08SJNWL1P
A39: 37 | B39: B01F2LAUGU
A40: 38 | B40: B0BT2LSQCJ
A41: 39 | B41: B0FZMB1DYS
A42: 40 | B42: B094JRQCJF
A43: 41 | B43: B0DQR69T8C
A44: 42 | B44: B0GTYN55XL
... A52: 50 | B52: B006VGMS8E
A53: 51 | B53: B00GRFRQZY | C53: Alvarez Gomez, Fresh Bath Water, Orange Blossom, Citrus, 750 Milliliters (Packaging May Vary) | D53: 4.5 | E53: 862 | F53: 23028 | G53: KRW | I53: https://www.amazon.com/-/en/Alvarez-Gomez-Blossom-Milliliters-Packaging/dp/B00GRFRQZY/ref=zg_bs_g_6397798031_d_sccl_1/522-8505739-1189111
A54: 52 | B54: B0CD7N84JW | C54: Nenuco Eau de Toilette, Original Fragrance, with Less Alcohol, Saving Format 1100 ml | D54: 4.7 | E54: 578 | F54: 9343 | G54: KRW | I54: https://www.amazon.com/-/en/Nenuco-Toilette-Original-Fragrance-Alcohol/dp/B0CD7N84JW/ref=zg_bs_g_6397798031_d_sccl_2/522-8505739-1189111
A55: 53 | B55: B000LZLLAC | C55: CALVIN KLEIN Eternity Eau de Toilette para hombres | Fragancia masculina con notas de mandarina, lavanda y madera de cedro | | D55: 4.5 | E55: 8577 | F55: 72285 | G55: KRW | I55: https://www.amazon.com/-/en/Calvin-Klein-Eternity-Men-Spray/dp/B000LZLLAC/ref=zg_bs_g_6397798031_d_sccl_3/522-8505739-1189111
A56: 54 | B56: B07CKDDL5K | C56: PRANAROM Essential Oil Eucalyptus Globulus BIO 10 ml – Respiratory Pathways | 100% Pure and Organic, AEQT Chemotyped Rich in | D56: 4.6 | E56: 1005 | F56: 16885 | G56: KRW | I56: https://www.amazon.com/-/en/PRANAROM-Essential-Oil-Eucalyptus-Globulus/dp/B07CKDDL5K/ref=zg_bs_g_6397798031_d_sccl_4/522-8505739-1189111
A57: 55 | B57: B0009OAHBY | C57: DAVIDOFF Cool Water Eau de Toilette | D57: 4.5 | E57: 53181 | F57: 26518 | G57: KRW | I57: https://www.amazon.com/-/en/Davidoff-Toilette-Fragrance-Coriander-Intensity/dp/B0009OAHBY/ref=zg_bs_g_6397798031_d_sccl_5/522-8505739-1189111
A58: 56 | B58: B00ICMT7A2 | C58: Babaria - After Shave Man With Aloe Vera | Facial Moisturizing Cream For After Shave | Refreshing And Soothing Man Face Cream | D58: 4.4 | E58: 810 | F58: 2637 | G58: KRW | I58: https://www.amazon.com/-/en/Babaria-Facial-Moisturizing-Refreshing-Soothing/dp/B00ICMT7A2/ref=zg_bs_g_6397798031_d_sccl_6/522-8505739-1189111
A59: 57 | B59: B0BZWP7GK3 | C59: 3 PCS 5ML Refillable Perfume Atomizer, Portable Mini Spray Bottle, Refillable Cologne Sprayer, Mini Perfume No Leak, Bottle, | D59: 3.8 | E59: 864 | F59: 8829 | G59: KRW | I59: https://www.amazon.com/-/en/Refillable-Perfume-Atomizer-Portable-Cologne/dp/B0BZWP7GK3/ref=zg_bs_g_6397798031_d_sccl_7/522-8505739-1189111
A60: 58 | B60: B01M1KNZA0 | C60: Atom Extract Bottle Saphir Elle 200 Ml | D60: 4.5 | E60: 366 | F60: 40187 | G60: KRW | I60: https://www.amazon.com/-/en/Atom-Extract-Bottle-Saphir-Elle/dp/B01M1KNZA0/ref=zg_bs_g_6397798031_d_sccl_8/522-8505739-1189111
A61: 59 | B61: B096LTQGTT | C61: NIVEA Creme Eau de Toilette Cologne with the Iconic Scent of Cream 1 fl oz | Unisex, Fresh Smell, Citrus and Floral Notes of | D61: 4.2 | E61: 237 | F61: 30538 | G61: KRW | I61: https://www.amazon.com/-/en/NIVEA-Creme-Toilette-Cologne-Iconic/dp/B096LTQGTT/ref=zg_bs_g_6397798031_d_sccl_9/522-8505739-1189111
A62: 60 | B62: B005LU5G44 | C62: ESCADA SPECIALLY Eau de Parfum | D62: 4.5 | E62: 1762 | F62: 55609 | G62: KRW | I62: https://www.amazon.com/-/en/ESCADA-ESPECIALLY-Womens-Feminine-Fragrance/dp/B005LU5G44/ref=zg_bs_g_6397798031_d_sccl_10/522-8505739-1189111
A63: 61 | B63: B0D8L92LQW | C63: FRENCH AVENUE Brun Eau De Parfum Liquid 100ml | D63: 4.5 | E63: 4452 | F63: 56268 | G63: KRW | I63: https://www.amazon.com/-/en/FRENCH-AVENUE-Parfum-Liquid-100ml/dp/B0D8L92LQW/ref=zg_bs_g_6397798031_d_sccl_11/522-8505739-1189111
A64: 62 | B64: B08KGBXFC1 | C64: PRANAROM - Aromaforce - Soothing Throat Lozenges With Organic Essential Oils - Soothes & Softens - 21 Tablets | D64: 4.5 | E64: 368 | F64: 8475 | G64: KRW | I64: https://www.amazon.com/-/en/PRANAROM-Aromaforce-Soothing-Lozenges-Essential/dp/B08KGBXFC1/ref=zg_bs_g_6397798031_d_sccl_12/522-8505739-1189111
... A80: 78 | B80: B07RTQ4VM7 | C80: Afnan 9 Pm Eau De Parfum 100 ml | D80: 4.4 | E80: 27808 | F80: 42615 | G80: KRW | I80: https://www.amazon.com/-/en/Afnan-Pm-Eau-Parfum-100/dp/B07RTQ4VM7/ref=zg_bs_g_6397798031_d_sccl_28/522-8505739-1189111
A81: 79 | B81: B01N8U3CVZ | C81: TEA TREE - 10 mL - Organic Essential Oil - 100% Pure, Natural, Chemotyping and AB Certified | D81: 4.9 | E81: 51 | I81: https://www.amazon.com/-/en/TEA-TREE-Essential-Chemotyping-Certified/dp/B01N8U3CVZ/ref=zg_bs_g_6397798031_d_sccl_29/522-8505739-1189111
A82: 80 | B82: B07XF918ZR | C82: LATTAFA Lattafa Perfumes Qaed al Fursan Eau for professional use to improve performance in each use with measurement or speci | D82: 4.3 | E82: 5497 | F82: 53036 | G82: KRW | I82: https://www.amazon.com/-/en/Lattafa-professional-performance-measurement-specification/dp/B07XF918ZR/ref=zg_bs_g_6397798031_d_sccl_30/522-8505739-1189111
A83: 81 | B83: B005KIUP9I
A84: 82 | B84: B0D3J4BT2L
A85: 83 | B85: B0F532FLK3
A86: 84 | B86: B0G449WC83
A87: 85 | B87: B0G1G1NLX6
A88: 86 | B88: B01CGNBM7S
A89: 87 | B89: B0B4P22MXW
A90: 88 | B90: B00XAIT9NI
A91: 89 | B91: B0788P99VG
A92: 90 | B92: B0D1CRXGWB
A93: 91 | B93: B0C6F47MXF
A94: 92 | B94: B00XAMD2T6
... A102: 100 | B102: B07R2DDH32

Sheet Make-up1
A1: Amazon Best Sellers — Make-up | I1: 🔗 Best Sellers 페이지 열기
A2: rank | B2: asin | C2: title | D2: rating | E2: ratings_count | F2: price | G2: currency | H2: offers_text | I2: url
A3: 1 | B3: B08P4YPB8Q | C3: Maybelline New York Lash Sensational Sky High Volume and Length, Black | Flexible Brush, Limit Length, Redefined Volume, Defi | D3: 4.2 | E3: 36429 | F3: 9086 | G3: KRW | I3: https://www.amazon.com/-/en/Maybelline-York-Sensational-Length-Black/dp/B08P4YPB8Q/ref=zg_bs_g_6397823031_d_sccl_1/522-8505739-1189111
A4: 2 | B4: B08CFSS35N | C4: Rimmel London Lasting Finish Lip Liner, Lip Liner, Shade 700 - 1 g | D4: 4.4 | E4: 12280 | F4: 3859 | G4: KRW | I4: https://www.amazon.com/-/en/Rimmel-London-Lasting-Finish-Liner/dp/B08CFSS35N/ref=zg_bs_g_6397823031_d_sccl_2/522-8505739-1189111
A5: 3 | B5: B00KLXFUW4 | C5: Maybelline New York Instant Anti-Age Eye Concealer, 01 Light | Multi-purpose Concealer, Modulable Coverage, Enriched with Goj | D5: 4.5 | E5: 20171 | F5: 8539 | G5: KRW | I5: https://www.amazon.com/-/en/Maybelline-Instant-Anti-Age-Concealer-Light/dp/B00KLXFUW4/ref=zg_bs_g_6397823031_d_sccl_3/522-8505739-1189111
A6: 4 | B6: B0FGJ9P8L9 | C6: L'Oréal Paris XL Infaillible Makeup Setting Spray with 36h* Duration, Fixes Makeup Without Transferring for a Flawless Look. | D6: 4.5 | E6: 9038 | F6: 14827 | G6: KRW | I6: https://www.amazon.com/-/en/Paris-Infaillible-Transferring-Water-proof-Oil-proof/dp/B0FGJ9P8L9/ref=zg_bs_g_6397823031_d_sccl_4/522-8505739-1189111
A7: 5 | B7: B0FHBJXX9M | C7: Erborian - CC Crème con Centella Asiática - Crema Facial Iluminadora de Alta Definición y Maquillaje - Protección Solar SPF 3 | D7: 4.5 | E7: 3889 | F7: 30538 | G7: KRW | I7: https://www.amazon.com/-/en/Erborian-Definition-Illuminating-Protection-Cosmetics/dp/B0FHBJXX9M/ref=zg_bs_g_6397823031_d_sccl_5/522-8505739-1189111
A8: 6 | B8: B077N513Z1 | C8: Maybelline New York SuperStay Matte Ink Long Lasting 65 Seductres | Lipstick, Highly Pigmented Color, Liquid Matt, Vegan Form | D8: 4.6 | E8: 56513 | F8: 18461 | G8: KRW | I8: https://www.amazon.com/-/en/Maybelline-SuperStay-Matte-Lasting-Seductres/dp/B077N513Z1/ref=zg_bs_g_6397823031_d_sccl_6/522-8505739-1189111
A9: 7 | B9: B0CWS16Y87 | C9: MNY SUPER LOCK BROW GLUE | D9: 4.4 | E9: 2737 | F9: 7622 | G9: KRW | I9: https://www.amazon.com/-/en/MNY-SUPER-LOCK-BROW-GLUE/dp/B0CWS16Y87/ref=zg_bs_g_6397823031_d_sccl_7/522-8505739-1189111
A10: 8 | B10: B0CJ5GW8RY | C10: L'Oréal Paris Panorama Volumizing Mascara, Black | Panoramic Brush for 360º Volume, for All Types of Eyelashes, Up to 24 Hour | D10: 4.4 | E10: 9359 | F10: 12624 | G10: KRW | I10: https://www.amazon.com/-/en/LOr%C3%A9al-Paris-Panorama-Lashes-Mascara/dp/B0CJ5GW8RY/ref=zg_bs_g_6397823031_d_sccl_8/522-8505739-1189111
A11: 9 | B11: B0CQKG841Y | C11: essence COLOR CHANGING LIP BAR META GLOW Tint (0.1 oz) | Color Matching, All Skin Types, Tint Effect, Lipstick | D11: 3.6 | E11: 6166 | F11: 1399 | G11: KRW | I11: https://www.amazon.com/-/en/essence-COLOR-CHANGING-META-GLOW/dp/B0CQKG841Y/ref=zg_bs_g_6397823031_d_sccl_9/522-8505739-1189111
A12: 10 | B12: B097WL6QWT | C12: L'Oréal Paris Accord Parfait Color Serum, Light (2-3), 1 fl oz | Hyaluronic Acid*, Glycerin, Smoother, Brighter Skin, Natural | D12: 4.5 | E12: 8822 | F12: 16113 | G12: KRW | I12: https://www.amazon.com/-/en/LOr%C3%A9al-Paris-Accord-Parfait-Hyaluronic/dp/B097WL6QWT/ref=zg_bs_g_6397823031_d_sccl_10/522-8505739-1189111
A13: 11 | B13: B074Y8LM6T | C13: NYX Professional Makeup Epic Ink Liner Eyeliner, Brush Tip, Waterproof, Vegan Formula, Black | Pincel Flexible, Trazo Preciso | D13: 4.4 | E13: 89269 | F13: 8314 | G13: KRW | I13: https://www.amazon.com/-/en/NYX-Professional-Makeup-Liquid-Eyeliner/dp/B074Y8LM6T/ref=zg_bs_g_6397823031_d_sccl_11/522-8505739-1189111
A14: 12 | B14: B0BYH9D5X4 | C14: 3INA MAKEUP - The No-Rules Cream 503 - Nude Pink Blush with Almond Oil - 3-in-1 Liquid Blush Natural Finish Lips and Eyes Che | D14: 4.5 | E14: 647 | F14: 13219 | G14: KRW | I14: https://www.amazon.com/-/en/3INA-MAKEUP-No-Rules-3-1/dp/B0BYH9D5X4/ref=zg_bs_g_6397823031_d_sccl_12/522-8505739-1189111
... A32: 30 | B32: B07T5BN3P2 | C32: Madagascar Centella Light Cleansing Oil by SKIN1004 for Women - Cleanser 6.76 oz | D32: 4.6 | E32: 13273 | F32: 43419 | G32: KRW | I32: https://www.amazon.com/-/en/SKIN1004-Centella-Light-Cleansing-200ml/dp/B07T5BN3P2/ref=zg_bs_g_6397823031_d_sccl_30/522-8505739-1189111
A33: 31 | B33: B0B2RX1W2C
A34: 32 | B34: B0DPJR1N27
A35: 33 | B35: B00B4YVU4G
A36: 34 | B36: B077DKPXF7
A37: 35 | B37: B0B9YHX8DX
A38: 36 | B38: B08H2F2JQW
A39: 37 | B39: B0C78G8ZPR
A40: 38 | B40: B08TLSRWTW
A41: 39 | B41: B0BRXRRNZN
A42: 40 | B42: B015COG25K
A43: 41 | B43: B08HHFRLR1
A44: 42 | B44: B0F2T9495C
... A52: 50 | B52: B07QSVTVRD
A53: 51 | B53: B0C3VLC4KW | C53: KIKO Milano 3D Hydra Lipgloss - Shade 46 Marvellous Mauve | Moisturizing | 3D Volume Effect | Non-Sticky Texture | Flocking A | D53: 4.6 | E53: 4753 | F53: 10935 | G53: KRW | I53: https://www.amazon.com/-/en/KIKO-Milano-Hydra-Lipgloss-Marvellous/dp/B0C3VLC4KW/ref=zg_bs_g_6397823031_d_sccl_1/522-8505739-1189111
A54: 52 | B54: B0C7N36SRY | C54: Rimmel London, Lasting Finish, Foundation, 200 - Soft Beige, 30 ml | D54: 4.6 | E54: 1497 | F54: 5821 | G54: KRW | I54: https://www.amazon.com/-/en/Rimmel-London-Lasting-Finish-Foundation/dp/B0C7N36SRY/ref=zg_bs_g_6397823031_d_sccl_2/522-8505739-1189111
A55: 53 | B55: B00A3VMVGC | C55: Max Factor LipFinity Lip Colour Lipstick, Shade 330 Essential Burgundy - Step 1: 2 ml Step 2: 2 g | D55: 4.4 | E55: 7491 | F55: 24685 | G55: KRW | I55: https://www.amazon.com/-/en/Max-Factor-LipFinity-Lipstick-Essential/dp/B00A3VMVGC/ref=zg_bs_g_6397823031_d_sccl_3/522-8505739-1189111
A56: 54 | B56: B08522ZYXN | C56: L'Oreal Paris Make-up Designer Volume And Length Paradise Mascara, Extra Black, 5 ml (Pack of 1) | D56: 4.4 | E56: 6678 | F56: 15840 | G56: KRW | I56: https://www.amazon.com/-/en/LOreal-Paris-Make-up-Designer-Paradise/dp/B08522ZYXN/ref=zg_bs_g_6397823031_d_sccl_4/522-8505739-1189111
A57: 55 | B57: B0B56TC2G5 | C57: Essence WHAT A TINT! Long Lasting Lip & Cheek Dye (5ml) | Long Lasting, Light Coverage, Lipstick & Blush, Instant Result | D57: 4.2 | E57: 4646 | F57: 4390 | G57: KRW | I57: https://www.amazon.com/-/en/Essence-WHAT-TINT-Lasting-Cheek/dp/B0B56TC2G5/ref=zg_bs_g_6397823031_d_sccl_5/522-8505739-1189111
A58: 56 | B58: B0D2XQ4VDX | C58: NIVEA Skin Glow Bi-Phase Micellar Water – Facial Cleanser – With 5% Vitamin C and E Serum – Face and Lip Makeup Remover – Ene | D58: 4.4 | E58: 613 | F58: 5259 | G58: KRW | I58: https://www.amazon.com/-/en/NIVEA-Skin-Bi-Phase-Micellar-Water/dp/B0D2XQ4VDX/ref=zg_bs_g_6397823031_d_sccl_6/522-8505739-1189111
A59: 57 | B59: B0C37HPN5F | C59: Catrice Plumping Lip Liner 069 Mainhattan 0,35g | Hidratante, Acabado mate sedoso y de larga duración, Con aceite de menta, R | D59: 4.6 | E59: 1829 | F59: 3329 | G59: KRW | I59: https://www.amazon.com/-/en/Catrice-Plumping-Lip-Liner-Mainhattan/dp/B0C37HPN5F/ref=zg_bs_g_6397823031_d_sccl_7/522-8505739-1189111
A60: 58 | B60: B0CK4H9VLV | C60: KIKO Milano Everlasting Colour Precision Lip Liner - Shade 505 Gingerbread | Automatic Liner | Matte Finish | Integrated Penc | D60: 4.5 | E60: 1339 | F60: 13219 | G60: KRW | I60: https://www.amazon.com/-/en/Milano-Everlasting-Precision-Automatic-Contour/dp/B0CK4H9VLV/ref=zg_bs_g_6397823031_d_sccl_8/522-8505739-1189111
A61: 59 | B61: B08W6331DP | C61: HYPO Hypoallergenic Compact Powder Long Wear HYDRA with Hyaluronic Acid | D61: 4.3 | E61: 186 | F61: 5854 | G61: KRW | I61: https://www.amazon.com/-/en/Hypoallergenic-Compact-Powder-HYDRA-Hyaluronic/dp/B08W6331DP/ref=zg_bs_g_6397823031_d_sccl_9/522-8505739-1189111
A62: 60 | B62: B09HNMRQN2 | C62: NYX Professional Makeup Bare With Me Serum Corrector, Natural, Cobertura Media, Vainilla, 9,6ml | D62: 4.6 | E62: 15005 | F62: 11884 | G62: KRW | I62: https://www.amazon.com/-/en/NYX-Professional-Corrector-Cobertura-Vainilla/dp/B09HNMRQN2/ref=zg_bs_g_6397823031_d_sccl_10/522-8505739-1189111
A63: 61 | B63: B0D35YXWZ4 | C63: KIKO Milano Unlimited Double Touch - Shade 120 Rosy Mauve | Liquid Lipstick 2 Steps | Colour + Shine | Lasting 12 Hours | No | D63: 4.3 | E63: 8830 | F63: 14200 | G63: KRW | I63: https://www.amazon.com/-/en/KIKO-Milano-Unlimited-Double-Touch/dp/B0D35YXWZ4/ref=zg_bs_g_6397823031_d_sccl_11/522-8505739-1189111
A64: 62 | B64: B0G52CKKMT | C64: Maybelline New York, Lash Sensational Sky Tubes, Extreme Length Defined Eyelashes, Long Lasting and Resilient Formula, with S | D64: 4.4 | E64: 494 | F64: 17609 | G64: KRW | I64: https://www.amazon.com/-/en/Maybelline-Sensational-Extreme-Eyelashes-Resilient/dp/B0G52CKKMT/ref=zg_bs_g_6397823031_d_sccl_12/522-8505739-1189111
... A69: 67 | B69: B0BM3NPL6S | C69: FV High Coverage Matte Long Lasting Makeup Foundation, Flawless Makeup Base For Oily Skin, Beige, 1 fl oz | D69: 4.2 | E69: 3724 | F69: 9777 | G69: KRW | I69: https://www.amazon.com/-/en/Coverage-Lasting-Makeup-Foundation-Flawless/dp/B0BM3NPL6S/ref=zg_bs_g_6397823031_d_sccl_17/522-8505739-1189111
A70: 68 | B70: B01758LL70 | C70: Urban Decay Eyeshadow Primer Potion Primer Eye Original 10ml | D70: 4.3 | E70: 1140 | I70: https://www.amazon.com/-/en/Urban-Decay-Eyeshadow-Primer-Original/dp/B01758LL70/ref=zg_bs_g_6397823031_d_sccl_18/522-8505739-1189111
A71: 69 | B71: B007B8UNVA | C71: Maybelline New York Fit Me Concealer for Dark Circles and Blemishes, All Skin Types 15, Fair, 5 ml | D71: 4.5 | E71: 67329 | F71: 6625 | G71: KRW | I71: https://www.amazon.com/-/en/Maybelline-Concealer-Circles-Blemishes-Types/dp/B007B8UNVA/ref=zg_bs_g_6397823031_d_sccl_19/522-8505739-1189111
A72: 70 | B72: B0B8BS8T84 | C72: KIKO Milano Creamy Colour Comfort Lip Liner 05 | Long Lasting Lipstick | Lip Liner | Intense Color | Precise Contour | Waterp | D72: 4.2 | E72: 5989 | F72: 5982 | G72: KRW | I72: https://www.amazon.com/-/en/Milano-Creamy-Comfort-Lasting-Lipstick/dp/B0B8BS8T84/ref=zg_bs_g_6397823031_d_sccl_20/522-8505739-1189111
A73: 71 | B73: B0BXSZPYD9 | C73: L'Oréal Paris Infaillible Matte Resistance Liquid Lipstick, 420 True Romance | Ácido Hialurónico*, Acabado Mate, Hasta 16 Hor | D73: 4.5 | E73: 4960 | F73: 27772 | G73: KRW | I73: https://www.amazon.com/-/en/Paris-Infaillible-Resistance-Lipstick-Romance/dp/B0BXSZPYD9/ref=zg_bs_g_6397823031_d_sccl_21/522-8505739-1189111
A74: 72 | B74: B0D4QMXTM2 | C74: KIKO Milano Unlimited Precision Automatic Eyeliner And Khôl 16, Automatic Eyeliner For Internal And External Use | Línea de A | D74: 4.3 | E74: 2286 | F74: 10083 | G74: KRW | I74: https://www.amazon.com/-/en/Milano-Unlimited-Precision-Automatic-Eyeliner/dp/B0D4QMXTM2/ref=zg_bs_g_6397823031_d_sccl_22/522-8505739-1189111
A75: 73 | B75: B0931KVQJ3 | C75: Rimmel London Concealer Multistaker – Concealer Tone 050 Sand | D75: 4.3 | E75: 437 | F75: 8636 | G75: KRW | I75: https://www.amazon.com/-/en/Rimmel-London-Concealer-Multistaker-Tone/dp/B0931KVQJ3/ref=zg_bs_g_6397823031_d_sccl_23/522-8505739-1189111
A76: 74 | B76: B0DQ9HXJ2H | C76: Wet n Wild Chameleon Chrome Retractable Waterproof Eye Liner with Iridescent Pigments that Reflect Light Creating a Dynamic C | D76: 4.5 | E76: 2096 | F76: 7076 | G76: KRW | I76: https://www.amazon.com/-/en/Wet-Wild-Retractable-Waterproof-Iridescent/dp/B0DQ9HXJ2H/ref=zg_bs_g_6397823031_d_sccl_24/522-8505739-1189111
A77: 75 | B77: B0CV4CBHY5 | C77: Sensilis - Máscara Transparente Pestañas y Cejas, 12 ml | Niacinamida, Pantenol, Fortalece, Hidrata, Estimula el Crecimiento, | D77: 4 | E77: 167 | F77: 8201 | G77: KRW | I77: https://www.amazon.com/-/en/Sensilis-Transparent-Mascara-Eyelashes-Eyebrows/dp/B0CV4CBHY5/ref=zg_bs_g_6397823031_d_sccl_25/522-8505739-1189111
A78: 76 | B78: B09ZDC111L | C78: 3INA - The No - Rules Stick 385 - Bordeaux Stick Blush - 3 in 1 | with Hyaluronic Acid - 3 in 1 Cheek Lip & Eye Blush - Trave | D78: 4 | E78: 1846 | F78: 19153 | G78: KRW | I78: https://www.amazon.com/-/en/3INA-Rules-Stick-Bordeaux-Blush/dp/B09ZDC111L/ref=zg_bs_g_6397823031_d_sccl_26/522-8505739-1189111
A79: 77 | B79: B0797KPXMY | C79: UltimateBrow Retractable Pencil | D79: 4.3 | E79: 12406 | F79: 3586 | G79: KRW | I79: https://www.amazon.com/-/en/Wet-Wild-Retractable-Triangular-Precision/dp/B0797KPXMY/ref=zg_bs_g_6397823031_d_sccl_27/522-8505739-1189111
A80: 78 | B80: B06XGJJN66 | C80: MAYBELLINE Matte & Porous Powder, Shade 120 Classic Ivory, 0.32 Ounce (Pack of 1) | D80: 4.6 | E80: 1521 | F80: 8105 | G80: KRW | I80: https://www.amazon.com/-/en/MAYBELLINE-Matte-Porous-Powder-Classic/dp/B06XGJJN66/ref=zg_bs_g_6397823031_d_sccl_28/522-8505739-1189111
A81: 79 | B81: B0BLC7PGCG | C81: RB RENATA BEAUTY Eyebrow Tint Kit – Semi-Permanent Dye with Developer Cream 1.8% + Dual Brush – PPD and Ammonia Free – Lasts | D81: 4.1 | E81: 2129 | F81: 27000 | G81: KRW | I81: https://www.amazon.com/-/en/RB-RENATA-BEAUTY-Eyebrow-Tint/dp/B0BLC7PGCG/ref=zg_bs_g_6397823031_d_sccl_29/522-8505739-1189111
A82: 80 | B82: B006XD1UGG | C82: Rimmel London Lasting Finish Lipstick Tone 002 Candy - 18g | D82: 4.3 | E82: 35090 | F82: 4921 | G82: KRW | I82: https://www.amazon.com/-/en/Rimmel-London-Lasting-Finish-Lipstick/dp/B006XD1UGG/ref=zg_bs_g_6397823031_d_sccl_30/522-8505739-1189111
A83: 81 | B83: B07QFYHPV1
A84: 82 | B84: B0CQKGL28D
A85: 83 | B85: B0CHW7NS4T
A86: 84 | B86: B084GXC77H
A87: 85 | B87: B0DLQH4PK1
A88: 86 | B88: B0G2LZPJCB
A89: 87 | B89: B08XXQXXGL
A90: 88 | B90: B073WYXK64
A91: 89 | B91: B0BZSZ82D8
A92: 90 | B92: B07KGT94LB
A93: 91 | B93: B000W9FS2Y
A94: 92 | B94: B077DD3HPV
... A102: 100 | B102: B07TXJHYKB

Sheet Skin Care2
A1: Amazon Best Sellers — Skin Care | I1: 🔗 Best Sellers 페이지 열기
A2: rank | B2: asin | C2: title | D2: rating | E2: ratings_count | F2: price | G2: currency | H2: offers_text | I2: url
A3: 1 | B3: B0DBF65JYY | C3: medicube PDRN Pink Peptide Serum with Salmon DNA | Niacinamide Peptide Serum for Hydration and Firmer Looking Skin, Improves | D3: 4.7 | E3: 20864 | F3: 51460 | G3: KRW | I3: https://www.amazon.com/-/en/medicube-PDRN-Peptide-Serum-Salmon/dp/B0DBF65JYY/ref=zg_bs_g_6397934031_d_sccl_1/522-8505739-1189111
A4: 2 | B4: B09SZ5JX2Y | C4: d'alba Piedmont White Truffle Double Serum All-in-one Multi Balm | Vegan Skin Care, 3 in 1 Treatment, Wrinkle Balm, Korean Sk | D4: 4.4 | E4: 8571 | F4: 28930 | G4: KRW | I4: https://www.amazon.com/-/en/dalba-Piedmont-White-Truffle-Double/dp/B09SZ5JX2Y/ref=zg_bs_g_6397934031_d_sccl_2/522-8505739-1189111
A5: 3 | B5: B0DK4Y2YP3 | C5: celimax The Vita A Retinal Shot Tightening Booster, 15ml | 0.1% Retinal, 3% Matryxyl, High Potency Retinoid, Anti-Aging, Pore | D5: 4.4 | E5: 22008 | F5: 48083 | G5: KRW | I5: https://www.amazon.com/-/en/celimax-Enhancer-Minimizer-Wrinkles-Expression/dp/B0DK4Y2YP3/ref=zg_bs_g_6397934031_d_sccl_3/522-8505739-1189111
A6: 4 | B6: B0B2RM68G2 | C6: BIODANCE Bio-Collagen Real Deep Mask - Hydrating Night Mask, Minimizes Pores and Improves Elasticity - Deep Hydration Facial | D6: 4.5 | E6: 43295 | F6: 37919 | G6: KRW | I6: https://www.amazon.com/-/en/BIODANCE-Bio-Collagen-Real-Deep-Mask/dp/B0B2RM68G2/ref=zg_bs_g_6397934031_d_sccl_4/522-8505739-1189111
A7: 5 | B7: B0DTKCN3Z4 | C7: medicube Salmon DNA PDRN Capsule Cream 55g - Lightweight Moisturizer with PDRN and Niacinamide for uneven tone and luminous h | D7: 4.6 | E7: 25813 | F7: 50817 | G7: KRW | I7: https://www.amazon.com/-/en/medicube-Salmon-PDRN-Capsule-Cream/dp/B0DTKCN3Z4/ref=zg_bs_g_6397934031_d_sccl_5/522-8505739-1189111
A8: 6 | B8: B09V7Z4TJG | C8: medicube Toner Pads Zero Pore Pad 2.0 | Dual Texture Toning Pads for Exfoliation and Pores with AHA and BHA, All Skin Types, | D8: 4.8 | E8: 29956 | F8: 23848 | G8: KRW | I8: https://www.amazon.com/-/en/medicube-Toner-Pads-Zero-Pore/dp/B09V7Z4TJG/ref=zg_bs_g_6397934031_d_sccl_6/522-8505739-1189111
A9: 7 | B9: B0GD6R7CFJ | C9: BIODANCE Collagen Peptide Eye Patches, Anti-Wrinkle for Expression Lines and Bags, Eye Contour, Korean Skin Care (60 Pcs) | D9: 4.5 | E9: 3485 | F9: 24122 | G9: KRW | I9: https://www.amazon.com/-/en/BIODANCE-Collagen-Peptide-Anti-Wrinkle-Expression/dp/B0GD6R7CFJ/ref=zg_bs_g_6397934031_d_sccl_7/522-8505739-1189111
A10: 8 | B10: B0DGPSZVW3 | C10: medicube Collagen Jelly Cream | Facial Cream with Hydrolyzed Collagen, Hydration and Glow 24 Hours, Fuller and Firmer Skin, 5 | D10: 4.4 | E10: 35120 | F10: 40123 | G10: KRW | I10: https://www.amazon.com/-/en/medicube-8800256112227-Collagen-Jelly-Cream/dp/B0DGPSZVW3/ref=zg_bs_g_6397934031_d_sccl_8/522-8505739-1189111
A11: 9 | B11: B0DGTMR754 | C11: medicube Jelly Gel Mask with Salmon DNA PDRN Pink Collagen | Glass Skin Effect Night Face Mask, Hydration and Firming Effect, | D11: 4.6 | E11: 12281 | F11: 48163 | G11: KRW | I11: https://www.amazon.com/-/en/medicube-Jelly-Mask-Salmon-Collagen/dp/B0DGTMR754/ref=zg_bs_g_6397934031_d_sccl_9/522-8505739-1189111
A12: 10 | B12: B09D7QJP1M | C12: d'alba Waterfull SPF50+PA++++ Italian White Truffle, Tinted Sun Cream with Vegan UV Filters, Bright and Brightening Sun Lotio | D12: 4.4 | E12: 7663 | F12: 61028 | G12: KRW | I12: https://www.amazon.com/-/en/dalba-Waterfull-Italian-Brightening-Skincare/dp/B09D7QJP1M/ref=zg_bs_g_6397934031_d_sccl_10/522-8505739-1189111
A13: 11 | B13: B0BFQ9RD5B | C13: d'alba Piedmont Italian White Truffle First Spray Serum (100 ml) | Vegan Skincare, Moisturizing Face Mist, Multifunctional Sp | D13: 4.5 | E13: 33851 | F13: 50704 | G13: KRW | I13: https://www.amazon.com/-/en/dalba-Piedmont-Italian-White-Truffle/dp/B0BFQ9RD5B/ref=zg_bs_g_6397934031_d_sccl_11/522-8505739-1189111
A14: 12 | B14: B0BRMYHMS5 | C14: medicube Wrapping Mask Collagen Overnight Peel Off Facial Mask | Hydrates and Firms, Helps Improve Skin Firmness and Luminous | D14: 4.5 | E14: 23338 | F14: 39994 | G14: KRW | I14: https://www.amazon.com/-/en/medicube-Wrapping-Collagen-Overnight-Facial/dp/B0BRMYHMS5/ref=zg_bs_g_6397934031_d_sccl_12/522-8505739-1189111
... A20: 18 | B20: B01MF9YDQN | C20: Neutrogena, Hydro Boost Water Gel, Normal to Combination Skins, Long-Lasting Non-Oily Hydration, with Hyaluronic Acid and Tre | D20: 4.4 | E20: 5271 | F20: 11578 | G20: KRW | I20: https://www.amazon.com/-/en/Neutrogena-Combination-Long-Lasting-Hyaluronic-Dermatologists/dp/B01MF9YDQN/ref=zg_bs_g_6397934031_d_sccl_18/522-8505739-1189111
A21: 19 | B21: B0GCC2JV65 | C21: medicube NAD EGF Firming Serum for Face & Neck | Anti-Aging Serum with Peptides and Collagen, Reduces Signs of Aging, Improve | D21: 4.6 | E21: 1677 | I21: https://www.amazon.com/-/en/medicube-Firming-Serum-Face-Neck/dp/B0GCC2JV65/ref=zg_bs_g_6397934031_d_sccl_19/522-8505739-1189111
A22: 20 | B22: B07C5XYT19 | C22: CeraVe, Cerave Face Moisturizing Lotion, Night Moisturizer, 53 ml | Hydrates and helps restore the protective barrier of the | D22: 4.6 | E22: 18626 | F22: 19667 | G22: KRW | I22: https://www.amazon.com/-/en/CeraVe-Cerave-Moisturizing-Lotion-Moisturizer/dp/B07C5XYT19/ref=zg_bs_g_6397934031_d_sccl_20/522-8505739-1189111
A23: 21 | B23: B0B2912ZZ5 | C23: Iroha Nature - Pimple Patches with Salicylic Acid, Tea Tree & Centella | Tea Tree, Centella Asiatica, Facial Use, Combination | D23: 4.3 | E23: 2429 | F23: 6288 | G23: KRW | I23: https://www.amazon.com/-/en/Iroha-Nature-Patches-Salicylic-Centella/dp/B0B2912ZZ5/ref=zg_bs_g_6397934031_d_sccl_21/522-8505739-1189111
A24: 22 | B24: B01MDOJGDK | C24: Neutrogena Hydro Boost Water Gel Facial Cleanser, 200 ml | With Hyaluronic Acid and Glycerin, Moisturizing, Non-Comedogenic, | D24: 4.6 | E24: 15243 | F24: 8700 | G24: KRW | I24: https://www.amazon.com/-/en/Neutrogena-Hydro-Boost-Facial-Cleanser/dp/B01MDOJGDK/ref=zg_bs_g_6397934031_d_sccl_22/522-8505739-1189111
A25: 23 | B25: B0FHBJXX9M | C25: Erborian - CC Crème con Centella Asiática - Crema Facial Iluminadora de Alta Definición y Maquillaje - Protección Solar SPF 3 | D25: 4.5 | E25: 3889 | F25: 30538 | G25: KRW | I25: https://www.amazon.com/-/en/Erborian-Definition-Illuminating-Protection-Cosmetics/dp/B0FHBJXX9M/ref=zg_bs_g_6397934031_d_sccl_23/522-8505739-1189111
A26: 24 | B26: B0DVLG7GD1 | C26: CeraVe Gel Limpiador Espumoso, Para Piel Normal a Grasa, Elimina el Exceso de Grasa y Suciedad, Enriquecido Con Ceramidas Ese | D26: 4.7 | E26: 44958 | F26: 14956 | G26: KRW | I26: https://www.amazon.com/-/en/CeraVe-Foaming-Cleansing-Removes-Excess/dp/B0DVLG7GD1/ref=zg_bs_g_6397934031_d_sccl_24/522-8505739-1189111
A27: 25 | B27: B0DYV2YCG8 | C27: Biodance Vita Niacinamide Gel Toner Pads – Toner Discs for Dark Spots and Uniform Tone – Soft Exfoliating Pads with Vitamin C | D27: 4.4 | E27: 336 | F27: 57844 | G27: KRW | I27: https://www.amazon.com/-/en/Biodance-Vita-Niacinamide-Toner-Pads/dp/B0DYV2YCG8/ref=zg_bs_g_6397934031_d_sccl_25/522-8505739-1189111
A28: 26 | B28: B07PK2P2XB | C28: Dr.Althea 345 Relief Cream | Face Moisturizer for Soothing Recovery and Blemish Care with PDRN & Niacinamide | Korean Vegan S | D28: 4.6 | E28: 20492 | F28: 48742 | G28: KRW | I28: https://www.amazon.com/-/en/Dr-Althea-Moisturizer-Soothing-Niacinamide-Unscented/dp/B07PK2P2XB/ref=zg_bs_g_6397934031_d_sccl_26/522-8505739-1189111
A29: 27 | B29: B0DQCLFJCB | C29: medicube Exosome Shot PDRN Pink Collagen 7,500 PPM Spicule Facial Serum | Liquid Booster with Exosomes & Salmon DNA Spicules, | D29: 4.6 | E29: 8162 | F29: 55641 | G29: KRW | I29: https://www.amazon.com/-/en/medicube-Exosome-Collagen-Spicule-Facial/dp/B0DQCLFJCB/ref=zg_bs_g_6397934031_d_sccl_27/522-8505739-1189111
A30: 28 | B30: B09NN88V83 | C30: d'alba Piedmont Italian White Truffle Double Serum and Cream (70g) | Vegan Cream, 2 in 1 Care, Elasticity and Nutrition, For | D30: 4.5 | E30: 5417 | F30: 51379 | G30: KRW | I30: https://www.amazon.com/-/en/dalba-Piedmont-Italian-Truffle-Double/dp/B09NN88V83/ref=zg_bs_g_6397934031_d_sccl_28/522-8505739-1189111
A31: 29 | B31: B06XDS7J69 | C31: L'Oréal Paris Revitalift Laser Cream SPF25 Nº1 Anti-Aging and Anti-Stain | Pro Retinol, Hyaluronic Acid and Vitamin Cg, Helps | D31: 4.5 | E31: 5487 | F31: 17979 | G31: KRW | I31: https://www.amazon.com/-/en/Paris-Revitalift-Anti-Aging-Protection-Pro-Retinol/dp/B06XDS7J69/ref=zg_bs_g_6397934031_d_sccl_29/522-8505739-1189111
A32: 30 | B32: B0GF86QJK7 | C32: BIODANCE Jelly Serum Mist with Collagen Peptides, Moisturizing Facial Mist, Volumizing Effect and Anti-Aging, Hydrogel Spray, | D32: 4.4 | E32: 3361 | F32: 24122 | G32: KRW | I32: https://www.amazon.com/-/en/BIODANCE-Moisturizing-Volumizing-Anti-Aging-Essential/dp/B0GF86QJK7/ref=zg_bs_g_6397934031_d_sccl_30/522-8505739-1189111
A33: 31 | B33: B002SSDHUW
A34: 32 | B34: B0GHMZXX8Y
A35: 33 | B35: B08B21PRLM
A36: 34 | B36: B0BPXT3GBN
A37: 35 | B37: B01BHPM36K
A38: 36 | B38: B0D1G7XF9X
A39: 37 | B39: B0CGJLC8G9
A40: 38 | B40: B07BYMJMJZ
A41: 39 | B41: B09XN22JBT
A42: 40 | B42: B07C5XD33D
A43: 41 | B43: B01MYEZPC8
A44: 42 | B44: B09BD7L35V
... A52: 50 | B52: B003JSEGNC
A53: 51 | B53: B0B2R7P7MB | C53: [Mizon] 50ml Korean Skincare Marine Collagen Enriched Cream 54% Marine Collagen Intensive Care Anti-Aging Fine Lines | D53: 4.4 | E53: 1869 | F53: 47295 | G53: KRW | I53: https://www.amazon.com/-/en/Skincare-Collagen-Enriched-Intensive-Anti-Aging/dp/B0B2R7P7MB/ref=zg_bs_g_6397934031_d_sccl_1/522-8505739-1189111
A54: 52 | B54: B00Z72U6JQ | C54: ISDIN Fotoprotección Fusion Water MAGIC SPF 50, Protector Solar Facial de Textura Ligera y Fase Externa Acuosa con Tacto Fina | D54: 4.7 | E54: 10878 | F54: 31262 | G54: KRW | I54: https://www.amazon.com/-/en/ISDIN-Fotoprotector-Facial-Fusion-SPF50-50ml/dp/B00Z72U6JQ/ref=zg_bs_g_6397934031_d_sccl_2/522-8505739-1189111
A55: 53 | B55: B0D9NL89YN | C55: Neutrogena Hydro Boost Hydrating Fluid SPF 50, Face Sun Cream, 50 ml | With Hyaluronic Acid and Niacinamide, Fragrance Free, | D55: 4.5 | E55: 1063 | F55: 13894 | G55: KRW | I55: https://www.amazon.com/-/en/Neutrogena-Hydro-Boost-Hydrating-Fluid/dp/B0D9NL89YN/ref=zg_bs_g_6397934031_d_sccl_3/522-8505739-1189111
A56: 54 | B56: B097WL6QWT | C56: L'Oréal Paris Accord Parfait Color Serum, Light (2-3), 1 fl oz | Hyaluronic Acid*, Glycerin, Smoother, Brighter Skin, Natural | D56: 4.5 | E56: 8822 | F56: 16113 | G56: KRW | I56: https://www.amazon.com/-/en/LOr%C3%A9al-Paris-Accord-Parfait-Hyaluronic/dp/B097WL6QWT/ref=zg_bs_g_6397934031_d_sccl_4/522-8505739-1189111
A57: 55 | B57: B09N6Z61GL | C57: The Ordinary Caffeine Solution 5% + EGCG, Caffeine Eye Serum, Decongestant Serum for Dark Circles and Tired Eyes, 30 ml | D57: 4.4 | E57: 3271 | F57: 14312 | G57: KRW | I57: https://www.amazon.com/-/en/Ordinary-Caffeine-Solution-Decongestant-Circles/dp/B09N6Z61GL/ref=zg_bs_g_6397934031_d_sccl_5/522-8505739-1189111
A58: 56 | B58: B082WHLTXF | C58: MASDERM - Radiofrequency Firming Moisturizing Body Gel and Cream 1000ml, Professional for Women, Cavitation and Ultrasound wi | D58: 4.4 | E58: 1890 | F58: 48228 | G58: KRW | I58: https://www.amazon.com/-/en/MASDERM-Radiofrequency-Moisturizing-Professional-Cavitation/dp/B082WHLTXF/ref=zg_bs_g_6397934031_d_sccl_6/522-8505739-1189111
A59: 57 | B59: B07C5T3DKW | C59: CeraVe Crema regeneradora de ojos, reduce las ojeras y la hinchazón, con 3 ceramidas esenciales y hialuron, 14 ml | Reduce vi | D59: 4.4 | E59: 45317 | F59: 17721 | G59: KRW | I59: https://www.amazon.com/-/en/CeraVe-regeneradora-hinchaz%C3%B3n-ceramidas-esenciales/dp/B07C5T3DKW/ref=zg_bs_g_6397934031_d_sccl_7/522-8505739-1189111
A60: 58 | B60: B0GS97T2MV | C60: celimax The Vita-A Retinal Shot Tightening Dual Cream 50ml | 0.05% Retinal, 3% Matryxyl, 5% Panthenol, High Potency Retinoid, | D60: 4.2 | E60: 249 | F60: 36183 | G60: KRW | I60: https://www.amazon.com/-/en/celimax-Vita-Retinal-Tightening-Cream/dp/B0GS97T2MV/ref=zg_bs_g_6397934031_d_sccl_8/522-8505739-1189111
A61: 59 | B61: B0DQLMXW1C | C61: Mixa Niacinamide Bright Anti-Blemish Body Cream for Off Skin, 400 ml | 9% Shea Butter, Niacinamide and Vitamin Cg, Anti-Dark | D61: 4.5 | E61: 2242 | F61: 9279 | G61: KRW | I61: https://www.amazon.com/-/en/Mixa-Niacinamide-Bright-Anti-Blemish-Cream/dp/B0DQLMXW1C/ref=zg_bs_g_6397934031_d_sccl_9/522-8505739-1189111
A62: 60 | B62: B0FQV2J48Q | C62: celimax The Vita A Retinal Shot Tightening Booster (Duo Set 0.51 fl.oz x 2) | 0.1% Retinal, 3% Matryxyl, High Potency Retinoi | D62: 4.5 | E62: 951 | F62: 43419 | G62: KRW | I62: https://www.amazon.com/-/en/celimax-Retinal-Tightening-Booster-fl-oz/dp/B0FQV2J48Q/ref=zg_bs_g_6397934031_d_sccl_10/522-8505739-1189111
A63: 61 | B63: B0G6KDLWKQ | C63: Garnier Vitamin C Fresh & Bright Sherbet Moisturizing Anti-Stain Cream - 4% [Niacinamide + Vitamin C*] - Cruelty Free Interna | D63: 4.2 | E63: 128 | F63: 4937 | G63: KRW | I63: https://www.amazon.com/-/en/Garnier-Vitamin-Sherbet-Moisturizing-Anti-Stain/dp/B0G6KDLWKQ/ref=zg_bs_g_6397934031_d_sccl_11/522-8505739-1189111
A64: 62 | B64: B08RXKBRR4 | C64: Beauty of Joseon - SPF 50+ sunscreen with rice extracts, sunscreen with rice probiotics | D64: 4.7 | E64: 6667 | F64: 48083 | G64: KRW | I64: https://www.amazon.com/-/en/Beauty-Joseon-sunscreen-extracts-probiotics/dp/B08RXKBRR4/ref=zg_bs_g_6397934031_d_sccl_12/522-8505739-1189111
... A82: 80 | B82: B0GT991JW7 | C82: BIODANCE Invisible SPF 50+ Solar Serum with Collagen and Peptides, Lightweight Facial Sunscreen, Glow Effect, Moisturizing an | D82: 4.6 | E82: 106 | F82: 20906 | G82: KRW | I82: https://www.amazon.com/-/en/BIODANCE-Invisible-Lightweight-Sunscreen-Moisturizing/dp/B0GT991JW7/ref=zg_bs_g_6397934031_d_sccl_30/522-8505739-1189111
A83: 81 | B83: B0DL92QM79
A84: 82 | B84: B07B9KD2JF
A85: 83 | B85: B09WDRFSLN
A86: 84 | B86: B07HMGVSWQ
A87: 85 | B87: B003Q3FPR6
A88: 86 | B88: B0FPCC599C
A89: 87 | B89: B0D3F5JXGR
A90: 88 | B90: B07Z9Y4M3C
A91: 89 | B91: B0D45LZBML
A92: 90 | B92: B08TTP8589
A93: 91 | B93: B0FVT77ZLL
A94: 92 | B94: B0FBS9W7Z2
... A102: 100 | B102: B0BQ3ZX2VV

Sheet Fragrances2
A1: Amazon Best Sellers — Fragrances | I1: 🔗 Best Sellers 페이지 열기
A2: rank | B2: asin | C2: title | D2: rating | E2: ratings_count | F2: price | G2: currency | H2: offers_text | I2: url
A3: 1 | B3: B0DHSS4ZW3 | C3: BIOLANE - Baby Eau de Toilette - Soft & Fresh - Unisex - 200 ml | Alcohol-free, delicately perfumed, sensitive skin, 98% natu | D3: 4.7 | E3: 1686 | F3: 43403 | G3: KRW | I3: https://www.amazon.com/-/en/BIOLANE-Baby-Toilette-Fresh-Unisex/dp/B0DHSS4ZW3/ref=zg_bs_g_210965031_d_sccl_1/522-7811629-0444522
A4: 2 | B4: B0DXTLWVBL | C4: GRIFEMA 200ml white fine mist water spray | Reusable Spray for Hair, Face, Plants and Personal Care | D4: 4.1 | E4: 2556 | F4: 8700 | G4: KRW | I4: https://www.amazon.com/GRIFEMA-200ml-white-water-spray/dp/B0DXTLWVBL/ref=zg_bs_g_210965031_d_sccl_2/522-7811629-0444522
A5: 3 | B5: B07YQFYKQH | C5: NIVEA MEN Sensitive - After Shave Balm for Sensitive Skin - 100 ml | 24H Hydration Soothes & Protects From 5 Signs of Skin Ir | D5: 4.6 | E5: 2841 | F5: 5500 | G5: KRW | I5: https://www.amazon.com/-/en/NIVEA-MEN-Sensitive-After-Shave/dp/B07YQFYKQH/ref=zg_bs_g_210965031_d_sccl_3/522-7811629-0444522
A6: 4 | B6: B001BKK3LO | C6: Giorgio Beverly Hills, Eau de Toilette for Women, Floral Scent, Spray Spray, Vanilla, Jasmine and Bergamot, Natural Ingredien | D6: 4.4 | E6: 15461 | F6: 44223 | G6: KRW | I6: https://www.amazon.com/-/en/Giorgio-Beverly-Toilette-Bergamot-Ingredients/dp/B001BKK3LO/ref=zg_bs_g_210965031_d_sccl_4/522-7811629-0444522
A7: 5 | B7: B0CZXXRWQC | C7: Corine de Farme Women's Eau Parfumed Tiare Monoï Care Mist 150 ml | D7: 4.4 | E7: 1048 | F7: 6690 | G7: KRW | I7: https://www.amazon.com/-/en/Corine-Farme-Womens-Parfumed-Tiare/dp/B0CZXXRWQC/ref=zg_bs_g_210965031_d_sccl_5/522-7811629-0444522
A8: 6 | B8: B003XJBWDY | C8: JEANNE ARTHES - Eau de Parfum for Women Amore Mio - Floral & Fresh - Tonka Bean, White Musk - Made in France À Grasse - Gift | D8: 4.3 | E8: 3156 | F8: 25875 | G8: KRW | I8: https://www.amazon.com/-/en/JEANNE-ARTHES-Parfum-Floral-France/dp/B003XJBWDY/ref=zg_bs_g_210965031_d_sccl_6/522-7811629-0444522
A9: 7 | B9: B088WCR8M3 | C9: Azzaro Sport Eau de Toilette - Men's Fragrance Fresh and Pure - Citrus, Aromatic & Woody Fragrance - For Casual Everyday Wear | D9: 4.5 | E9: 4088 | F9: 45269 | G9: KRW | I9: https://www.amazon.com/-/en/Azzaro-Sport-Eau-Toilette-Fragrance/dp/B088WCR8M3/ref=zg_bs_g_210965031_d_sccl_7/522-7811629-0444522
A10: 8 | B10: B000C213ZM | C10: Drakkar Noir de Guy Laroche - Eau de Toilette Sensuel & Intrépide - Boisé et Aromatique, Notes de Mousse de Chêne, Patchouli | D10: 4.5 | E10: 30602 | F10: 59163 | G10: KRW | I10: https://www.amazon.com/-/en/Drakkar-Guy-Laroche-Fearless-Toilette/dp/B000C213ZM/ref=zg_bs_g_210965031_d_sccl_8/522-7811629-0444522
A11: 9 | B11: B01AY5UDU2 | C11: Giorgio Beverly Hills Perfume Mist Women Floral Spray Spray 8 fl oz | Floral mist with a marked trail mixing orange blossom, | D11: 4.3 | E11: 3278 | F11: 10983 | G11: KRW | I11: https://www.amazon.com/-/en/Giorgio-Beverly-Hills-Perfume-Floral/dp/B01AY5UDU2/ref=zg_bs_g_210965031_d_sccl_9/522-7811629-0444522
A12: 10 | B12: B0FR46YJJM | C12: 4 x 20 ml Small Spray Bottle Transparent Spray Bottles Set of Portable Travel Bottles Cosmetic Sprayers for Perfumes Oils Alc | D12: 4.3 | E12: 142 | F12: 7703 | G12: KRW | I12: https://www.amazon.com/-/en/Transparent-Portable-Cosmetic-Sprayers-Perfumes/dp/B0FR46YJJM/ref=zg_bs_g_210965031_d_sccl_10/522-7811629-0444522
A13: 11 | B13: B00017XGDU | C13: Azzaro Chrome, Eau de Toilette for Men | D13: 4.8 | E13: 12345 | I13: https://www.amazon.com/-/en/Azzaro-Toilette-Aquatic-Intense-Freshness/dp/B00017XGDU/ref=zg_bs_g_210965031_d_sccl_11/522-7811629-0444522
A14: 12 | B14: B000JLAWIA | C14: MUGLER A*MEN Men's Eau de Toilette Refillable Fragrance Oriental Woody Gourmand Male Fragrance | D14: 4.6 | E14: 2851 | F14: 76225 | G14: KRW | I14: https://www.amazon.com/-/en/Mugler-Toilette-Amber-Gourmet-Refillable/dp/B000JLAWIA/ref=zg_bs_g_210965031_d_sccl_12/522-7811629-0444522
A15: 13 | B15: B002QQN37S | C15: Tiger Balm® Tiger Balm® White Balm, Cold Effect, After Exercise, 19 g | D15: 4.7 | E15: 753 | F15: 12029 | G15: KRW | I15: https://www.amazon.com/-/en/Tiger-Balm%C2%AE-Balm-Effect-Exercise/dp/B002QQN37S/ref=zg_bs_g_210965031_d_sccl_13/522-7811629-0444522
A16: 14 | B16: B00IOEEOCE | C16: DIESEL Only The Brave - Eau De Toilette Homme - Boisé Ambré - Citron Frais, Ambre & Accord de Cuir - Tenue Longue Durée - Spr | D16: 4.7 | E16: 15723 | F16: 43853 | G16: KRW | I16: https://www.amazon.com/-/en/Diesel-Brave-Toilette-Spray-Fragrance/dp/B00IOEEOCE/ref=zg_bs_g_210965031_d_sccl_14/522-7811629-0444522
A17: 15 | B17: B003JSEG4Q | C17: AZZARO Wanted - Eau De Toilette Homme - Boisé Agrume Épicé - Cardamome, Vétiver & Citron - Tenue Longue Durée - Spray Vaporis | D17: 4.6 | E17: 6570 | I17: https://www.amazon.com/-/en/Azzaro-Wanted-Toilette-Citrus-Elegant/dp/B003JSEG4Q/ref=zg_bs_g_210965031_d_sccl_15/522-7811629-0444522
A18: 16 | B18: B08ZFKB8ZK | C18: AZZARO The Most Wanted Intense Eau De Parfum for Men - Woody Amber Fern - Cardamom, Fondant Caramel & Amber Wood - Long-Lasti | D18: 4.6 | E18: 13566 | I18: https://www.amazon.com/-/en/AZZARO-Most-Wanted-Intense-Parfum/dp/B08ZFKB8ZK/ref=zg_bs_g_210965031_d_sccl_16/522-7811629-0444522
A19: 17 | B19: B0BYSCSPLM | C19: ULRIC DE VARENS - Varens Sweet Vanilla Caramel Eau de Parfum - Gourmand, Caramel, Vanilla - Women's perfume - Spray - Made in | D19: 4.3 | E19: 910 | F19: 46619 | G19: KRW | I19: https://www.amazon.com/-/en/ULRIC-VARENS-Vanilla-Caramel-Gourmand/dp/B0BYSCSPLM/ref=zg_bs_g_210965031_d_sccl_17/522-7811629-0444522
